Workbook

Sheet 字段
B2: 拍卖数据 | D2: 抵质押物台账
B4: 资产所有人 | D4: 序号
B5: 竞拍人 | D5: 资产编号
B6: 证件号码 | D6: 是否终极处置
B7: 拍品名称 | D7: 债务人名称
B8: 省 | D8: 行业
B9: 市 | D9: 债权本金余额（万元）
B10: 县/区 | D10: 债权利息余额（万元）
B11: 地址 | D11: 代垫费用余额（万元）
B12: 拍卖轮次 | D12: 孳息余额（万元）
B13: 成交状态 | D13: 资产原值余额合计（万元）
B14: 类型 | D14: 担保形式
... B41: 源网站链接 | D41: 法定优先受偿权情况
D42: 法定优先受偿权金额（万元）
D43: 其他说明
D44: 管户经理
D45: 分公司
D46: 所属项目
D47: 所属项目名称
D48: 投放日期
D49: 是否需要补录数据
D50: 剔除重复押品逻辑
D51: 考虑优先受偿和顺位剔除重复押品

Sheet 拍卖数据
A1: 新报表
A3: 资产所有人 | B3: 竞拍人 | C3: 证件号码 | D3: 拍品名称 | E3: 省 | F3: 市 | G3: 县/区 | H3: 地址 | I3: 拍卖轮次 | J3: 成交状态 | K3: 类型 | L3: 起拍价格（单位：元） | M3: 评估价（单位：元） | N3: 成交价 | O3: 房产类型 | P3: 建筑面积(单位:平方米) | Q3: 土地面积(单位:平方米) | R3: 是否腾空 | S3: 共有情况 | T3: 是否瑕疵 | U3: 朝向 | V3: 户型 | W3: 是否租赁 | X3: 装修程度 | Y3: 土地用途 | Z3: 总楼层 | AA3: 所在楼层 | AB3: 是否查封 | AC3: 使用权终止日期 | AD3: 权利来源 | AE3: 建成年代 | AF3: 房屋结构 | AG3: 债权本金（单位：元） | AH3: 未尝利息（单位：元） | AI3: 债权总额（单位：元） | AJ3: 担保方式 | AK3: 拍卖结束时间 | AL3: 源网站链接 | AM3: 竞拍人长度 | AN3: 机构/个人
B4: 孙艳红 | D4: 合肥市庐阳区临泉路7366号橡树湾7幢2404室 | E4: 安徽省 | F4: 合肥市 | G4: 庐阳区 | H4: 安徽省合肥市庐阳区临泉路7366号橡树湾7幢2404室 | I4: 变卖 | J4: 成交 | K4: 房产 | L4: 2446393 | M4: 3197900 | N4: 2446393 | O4: 居住用房 | P4: 130.09 | Q4: 0 | T4: 是 | W4: 未知 | Y4: 住宅 | Z4: 35 | AA4: 24 | AB4: 是 | AE4: 2013 | AF4: 钢混结构 | AK4: 45597.805 | AL4: https://zc-item.taobao.com/auction/824704626523.htm | AM4: =LEN(B4) -> 3 | AN4: 个人
B5: 王友勤 | D5: 安庆市迎江区华中西路98-124#2单元604室（实勘为192号1号楼）房产 | E5: 安徽省 | F5: 安庆市 | G5: 迎江区 | H5: 安徽省安庆市迎江区华中西路98-124#2单元604室（实勘为192号1号楼） | I5: 变卖 | J5: 成交 | K5: 房产 | L5: 310856 | M5: 555100 | N5: 310856 | O5: 居住用房 | P5: 93.06 | Q5: 0 | T5: 是 | U5: 南北 | W5: 否 | X5: 精装，外墙真石漆，钢制入户门，铝合金窗；室内地面地砖（卧室木地板），墙面乳胶漆和墙布、石膏板吊顶、设备较齐全（定制橱柜、燃气灶、浴霸、马桶、淋雨、置物架） | Y5: 住宅 | Z5: 6 | AA5: 6 | AB5: 未知 | AF5: 混合结构 | AK5: 45603.341 | AL5: https://zc-item.taobao.com/auction/827369118883.htm | AM5: =LEN(B5) -> 3 | AN5: 个人
B6: 余泉 | C6: ****0213 | D6: 安徽省颍上县慎城镇城北新区颍阳路北侧荐贤路西侧在水一方11#楼2-403号 | E6: 安徽省 | F6: 阜阳市 | G6: 颍上县 | H6: 安徽省阜阳市颍上县慎城镇城北新区颍阳路北侧荐贤路西侧在水一方11#楼2-403号 | I6: 变卖 | J6: 成交 | K6: 房产 | L6: 354304 | M6: 553600 | N6: 354304 | O6: 居住用房 | P6: 118.26 | Q6: 0 | T6: 未知 | W6: 未知 | Y6: 成套住宅 | Z6: 6 | AA6: 4 | AB6: 是 | AD6: 不动产权证书号：99053760 | AK6: 45606.481 | AL6: http://paimai.jd.com/307426302 | AM6: =LEN(B6) -> 2 | AN6: 个人
B7: 朱佳琳 | D7: 芜湖市弋江区金玺商业广场裙楼B202室房产 | E7: 安徽省 | F7: 芜湖市 | G7: 弋江区 | H7: 安徽省芜湖市弋江区金玺商业广场裙楼B202室房产 | I7: 变卖 | J7: 成交 | K7: 房产 | L7: 2826571 | M7: 5047447 | N7: 2826571 | O7: 商业用房 | P7: 835.67 | Q7: 0 | T7: 未知 | W7: 未知 | Z7: 21 | AA7: 2 | AB7: 是 | AF7: 钢混结构 | AK7: 45616.419 | AL7: https://zc-item.taobao.com/auction/833128405681.htm | AM7: =LEN(B7) -> 3 | AN7: 个人
B8: 徐婉豪 | D8: 太和县城关镇侯沟南侧、椿樱大道东侧、解放西路北侧西城首府B2号楼102户 | E8: 安徽省 | F8: 阜阳市 | G8: 太和县 | H8: 安徽省阜阳市太和县城关镇侯沟南侧、椿樱大道东侧、解放西路北侧西城首府B2号楼102户 | I8: 变卖 | J8: 成交 | K8: 房产 | L8: 767686 | M8: 950695 | N8: 849686 | O8: 居住用房 | P8: 136.83 | Q8: 0 | S8: 共同共有 | T8: 未知 | W8: 否 | Y8: 住宅 | Z8: 31 | AA8: 1 | AB8: 是 | AF8: 混合结构 | AK8: 45603.549 | AL8: https://zc-item.taobao.com/auction/833884836836.htm | AM8: =LEN(B8) -> 3 | AN8: 个人
B9: 戚雪莲 | D9: 合肥市长丰县双凤开发区蒙城北路与梅登路交口御景嘉苑15幢901室 | E9: 安徽省 | F9: 合肥市 | G9: 长丰县 | H9: 安徽省合肥市长丰县合肥市长丰县双凤开发区蒙城北路与梅登路交口御景嘉苑15幢901室 | I9: 变卖 | J9: 成交 | K9: 房产 | L9: 830674 | M9: 1297927 | N9: 830674 | O9: 居住用房 | P9: 117.58 | Q9: 0 | T9: 是 | W9: 否 | Y9: 住宅 | Z9: 28 | AA9: 9 | AB9: 是 | AC9: 2083-5-1 | AE9: 2016-10-17 | AK9: 45597.375 | AL9: https://zc-item.taobao.com/auction/834507454051.htm | AM9: =LEN(B9) -> 3 | AN9: 个人
B10: 李仕保 | D10: 安徽省六安市霍邱县城关镇锦绣·壹号院3幢3201室 | E10: 安徽省 | F10: 六安市 | G10: 霍邱县 | H10: 安徽省六安市霍邱县城关镇锦绣·壹号院3幢3201室 | I10: 变卖 | J10: 成交 | K10: 房产 | L10: 488608 | M10: 642906 | N10: 488608 | O10: 居住用房 | P10: 122.21 | Q10: 0 | T10: 未知 | W10: 未知 | Z10: 0 | AA10: 0 | AB10: 是 | AF10: 钢混结构 | AK10: 45601.397 | AL10: https://zc-item.taobao.com/auction/826758013487.htm | AM10: =LEN(B10) -> 3 | AN10: 个人
B11: 吴梅芳 | D11: 旌德县白地镇金玉苑小区6幢503室住宅房地产 | E11: 安徽省 | F11: 宣城市 | G11: 旌德县 | H11: 安徽省宣城市旌德县白地镇金玉苑小区6幢503室住宅房地产 | I11: 变卖 | J11: 成交 | K11: 房产 | L11: 213960 | M11: 370864 | N11: 213960 | O11: 居住用房 | P11: 142.64 | Q11: 0 | T11: 未知 | W11: 否 | Y11: 住宅 | Z11: 6 | AA11: 5 | AB11: 是 | AD11: 司法裁定 | AK11: 45619.668 | AL11: https://zc-item.taobao.com/auction/833431254001.htm | AM11: =LEN(B11) -> 3 | AN11: 个人
B12: 吴梅芳 | D12: 旌德县白地镇金玉苑小区6幢602室住宅房地产 | E12: 安徽省 | F12: 宣城市 | G12: 旌德县 | H12: 安徽省宣城市旌德县白地镇金玉苑小区6幢602室住宅房地产 | I12: 变卖 | J12: 成交 | K12: 房产 | L12: 166665 | M12: 277775 | N12: 166665 | O12: 居住用房 | P12: 111.11 | Q12: 0 | T12: 未知 | W12: 否 | Y12: 住宅 | Z12: 6 | AA12: 6 | AB12: 是 | AD12: 司法裁定 | AK12: 45619.675 | AL12: https://zc-item.taobao.com/auction/833433406170.htm | AM12: =LEN(B12) -> 3 | AN12: 个人
B13: 余杨 | D13: 泾县泾川镇环城南路秀江南8幢2-601室 | E13: 安徽省 | F13: 宣城市 | G13: 泾县 | H13: 安徽省宣城市泾县泾川镇环城南路秀江南8幢2-601室 | I13: 变卖 | J13: 成交 | K13: 房产 | L13: 341000 | M13: 607800 | N13: 341000 | O13: 居住用房 | P13: 119.1 | Q13: 0 | T13: 未知 | W13: 未知 | Y13: 住宅 | Z13: 6 | AA13: 6 | AB13: 是 | AE13: 2007 | AF13: 混合结构 | AK13: 45617.443 | AL13: https://zc-item.taobao.com/auction/833433358068.htm | AM13: =LEN(B13) -> 2 | AN13: 个人
B14: 吴梅芳 | D14: 旌德县白地镇金玉苑小区12幢501室住宅房地产 | E14: 安徽省 | F14: 宣城市 | G14: 旌德县 | H14: 安徽省宣城市旌德县白地镇金玉苑小区12幢501室住宅房地产 | I14: 变卖 | J14: 成交 | K14: 房产 | L14: 204885 | M14: 341475 | N14: 204885 | O14: 居住用房 | P14: 136.59 | Q14: 0 | T14: 未知 | W14: 否 | Y14: 住宅 | Z14: 5 | AA14: 4 | AB14: 是 | AD14: 司法裁定 | AK14: 45619.674 | AL14: https://zc-item.taobao.com/auction/833424382597.htm | AM14: =LEN(B14) -> 3 | AN14: 个人
B15: 吴梅芳 | D15: 旌德县白地镇金玉苑小区12幢505室住宅房地产 | E15: 安徽省 | F15: 宣城市 | G15: 旌德县 | H15: 安徽省宣城市旌德县白地镇金玉苑小区12幢505室住宅房地产 | I15: 变卖 | J15: 成交 | K15: 房产 | L15: 157830 | M15: 263050 | N15: 157830 | O15: 居住用房 | P15: 105.22 | Q15: 0 | T15: 未知 | W15: 否 | Y15: 住宅 | Z15: 5 | AA15: 4 | AB15: 是 | AD15: 司法裁定 | AK15: 45619.674 | AL15: https://zc-item.taobao.com/auction/833442026058.htm | AM15: =LEN(B15) -> 3 | AN15: 个人
B16: 吴梅芳 | D16: 旌德县白地镇金玉苑小区12幢503室住宅房地产 | E16: 安徽省 | F16: 宣城市 | G16: 旌德县 | H16: 安徽省宣城市旌德县白地镇金玉苑小区12幢503室住宅房地产 | I16: 变卖 | J16: 成交 | K16: 房产 | L16: 170460 | M16: 284100 | N16: 170460 | O16: 居住用房 | P16: 113.64 | Q16: 0 | T16: 未知 | W16: 否 | Y16: 住宅 | Z16: 5 | AA16: 4 | AB16: 是 | AD16: 司法裁定 | AK16: 45619.674 | AL16: https://zc-item.taobao.com/auction/833438958272.htm | AM16: =LEN(B16) -> 3 | AN16: 个人
B17: 吴梅芳 | D17: 旌德县白地镇金玉苑小区6幢603室住宅房地产 | E17: 安徽省 | F17: 宣城市 | G17: 旌德县 | H17: 安徽省宣城市旌德县白地镇金玉苑小区6幢603室住宅房地产 | I17: 变卖 | J17: 成交 | K17: 房产 | L17: 143055 | M17: 238425 | N17: 143055 | O17: 居住用房 | P17: 95.37 | Q17: 0 | T17: 未知 | W17: 否 | Y17: 住宅 | Z17: 6 | AA17: 6 | AB17: 是 | AD17: 司法裁定 | AK17: 45619.675 | AL17: https://zc-item.taobao.com/auction/833809928635.htm | AM17: =LEN(B17) -> 3 | AN17: 个人
B18: 吴梅芳 | D18: 旌德县白地镇金玉苑小区6幢502室住宅房地产 | E18: 安徽省 | F18: 宣城市 | G18: 旌德县 | H18: 安徽省宣城市旌德县白地镇金玉苑小区6幢502室住宅房地产 | I18: 变卖 | J18: 成交 | K18: 房产 | L18: 209490 | M18: 363116 | N18: 209490 | O18: 居住用房 | P18: 139.66 | Q18: 0 | T18: 未知 | W18: 否 | Y18: 住宅 | Z18: 6 | AA18: 5 | AB18: 是 | AD18: 司法裁定 | AK18: 45619.667 | AL18: https://zc-item.taobao.com/auction/833213543614.htm | AM18: =LEN(B18) -> 3 | AN18: 个人
B19: 周金娣 | D19: 滁州市滁宁大道1998号碧桂园.花语岸15幢1单元1602室的不动产 | E19: 安徽省 | F19: 滁州市 | G19: 南谯区 | H19: 安徽省滁州市南谯区花语岸 | I19: 变卖 | J19: 成交 | K19: 房产 | L19: 300000 | M19: 350000 | N19: 300000 | O19: 居住用房 | P19: 119.61 | Q19: 0 | T19: 是 | W19: 否 | Z19: 0 | AA19: 1 | AB19: 是 | AD19: 司法裁定 | AK19: 45603.527 | AL19: https://zc-item.taobao.com/auction/828721080522.htm | AM19: =LEN(B19) -> 3 | AN19: 个人
B20: 夏佐茂 | D20: 池州绿地城二期紫荆苑小区B15#楼108、108复式一、108复式二 | E20: 安徽省 | F20: 池州市 | G20: 贵池区 | H20: 安徽省池州市贵池区池州绿地城二期紫荆苑小区B15#楼108、108复式一、108复式二 | I20: 变卖 | J20: 成交 | K20: 房产 | L20: 1071612 | M20: 1400800 | N20: 1071612 | O20: 居住用房 | P20: 158.07 | Q20: 0 | T20: 是 | W20: 否 | Y20: 城镇住宅用地 | Z20: 3 | AA20: 1 | AB20: 是 | AC20: 2089-12-29 | AE20: 2024 | AF20: 钢混结构 | AK20: 45618.571 | AL20: https://zc-item.taobao.com/auction/833984135138.htm | AM20: =LEN(B20) -> 3 | AN20: 个人
B21: 夏佐茂 | D21: 池州市贵池区池州绿地城二期紫荆苑小区B5#楼104、104复式一、104复式二 | E21: 安徽省 | F21: 池州市 | G21: 贵池区 | H21: 安徽省池州市贵池区池州绿地城二期紫荆苑小区B5#楼104、104复式一、104复式二 | I21: 变卖 | J21: 成交 | K21: 房产 | L21: 1068323 | M21: 1396500 | N21: 1068323 | O21: 居住用房 | P21: 157.58 | Q21: 0 | T21: 是 | W21: 否 | Y21: 城镇住宅用地 | Z21: 3 | AA21: 1 | AB21: 是 | AC21: 2089-12-29 | AE21: 2024 | AF21: 钢混结构 | AK21: 45618.567 | AL21: https://zc-item.taobao.com/auction/834436773952.htm | AM21: =LEN(B21) -> 3 | AN21: 个人
B22: 夏佐茂 | D22: 池州绿地城二期紫荆苑小区B15#楼104、104复式一、104复式二 | E22: 安徽省 | F22: 池州市 | G22: 贵池区 | H22: 安徽省池州市贵池区池州绿地城二期紫荆苑小区B15#楼104、104复式一、104复式二 | I22: 变卖 | J22: 成交 | K22: 房产 | L22: 1071612 | M22: 1400800 | N22: 1071612 | O22: 居住用房 | P22: 158.07 | Q22: 0 | T22: 是 | W22: 否 | Y22: 城镇住宅用地 | Z22: 3 | AA22: 1 | AB22: 是 | AC22: 2089-12-29 | AE22: 2024 | AF22: 钢混结构 | AK22: 45618.573 | AL22: https://zc-item.taobao.com/auction/833984159777.htm | AM22: =LEN(B22) -> 3 | AN22: 个人
B23: 钱俊 | D23: 合肥市蜀山区长江西路844号瑞园小区1幢2101室 | E23: 安徽省 | F23: 合肥市 | G23: 蜀山区 | H23: 安徽省合肥市蜀山区合肥市蜀山区长江西路844号瑞园小区1幢2101室 | I23: 变卖 | J23: 成交 | K23: 房产 | L23: 2214012 | M23: 2894132 | N23: 2214012 | O23: 居住用房 | P23: 198.6 | Q23: 0 | T23: 是 | W23: 否 | Y23: 成套住宅 | Z23: 25 | AA23: 21 | AB23: 是 | AK23: 45609.457 | AL23: https://zc-item.taobao.com/auction/829607633449.htm | AM23: =LEN(B23) -> 2 | AN23: 个人
B24: 蔡贞 | D24: 宿州市银河一路南侧瞰景苑小区4#楼0601室(附赠阁楼) | E24: 安徽省 | F24: 宿州市 | G24: 埇桥区 | H24: 安徽省宿州市埇桥区宿州市银河一路南侧瞰景苑小区4#楼0601室(附赠阁楼) | I24: 变卖 | J24: 成交 | K24: 房产 | L24: 646687 | M24: 756359 | N24: 646687 | O24: 居住用房 | P24: 129.27 | Q24: 0 | T24: 是 | W24: 未知 | Y24: 成套住宅 | Z24: 6 | AA24: 6 | AB24: 是 | AF24: 混合结构 | AK24: 45616.388 | AL24: https://zc-item.taobao.com/auction/834525651870.htm | AM24: =LEN(B24) -> 2 | AN24: 个人
B25: 周凤 | D25: 芜湖市鸠江区恒大华府30#楼2单元102室 | E25: 安徽省 | F25: 芜湖市 | G25: 鸠江区 | H25: 安徽省芜湖市鸠江区恒大华府30#楼2单元102室 | I25: 变卖 | J25: 成交 | K25: 房产 | L25: 950418 | M25: 1508598 | N25: 950418 | O25: 居住用房 | P25: 125.57 | Q25: 0 | T25: 未知 | W25: 否 | X25: 简装 | Z25: 0 | AA25: 0 | AB25: 是 | AK25: 45626.906 | AL25: https://zc-item.taobao.com/auction/835195676834.htm | AM25: =LEN(B25) -> 2 | AN25: 个人
B26: 李玲 | D26: 安徽省蚌埠市怀远县荆山镇禹王东路89号江山御景C区C9号楼S111店面 | E26: 安徽省 | F26: 蚌埠市 | G26: 怀远县 | H26: 安徽省蚌埠市怀远县荆山镇禹王东路89号江山御景C区C9号楼S111店面 | I26: 变卖 | J26: 成交 | K26: 房产 | L26: 484139 | M26: 864533 | N26: 484139 | O26: 商业用房 | P26: 96.3 | Q26: 0 | T26: 未知 | W26: 是 | Y26: 店面 | Z26: 0 | AA26: 0 | AB26: 是 | AD26: 司法裁定 | AK26: 45625.682 | AL26: https://zc-item.taobao.com/auction/835262040664.htm | AM26: =LEN(B26) -> 2 | AN26: 个人
B27: 李玲 | D27: 安徽省蚌埠市怀远县荆山镇禹王东路89号江山御景A区A5号楼S109店面 | E27: 安徽省 | F27: 蚌埠市 | G27: 怀远县 | H27: 安徽省蚌埠市怀远县荆山镇禹王东路89号江山御景A区A5号楼S109店面 | I27: 变卖 | J27: 成交 | K27: 房产 | L27: 650176 | M27: 1161029 | N27: 650176 | O27: 商业用房 | P27: 81.86 | Q27: 0 | T27: 未知 | W27: 是 | Y27: 店面 | Z27: 0 | AA27: 0 | AB27: 是 | AD27: 司法裁定 | AK27: 45625.699 | AL27: https://zc-item.taobao.com/auction/835267552711.htm | AM27: =LEN(B27) -> 2 | AN27: 个人
B28: 李玲 | D28: 安徽省蚌埠市怀远县荆山镇禹王东路89号江山御景C区C9号楼S117店面 | E28: 安徽省 | F28: 蚌埠市 | G28: 怀远县 | H28: 安徽省蚌埠市怀远县荆山镇禹王东路89号江山御景C区C9号楼S117店面 | I28: 变卖 | J28: 成交 | K28: 房产 | L28: 478156 | M28: 853850 | N28: 478156 | O28: 商业用房 | P28: 95.11 | Q28: 0 | T28: 未知 | W28: 是 | Y28: 店面 | Z28: 0 | AA28: 0 | AB28: 是 | AD28: 司法裁定 | AK28: 45625.693 | AL28: https://zc-item.taobao.com/auction/835088749486.htm | AM28: =LEN(B28) -> 2 | AN28: 个人
B29: 李玲 | D29: 安徽省蚌埠市怀远县荆山镇禹王东路89号江山御景C区C9号楼S105店面 | E29: 安徽省 | F29: 蚌埠市 | G29: 怀远县 | H29: 安徽省蚌埠市怀远县荆山镇禹王东路89号江山御景C区C9号楼S105店面 | I29: 变卖 | J29: 成交 | K29: 房产 | L29: 191704 | M29: 342329 | N29: 191704 | O29: 商业用房 | P29: 28.77 | Q29: 0 | T29: 未知 | W29: 是 | Y29: 店面 | Z29: 0 | AA29: 0 | AB29: 是 | AD29: 司法裁定 | AK29: 45625.648 | AL29: https://zc-item.taobao.com/auction/835259372624.htm | AM29: =LEN(B29) -> 2 | AN29: 个人
B30: 李玲 | D30: 安徽省蚌埠市怀远县荆山镇禹王东路89号江山御景C区C9号楼S115店面 | E30: 安徽省 | F30: 蚌埠市 | G30: 怀远县 | H30: 安徽省蚌埠市怀远县荆山镇禹王东路89号江山御景C区C9号楼S115店面 | I30: 变卖 | J30: 成交 | K30: 房产 | L30: 304798 | M30: 544282 | N30: 304798 | O30: 商业用房 | P30: 50.82 | Q30: 0 | T30: 未知 | W30: 是 | Y30: 店面 | Z30: 0 | AA30: 0 | AB30: 是 | AD30: 司法裁定 | AK30: 45625.688 | AL30: https://zc-item.taobao.com/auction/834843234708.htm | AM30: =LEN(B30) -> 2 | AN30: 个人
B31: 李玲 | D31: 安徽省蚌埠市怀远县荆山镇禹王东路89号江山御景A区A-SY1号楼S102店面 | E31: 安徽省 | F31: 蚌埠市 | G31: 怀远县 | H31: 安徽省蚌埠市怀远县荆山镇禹王东路89号江山御景A区A-SY1号楼S102店面 | I31: 变卖 | J31: 成交 | K31: 房产 | L31: 332775 | M31: 594240 | N31: 332775 | O31: 商业用房 | P31: 42.85 | Q31: 0 | T31: 未知 | W31: 是 | Y31: 店面 | Z31: 0 | AA31: 0 | AB31: 是 | AD31: 司法裁定 | AK31: 45625.695 | AL31: https://zc-item.taobao.com/auction/834847134441.htm | AM31: =LEN(B31) -> 2 | AN31: 个人
B32: 李玲 | D32: 安徽省蚌埠市怀远县荆山镇禹王东路89号江山御景C区C6号楼S115店面 | E32: 安徽省 | F32: 蚌埠市 | G32: 怀远县 | H32: 安徽省蚌埠市怀远县荆山镇禹王东路89号江山御景C区C6号楼S115店面 | I32: 变卖 | J32: 成交 | K32: 房产 | L32: 272938 | M32: 487389 | N32: 272938 | O32: 商业用房 | P32: 42.92 | Q32: 0 | T32: 未知 | W32: 是 | Y32: 店面 | Z32: 0 | AA32: 0 | AB32: 是 | AD32: 司法裁定 | AK32: 45625.669 | AL32: https://zc-item.taobao.com/auction/834632351926.htm | AM32: =LEN(B32) -> 2 | AN32: 个人
B33: 李玲 | D33: 安徽省蚌埠市怀远县荆山镇禹王东路89号江山御景C区C9号楼S102店面 | E33: 安徽省 | F33: 蚌埠市 | G33: 怀远县 | H33: 安徽省蚌埠市怀远县荆山镇禹王东路89号江山御景C区C9号楼S102店面 | I33: 变卖 | J33: 成交 | K33: 房产 | L33: 330934 | M33: 590953 | N33: 330934 | O33: 商业用房 | P33: 52.04 | Q33: 0 | T33: 未知 | W33: 是 | Y33: 店面 | Z33: 0 | AA33: 0 | AB33: 是 | AD33: 司法裁定 | AK33: 45625.675 | AL33: https://zc-item.taobao.com/auction/834634691702.htm | AM33: =LEN(B33) -> 2 | AN33: 个人
B34: 李玲 | D34: 安徽省蚌埠市怀远县荆山镇禹王东路89号江山御景C区C9号楼S112店面 | E34: 安徽省 | F34: 蚌埠市 | G34: 怀远县 | H34: 安徽省蚌埠市怀远县荆山镇禹王东路89号江山御景C区C9号楼S112店面 | I34: 变卖 | J34: 成交 | K34: 房产 | L34: 304798 | M34: 544282 | N34: 304798 | O34: 商业用房 | P34: 50.82 | Q34: 0 | T34: 未知 | W34: 是 | Y34: 店面 | Z34: 0 | AA34: 0 | AB34: 是 | AD34: 司法裁定 | AK34: 45625.684 | AL34: https://zc-item.taobao.com/auction/834634431818.htm | AM34: =LEN(B34) -> 2 | AN34: 个人
B35: 李玲 | D35: 安徽省蚌埠市怀远县荆山镇禹王东路89号江山御景C区C6号楼S112店面 | E35: 安徽省 | F35: 蚌埠市 | G35: 怀远县 | H35: 安徽省蚌埠市怀远县荆山镇禹王东路89号江山御景C区C6号楼S112店面 | I35: 变卖 | J35: 成交 | K35: 房产 | L35: 284766 | M35: 508510 | N35: 284766 | O35: 商业用房 | P35: 44.78 | Q35: 0 | T35: 未知 | W35: 是 | Y35: 店面 | Z35: 0 | AA35: 0 | AB35: 是 | AD35: 司法裁定 | AK35: 45625.628 | AL35: https://zc-item.taobao.com/auction/834841482701.htm | AM35: =LEN(B35) -> 2 | AN35: 个人
B36: 李玲 | D36: 安徽省蚌埠市怀远县荆山镇禹王东路89号江山御景C区C9号楼S113店面 | E36: 安徽省 | F36: 蚌埠市 | G36: 怀远县 | H36: 安徽省蚌埠市怀远县荆山镇禹王东路89号江山御景C区C9号楼S113店面 | I36: 变卖 | J36: 成交 | K36: 房产 | L36: 304798 | M36: 544282 | N36: 304798 | O36: 商业用房 | P36: 50.82 | Q36: 0 | T36: 未知 | W36: 是 | Y36: 店面 | Z36: 0 | AA36: 0 | AB36: 是 | AD36: 司法裁定 | AK36: 45625.686 | AL36: https://zc-item.taobao.com/auction/834635095782.htm | AM36: =LEN(B36) -> 2 | AN36: 个人
B37: 程余 | D37: 广德市大观国际105号、106号商铺 | E37: 安徽省 | F37: 宣城市 | G37: 广德市 | H37: 安徽省宣城市广德市大观国际105号、106号商铺 | I37: 变卖 | J37: 成交 | K37: 房产 | L37: 1493688 | M37: 2667300 | N37: 1493688 | O37: 商业用房 | P37: 199.66 | Q37: 0 | T37: 未知 | W37: 未知 | Y37: 商业服务 | Z37: 4 | AA37: 1 | AB37: 是 | AC37: 2053-9-10 | AD37: 司法裁定 | AF37: 钢混结构 | AK37: 45656.25 | AL37: https://zc-item.taobao.com/auction/841829618732.htm | AM37: =LEN(B37) -> 2 | AN37: 个人
B38: 张星 | C38: ****1824 | D38: 安徽省蚌埠市蚌山区荣盛华府11号楼1单元11层2号 | E38: 安徽省 | F38: 蚌埠市 | G38: 蚌山区 | H38: 安徽省蚌埠市蚌山区荣盛华府11号楼1单元11层2号 | I38: 一拍 | J38: 成交 | K38: 房产 | L38: 1492920.4 | M38: 2132743.5 | N38: 2542920.5 | O38: 居住用房 | P38: 219.17 | Q38: 0 | T38: 是 | U38: 南 | W38: 未知 | Y38: 住宅 | Z38: 19 | AA38: 11 | AB38: 是 | AK38: 45601.494 | AL38: http://paimai.jd.com/307562181 | AM38: =LEN(B38) -> 2 | AN38: 个人
B39: 曾萧雅 | D39: 舒城县繁华里小区2幢号楼1703室 | E39: 安徽省 | F39: 六安市 | G39: 舒城县 | H39: 安徽省六安市舒城县舒城县繁华里小区2幢号楼1703室 | I39: 变卖 | J39: 成交 | K39: 房产 | L39: 290664 | M39: 403700 | N39: 290664 | O39: 居住用房 | P39: 79.44 | Q39: 0 | S39: 单独所有 | T39: 未知 | W39: 否 | Y39: 成套住宅 | Z39: 24 | AA39: 17 | AB39: 是 | AK39: 45647.604 | AL39: https://zc-item.taobao.com/auction/842110176811.htm | AM39: =LEN(B39) -> 3 | AN39: 个人
B40: 程余 | D40: 广德市大观国际B-1406室 | E40: 安徽省 | F40: 宣城市 | G40: 广德市 | H40: 安徽省宣城市广德市大观国际B-1406室 | I40: 变卖 | J40: 成交 | K40: 房产 | L40: 230440 | M40: 411500 | N40: 230440 | O40: 商业用房 | P40: 70.48 | Q40: 0 | T40: 未知 | W40: 否 | Y40: 商业服务 | Z40: 20 | AA40: 14 | AB40: 是 | AC40: 2053-9-10 | AD40: 司法裁定 | AF40: 钢混结构 | AK40: 45596.417 | AL40: https://zc-item.taobao.com/auction/842289140957.htm | AM40: =LEN(B40) -> 2 | AN40: 个人
B41: 王成玉 | D41: 广德市桃州镇广宁路卡地亚花园23栋2单元602室房产 | E41: 安徽省 | F41: 宣城市 | G41: 广德市 | H41: 安徽省宣城市广德市桃州镇广宁路卡地亚花园23栋2单元602室 | I41: 一拍 | J41: 成交 | K41: 房产 | L41: 638671 | M41: 912386 | N41: 752671 | O41: 居住用房 | P41: 100.95 | Q41: 9.17 | T41: 未知 | W41: 未知 | Y41: 城镇住宅用地/住宅 | Z41: 0 | AA41: 6 | AB41: 是 | AC41: 2079-11-28 | AD41: 司法裁定 | AF41: 钢混结构 | AK41: 45607.435 | AL41: https://zc-item.taobao.com/auction/842293820778.htm | AM41: =LEN(B41) -> 3 | AN41: 个人
B42: 李伟 | D42: 安徽省淮北市相山区人民路239号慢城花园4#1002室 | E42: 安徽省 | F42: 淮北市 | G42: 相山区 | H42: 安徽省淮北市相山区人民路239号 | I42: 一拍 | J42: 成交 | K42: 房产 | L42: 587448 | M42: 783265 | N42: 593448 | O42: 居住用房 | P42: 120.75 | Q42: 0 | T42: 未知 | W42: 是 | Y42: 住宅 | Z42: 12 | AA42: 10 | AB42: 未知 | AF42: 钢筋混凝土结构 | AK42: 45597.422 | AL42: https://zc-item.taobao.com/auction/839548970929.htm | AM42: =LEN(B42) -> 2 | AN42: 个人
B43: 齐春英 | D43: 镜湖区法院关于安徽省芜湖市鸠江区信德半岛A18#楼2单元202室房屋 | E43: 安徽省 | F43: 芜湖市 | G43: 鸠江区 | H43: 安徽省芜湖市鸠江区信德半岛A18#楼2单元202室 | I43: 变卖 | J43: 成交 | K43: 房产 | L43: 685459 | M43: 1088029 | N43: 685459 | O43: 居住用房 | P43: 114.88 | Q43: 0 | T43: 未知 | W43: 否 | Z43: 6 | AA43: 0 | AB43: 是 | AK43: 45644.524 | AL43: https://zc-item.taobao.com/auction/841753419547.htm | AM43: =LEN(B43) -> 3 | AN43: 个人
B44: 马明轩 | C44: ****1818 | D44: 安徽省合肥市滨湖区中山路1298号佳源都市小区5幢1804号房产及地下2036号车库 | E44: 安徽省 | F44: 合肥市 | G44: 瑶海区 | H44: 安徽省合肥市瑶海区中山路1298号佳源都市小区5幢1804号房产及地下2036号车库 | I44: 一拍 | J44: 成交 | K44: 房产 | L44: 2078723.7 | M44: 2969605.3 | N44: 2308723.7 | O44: 居住用房 | P44: 126.68 | Q44: 0 | T44: 是 | U44: 南 | W44: 未知 | Y44: 住宅 | Z44: 29 | AA44: 0 | AB44: 是 | AK44: 45601.437 | AL44: http://paimai.jd.com/307562405 | AM44: =LEN(B44) -> 3 | AN44: 个人
B45: 许金保 | D45: 池州市百牙中路南侧13号工业房地产及地上建筑物、附属物、设备 | E45: 安徽省 | F45: 池州市 | G45: 贵池区 | H45: 安徽省池州市贵池区百牙中路南侧13号 | I45: 一拍 | J45: 成交 | K45: 房产 | L45: 22030319 | M45: 22030319 | N45: 22030319 | O45: 工业用房 | P45: 6783.62 | Q45: 3426 | T45: 未知 | W45: 是 | Y45: 商业用房、办公楼 | Z45: 7 | AA45: 1 | AB45: 是 | AD45: 司法裁定 | AE45: 2013 | AF45: 钢混结构 | AK45: 45597.417 | AL45: https://zc-item.taobao.com/auction/839636026509.htm | AM45: =LEN(B45) -> 3 | AN45: 个人
B46: 黄凯玲 | D46: 安徽省郎溪县建平镇中港东路朗润园19幢3单元906室的不动产 | E46: 安徽省 | F46: 宣城市 | G46: 郎溪县 | H46: 安徽省宣城市郎溪县朗润园 | I46: 一拍 | J46: 成交 | K46: 房产 | L46: 500000 | M46: 711887 | N46: 500000 | O46: 居住用房 | P46: 124.63 | Q46: 0 | T46: 未知 | W46: 否 | Y46: 城镇住宅用地/住宅 | Z46: 11 | AA46: 0 | AB46: 是 | AK46: 45597.417 | AL46: https://zc-item.taobao.com/auction/839537230313.htm | AM46: =LEN(B46) -> 3 | AN46: 个人
B47: 孙琦 | D47: 安徽省铜陵市铜官区新苑四区1栋一层46#车位 | E47: 安徽省 | F47: 铜陵市 | G47: 铜官区 | H47: 安徽省铜陵市铜官区新苑四区1栋一层46#车位 | I47: 一拍 | J47: 成交 | K47: 房产 | L47: 39315 | M47: 46253 | N47: 39315 | O47: 未分类 | T47: 未知 | W47: 未知 | Z47: 16 | AA47: 1 | AB47: 是 | AC47: 2053-8-15 | AD47: 司法裁定 | AE47: 2006 | AF47: 钢筋混凝土结构 | AK47: 45608.417 | AL47: https://zc-item.taobao.com/auction/842756489665.htm | AM47: =LEN(B47) -> 2 | AN47: 个人
B48: 查志勇 | D48: 安徽省铜陵市铜官区新苑四区1栋一层1#车位 | E48: 安徽省 | F48: 铜陵市 | G48: 铜官区 | H48: 安徽省铜陵市铜官区新苑四区1栋一层1#车位 | I48: 一拍 | J48: 成交 | K48: 房产 | L48: 39326 | M48: 46266 | N48: 39326 | O48: 未分类 | T48: 未知 | W48: 未知 | Z48: 16 | AA48: 1 | AB48: 是 | AC48: 2053-8-15 | AD48: 司法裁定 | AE48: 2006 | AF48: 钢筋混凝土结构 | AK48: 45608.417 | AL48: https://zc-item.taobao.com/auction/842478310511.htm | AM48: =LEN(B48) -> 3 | AN48: 个人
B49: 孙琦 | D49: 安徽省铜陵市铜官区新苑四区1栋一层37#车位 | E49: 安徽省 | F49: 铜陵市 | G49: 铜官区 | H49: 安徽省铜陵市铜官区新苑四区1栋一层37#车位 | I49: 一拍 | J49: 成交 | K49: 房产 | L49: 38983 | M49: 45862 | N49: 38983 | O49: 未分类 | T49: 未知 | W49: 未知 | Z49: 16 | AA49: 1 | AB49: 是 | AC49: 2053-8-15 | AD49: 司法裁定 | AE49: 2006 | AF49: 钢筋混凝土结构 | AK49: 45608.417 | AL49: https://zc-item.taobao.com/auction/842941996947.htm | AM49: =LEN(B49) -> 2 | AN49: 个人
B50: 徐凡 | D50: 黄山市屯溪区阳光绿水花园B幢201号房产 | E50: 安徽省 | F50: 黄山市 | G50: 屯溪区 | H50: 安徽省黄山市屯溪区阳光绿水花园B幢201号 | I50: 一拍 | J50: 成交 | K50: 房产 | L50: 3870000 | M50: 4833411 | N50: 3870000 | O50: 商业用房 | P50: 830.33 | Q50: 0 | T50: 是 | W50: 否 | Y50: 商业服务 | Z50: 7 | AA50: 2 | AB50: 是 | AC50: 2043-8-21 | AF50: 混合结构 | AK50: 45597.417 | AL50: https://zc-item.taobao.com/auction/840069380864.htm | AM50: =LEN(B50) -> 2 | AN50: 个人
B51: 赵栋 | D51: 合肥市瑶海区滨河苑5幢404室 | E51: 安徽省 | F51: 合肥市 | G51: 肥东县 | H51: 安徽省合肥市瑶海区滨河苑5幢404室 | I51: 一拍 | J51: 成交 | K51: 房产 | L51: 830000 | M51: 1185509.3 | N51: 972000 | O51: 居住用房 | P51: 87.11 | Q51: 0 | T51: 是 | W51: 未知 | Y51: 成套住宅 | Z51: 6 | AA51: 4 | AB51: 是 | AK51: 45607.441 | AL51: https://zc-item.taobao.com/auction/839547543620.htm | AM51: =LEN(B51) -> 2 | AN51: 个人
B52: 侯成 | D52: 安徽省黄山市屯溪区徽州大道11号大观上河城9幢910室房产 | E52: 安徽省 | F52: 黄山市 | G52: 屯溪区 | H52: 安徽省黄山市屯溪区徽州大道11号大观上河城9幢 | I52: 变卖 | J52: 成交 | K52: 房产 | L52: 219228.8 | M52: 342545 | N52: 219228.8 | O52: 居住用房 | P52: 43.12 | Q52: 0 | T52: 是 | W52: 否 | Y52: 住宅 | Z52: 24 | AA52: 9 | AB52: 是 | AF52: 钢筋混凝土结构 | AK52: 45601.739 | AL52: https://zc-item.taobao.com/auction/842763629490.htm | AM52: =LEN(B52) -> 2 | AN52: 个人
B53: 李浩奇 | D53: 安徽省亳州市利辛县城关镇文州路南侧淝河路东侧翰联时代广场3号楼0101室 | E53: 安徽省 | F53: 亳州市 | G53: 利辛县 | H53: 安徽省亳州市利辛县城关镇文州路南侧淝河路东侧翰联时代广场3号楼0101室 | I53: 一拍 | J53: 成交 | K53: 房产 | L53: 1714090 | M53: 2448700 | N53: 2454090 | O53: 商业用房 | P53: 175.47 | Q53: 0 | T53: 未知 | W53: 是 | Y53: 商业服务 | Z53: 6 | AA53: 1 | AB53: 是 | AK53: 45608.446 | AL53: https://zc-item.taobao.com/auction/842476279965.htm | AM53: =LEN(B53) -> 3 | AN53: 个人
B54: 徐凡 | D54: 黄山市屯溪区阳光绿水花园B幢101号房产 | E54: 安徽省 | F54: 黄山市 | G54: 屯溪区 | H54: 安徽省黄山市屯溪区阳光绿水花园B幢101号 | I54: 一拍 | J54: 成交 | K54: 房产 | L54: 7060000 | M54: 8820577 | N54: 7060000 | O54: 商业用房 | P54: 830.33 | Q54: 0 | T54: 是 | W54: 否 | Y54: 商业服务 | Z54: 7 | AA54: 1 | AB54: 是 | AC54: 2043-8-21 | AF54: 混合结构 | AK54: 45597.417 | AL54: https://zc-item.taobao.com/auction/839892233463.htm | AM54: =LEN(B54) -> 2 | AN54: 个人
B55: 王凡 | D55: 合肥市瑶海区临泉路江晨园B-9幢1401-1406号 | E55: 安徽省 | F55: 合肥市 | G55: 瑶海区 | H55: 安徽省合肥市瑶海区瑶海区临泉路江晨园B-9幢1401-1406号 | I55: 变卖 | J55: 成交 | K55: 房产 | L55: 2299248 | M55: 4105800 | N55: 2299248 | O55: 商业用房 | P55: 583.18 | Q55: 0 | T55: 未知 | W55: 是 | X55: 中等装修 | Y55: 住宅 | Z55: 18 | AA55: 14 | AB55: 是 | AF55: 钢混结构 | AK55: 45647.601 | AL55: https://zc-item.taobao.com/auction/841472851152.htm | AM55: =LEN(B55) -> 2 | AN55: 个人
B56: 刘丽丽 | D56: 安徽宁国市东风路新业小区B-06号房产 | E56: 安徽省 | F56: 宣城市 | G56: 宁国市 | H56: 安徽省宣城市宁国市东风路新业小区 | I56: 一拍 | J56: 成交 | K56: 房产 | L56: 2833129.5 | M56: 3777506 | N56: 5143129.5 | O56: 居住用房 | P56: 527.29 | Q56: 0 | T56: 未知 | W56: 未知 | Z56: 0 | AA56: 0 | AB56: 未知 | AK56: 45609.462 | AL56: https://zc-item.taobao.com/auction/842818043197.htm | AM56: =LEN(B56) -> 3 | AN56: 个人
B57: 张传妹 | D57: 和县历阳镇共义小康村十八米路1号房不动产 | E57: 安徽省 | F57: 马鞍山市 | G57: 和县 | H57: 安徽省马鞍山市和县历阳镇共义小康村十八米路1号房不动产 | I57: 变卖 | J57: 成交 | K57: 房产 | L57: 897408 | M57: 1402200 | N57: 897408 | O57: 居住用房 | P57: 278.72 | Q57: 216 | T57: 是 | U57: 南北 | W57: 未知 | Y57: 成套住宅 | Z57: 0 | AA57: 0 | AB57: 是 | AC57: 2071-12-11 | AD57: （2024）皖0523执恢140号 | AE57: 2004 | AK57: 45602.382 | AL57: https://zc-item.taobao.com/auction/841536803362.htm | AM57: =LEN(B57) -> 3 | AN57: 个人
B58: 周舰 | D58: 安徽省凤阳县中都大道西侧前门路北侧海棠花园9幢1单元101室房产 | E58: 安徽省 | F58: 滁州市 | G58: 凤阳县 | H58: 安徽省滁州市凤阳县中都大道西侧前门路北侧海棠花园9幢1单元101室 | I58: 一拍 | J58: 成交 | K58: 房产 | L58: 487847.3 | M58: 573938 | N58: 535847.3 | O58: 居住用房 | P58: 96.59 | Q58: 0 | T58: 未知 | W58: 否 | Z58: 0 | AA58: 0 | AB58: 是 | AK58: 45611.448 | AL58: https://zc-item.taobao.com/auction/843068292723.htm | AM58: =LEN(B58) -> 2 | AN58: 个人
B59: 窦裕新 | D59: 阜阳市颍东区致富路948号幸福家园小区6#住宅楼2704室 | E59: 安徽省 | F59: 阜阳市 | G59: 颍东区 | H59: 安徽省阜阳市颍东区致富路948号幸福家园小区6#住宅楼2704室 | I59: 二拍 | J59: 成交 | K59: 房产 | L59: 317813.76 | M59: 496584 | N59: 361313.76 | O59: 居住用房 | P59: 98.34 | Q59: 0 | T59: 未知 | U59: 南北 | V59: 3室1厅 | W59: 否 | X59: 简装 | Y59: 住宅 | Z59: 33 | AA59: 27 | AB59: 是 | AF59: 钢混结构 | AK59: 45596.427 | AL59: https://zc-item.taobao.com/auction/843076896114.htm | AM59: =LEN(B59) -> 3 | AN59: 个人
B60: 安徽西派仪表有限公司 | D60: 天长市西城区的工业房地产及附属物 | E60: 安徽省 | F60: 滁州市 | G60: 天长市 | H60: 安徽省滁州市天长市西城区的工业房地产及附属物 | I60: 一拍 | J60: 成交 | K60: 房产 | L60: 11762560 | M60: 14703200 | N60: 14222560 | O60: 工业用房 | P60: 6600 | Q60: 18615 | T60: 是 | W60: 是 | Z60: 0 | AA60: 0 | AB60: 是 | AC60: 2054-4-13 | AD60: 司法裁定 | AF60: 钢结构 | AK60: 45598.469 | AL60: https://zc-item.taobao.com/auction/839555595889.htm | AM60: =LEN(B60) -> 10 | AN60: 机构
B61: 何虹 | D61: 宣州区阳光小区D2幢6室商业房地产 | E61: 安徽省 | F61: 宣城市 | G61: 宣州区 | H61: 安徽省宣城市宣州区阳光小区D2幢6室商业房地产 | I61: 一拍 | J61: 成交 | K61: 房产 | L61: 581676 | M61: 830965 | N61: 586676 | O61: 商业用房 | P61: 76.87 | Q61: 0 | T61: 未知 | W61: 未知 | Y61: 商业、住宅 | Z61: 3 | AA61: 1 | AB61: 是 | AD61: 司法裁定 | AE61: 2005 | AF61: 混合结构 | AK61: 45608.419 | AL61: https://zc-item.taobao.com/auction/841924497278.htm | AM61: =LEN(B61) -> 2 | AN61: 个人
B62: 苏钰 | C62: ****0644 | D62: 安徽省蚌埠市蚌山区万达广场10号楼2单元6层8号 | E62: 安徽省 | F62: 蚌埠市 | G62: 蚌山区 | H62: 安徽省蚌埠市蚌山区万达广场10号楼2单元6层8号 | I62: 一拍 | J62: 成交 | K62: 房产 | L62: 693971.11 | M62: 991387.3 | N62: 1133971.1 | O62: 居住用房 | P62: 136.85 | Q62: 0 | T62: 是 | U62: 南 | W62: 未知 | Y62: 住宅 | Z62: 35 | AA62: 6 | AB62: 是 | AK62: 45601.5 | AL62: http://paimai.jd.com/307562117 | AM62: =LEN(B62) -> 2 | AN62: 个人
B63: 吴爱禄 | D63: 和县历阳镇佳源中央城商业D1a幢135室 | E63: 安徽省 | F63: 马鞍山市 | G63: 和县 | H63: 安徽省马鞍山市和县历阳镇佳源中央城商业D1a幢135室 | I63: 一拍 | J63: 成交 | K63: 房产 | L63: 916400 | M63: 1145500 | N63: 1348400 | O63: 商业用房 | P63: 103.38 | Q63: 0 | S63: 单独所有 | T63: 是 | W63: 未知 | Z63: 12 | AA63: 0 | AB63: 是 | AC63: 2054-3-17 | AD63: （2024）皖0523执恢409号 | AE63: 2023 | AF63: 钢筋混凝土结构 | AK63: 45597.445 | AL63: https://zc-item.taobao.com/auction/839915765064.htm | AM63: =LEN(B63) -> 3 | AN63: 个人
B64: 吴立根 | D64: 安徽省合肥市肥东县长江批发市场服装城1幢F8138 | E64: 安徽省 | F64: 合肥市 | G64: 肥东县 | H64: 安徽省合肥市肥东县长江批发市场服装城1幢F8138 | I64: 一拍 | J64: 成交 | K64: 房产 | L64: 228212 | M64: 285265 | N64: 338212 | O64: 商业用房 | P64: 69.34 | Q64: 0 | T64: 未知 | W64: 是 | Y64: 商业服务 | Z64: 2 | AA64: 1 | AB64: 未知 | AK64: 45601.434 | AL64: https://zc-item.taobao.com/auction/840023648154.htm | AM64: =LEN(B64) -> 3 | AN64: 个人
B65: 王燕 | D65: 和县历阳镇佳源中央城商业D1a幢133室不动产 | E65: 安徽省 | F65: 马鞍山市 | G65: 和县 | H65: 安徽省马鞍山市和县历阳镇佳源中央城商业D1a幢133室不动产 | I65: 一拍 | J65: 成交 | K65: 房产 | L65: 916400 | M65: 1145500 | N65: 1312400 | O65: 商业用房 | P65: 103.38 | Q65: 0 | S65: 单独所有 | T65: 是 | W65: 未知 | Z65: 12 | AA65: 0 | AB65: 是 | AC65: 2054-3-17 | AD65: （2024）皖0523执恢409号 | AE65: 2023 | AF65: 钢筋混凝土结构 | AK65: 45597.429 | AL65: https://zc-item.taobao.com/auction/839915413081.htm | AM65: =LEN(B65) -> 2 | AN65: 个人
B66: 李如男 | D66: 安徽省亳州市谯城区还原安置小区D区龙凤家园9号楼1308号 | E66: 安徽省 | F66: 亳州市 | G66: 谯城区 | H66: 安徽省亳州市谯城区还原安置小区D区龙凤家园9号楼1308号 | I66: 一拍 | J66: 成交 | K66: 房产 | L66: 440402 | M66: 518120 | N66: 468402 | O66: 居住用房 | P66: 129.53 | Q66: 0 | T66: 是 | W66: 否 | Y66: 住宅 | Z66: 18 | AA66: 13 | AB66: 是 | AK66: 45600.432 | AL66: https://zc-item.taobao.com/auction/839984032784.htm | AM66: =LEN(B66) -> 3 | AN66: 个人
B67: 俞晓红 | D67: 合肥市蜀山区聚云路138号白天鹅国际商务中心公寓307室办公房产 | E67: 安徽省 | F67: 合肥市 | G67: 蜀山区 | H67: 安徽省合肥市蜀山区聚云路138号白天鹅国际商务中心公寓307室办公房产 | I67: 一拍 | J67: 成交 | K67: 房产 | L67: 222881 | M67: 318401 | N67: 252881 | O67: 商业用房 | P67: 48.7 | Q67: 0 | T67: 是 | W67: 未知 | Y67: 办公 | Z67: 18 | AA67: 3 | AB67: 是 | AK67: 45610.435 | AL67: https://zc-item.taobao.com/auction/841933077540.htm | AM67: =LEN(B67) -> 3 | AN67: 个人
B68: 张佳豪 | D68: 合肥市滨湖区包河大道699号时代城2幢2202室房产 | E68: 安徽省 | F68: 合肥市 | G68: 包河区 | H68: 安徽省合肥市包河区滨湖区包河大道699号时代城2幢2202室房产 | I68: 一拍 | J68: 成交 | K68: 房产 | L68: 1217581 | M68: 1739401 | N68: 1272581 | O68: 居住用房 | P68: 93.91 | Q68: 0 | T68: 是 | W68: 未知 | Y68: 住宅 | Z68: 34 | AA68: 22 | AB68: 是 | AK68: 45610.426 | AL68: https://zc-item.taobao.com/auction/841936309755.htm | AM68: =LEN(B68) -> 3 | AN68: 个人
B69: 马征 | D69: 安徽省合肥市瑶海区合钢二厂钢红34幢502 | E69: 安徽省 | F69: 合肥市 | G69: 瑶海区 | H69: 安徽省合肥市瑶海区合钢二厂钢红34幢502 | I69: 一拍 | J69: 成交 | K69: 房产 | L69: 480598 | M69: 600747 | N69: 852598 | O69: 居住用房 | P69: 65.48 | Q69: 0 | T69: 是 | W69: 未知 | Y69: 成套住宅 | Z69: 5 | AA69: 5 | AB69: 是 | AE69: 1988-1-1 | AK69: 45609.515 | AL69: https://zc-item.taobao.com/auction/841637826369.htm | AM69: =LEN(B69) -> 2 | AN69: 个人
B70: 孙甜甜 | D70: 合肥市蜀山区聚云路138号白天鹅国际商务中心公寓401室办公房产 | E70: 安徽省 | F70: 合肥市 | G70: 蜀山区 | H70: 安徽省合肥市蜀山区聚云路138号白天鹅国际商务中心公寓401室办公房产 | I70: 一拍 | J70: 成交 | K70: 房产 | L70: 746018 | M70: 1065740 | N70: 890018 | O70: 商业用房 | P70: 162.87 | Q70: 0 | T70: 是 | W70: 未知 | Y70: 办公 | Z70: 18 | AA70: 4 | AB70: 是 | AK70: 45610.44 | AL70: https://zc-item.taobao.com/auction/841578635443.htm | AM70: =LEN(B70) -> 3 | AN70: 个人
B71: 吴晓珍 | D71: 合肥市瑶海区龙岗开发区明皇路郎溪尚里16幢2104 | E71: 安徽省 | F71: 合肥市 | G71: 瑶海区 | H71: 安徽省合肥市瑶海区龙岗开发区明皇路郎溪尚里16幢2104 | I71: 一拍 | J71: 成交 | K71: 房产 | L71: 1329686.4 | M71: 1662108 | N71: 1329686.4 | O71: 居住用房 | P71: 105.27 | Q71: 0 | T71: 未知 | W71: 未知 | Y71: 住宅 | Z71: 0 | AA71: 0 | AB71: 未知 | AK71: 45606.417 | AL71: https://zc-item.taobao.com/auction/841455095806.htm | AM71: =LEN(B71) -> 3 | AN71: 个人
B72: 王敏 | D72: 明光市龙山路261号巴黎公馆1幢1单元402室房地产 | E72: 安徽省 | F72: 滁州市 | G72: 明光市 | H72: 安徽省滁州市明光市龙山路261号巴黎公馆1幢1单元402室 | I72: 一拍 | J72: 成交 | K72: 房产 | L72: 650000 | M72: 923600 | N72: 650000 | O72: 居住用房 | P72: 130.09 | Q72: 0 | T72: 未知 | W72: 否 | Y72: 住宅 | Z72: 22 | AA72: 4 | AB72: 是 | AD72: 司法裁定 | AF72: 框架结构 | AK72: 45605.42 | AL72: https://zc-item.taobao.com/auction/841619482428.htm | AM72: =LEN(B72) -> 2 | AN72: 个人
B73: 陈道平 | D73: 安徽省淮南市田家庵区山南新区志高新城·凯旋首府6栋703 | E73: 安徽省 | F73: 淮南市 | G73: 田家庵区 | H73: 安徽省淮南市田家庵区山南新区志高新城·凯旋首府6栋703 | I73: 一拍 | J73: 成交 | K73: 房产 | L73: 421419 | M73: 602027 | N73: 475419 | O73: 居住用房 | P73: 113.88 | Q73: 0 | T73: 是 | W73: 未知 | Y73: 住宅用房 | Z73: 11 | AA73: 7 | AB73: 是 | AF73: 钢混结构 | AK73: 45608.45 | AL73: https://zc-item.taobao.com/auction/841564222177.htm | AM73: =LEN(B73) -> 3 | AN73: 个人
B74: 孙协友 | D74: 芜湖市三山区碧桂园江心环玉627#楼1单元3103室 | E74: 安徽省 | F74: 芜湖市 | G74: 弋江区 | H74: 安徽省芜湖市三山区碧桂园江心环玉627#楼1单元3103室 | I74: 变卖 | J74: 成交 | K74: 房产 | L74: 340000 | M74: 606959 | N74: 340000 | O74: 居住用房 | P74: 116.51 | Q74: 0 | T74: 未知 | W74: 未知 | Y74: 住宅 | Z74: 32 | AA74: 31 | AB74: 未知 | AK74: 45615.485 | AL74: https://zc-item.taobao.com/auction/841654186049.htm | AM74: =LEN(B74) -> 3 | AN74: 个人
B75: 陶盛兰 | D75: 合肥市新站区颍河路香江生态丽景72幢401室 | E75: 安徽省 | F75: 合肥市 | G75: 瑶海区 | H75: 安徽省合肥市瑶海区合肥市新站区颍河路香江生态丽景72幢401室 | I75: 变卖 | J75: 成交 | K75: 房产 | L75: 914133 | M75: 1344313 | N75: 914133 | O75: 居住用房 | P75: 126.81 | Q75: 0 | T75: 是 | W75: 否 | Y75: 住宅 | Z75: 22 | AA75: 4 | AB75: 是 | AE75: 2011-12-8 | AK75: 45641.51 | AL75: https://zc-item.taobao.com/auction/839186520954.htm | AM75: =LEN(B75) -> 3 | AN75: 个人
B76: 胡宝成 | D76: 安徽省蚌埠市怀远县东方红商贸中心3803号房产一处 | E76: 安徽省 | F76: 蚌埠市 | G76: 怀远县 | H76: 安徽省蚌埠市怀远县东方红商贸中心3803号房产一处 | I76: 一拍 | J76: 成交 | K76: 房产 | L76: 469026 | M76: 586282 | N76: 469026 | O76: 居住用房 | P76: 108.37 | Q76: 0 | T76: 是 | U76: 南北 | V76: 三室一厅 | W76: 未知 | X76: 普通装修 | Y76: 住宅 | Z76: 11 | AA76: 8 | AB76: 是 | AE76: 2011 | AF76: 钢混结构 | AK76: 45597.419 | AL76: https://zc-item.taobao.com/auction/839539570707.htm | AM76: =LEN(B76) -> 3 | AN76: 个人
B77: 盛凤连 | D77: 界首市陶园路66号馨园16幢1单元402户房产一套 | E77: 安徽省 | F77: 阜阳市 | G77: 界首市 | H77: 安徽省阜阳市界首市陶园路66号馨园16幢1单元402户房产一套 | I77: 一拍 | J77: 成交 | K77: 房产 | L77: 634680 | M77: 705200 | N77: 684680 | O77: 居住用房 | P77: 111.06 | Q77: 0 | T77: 未知 | U77: 南 | W77: 未知 | Y77: 住宅 | Z77: 11 | AA77: 4 | AB77: 是 | AK77: 45597.424 | AL77: https://zc-item.taobao.com/auction/840103516541.htm | AM77: =LEN(B77) -> 3 | AN77: 个人
B78: 王敬 | D78: 安徽省淮北市相山区相山中路5号帝景翰园21幢101 | E78: 安徽省 | F78: 淮北市 | G78: 相山区 | H78: 安徽省淮北市相山区相山中路5号帝景翰园21幢101 | I78: 一拍 | J78: 成交 | K78: 房产 | L78: 1596293 | M78: 1596293 | N78: 3060293 | O78: 居住用房 | P78: 268.48 | Q78: 0 | T78: 未知 | W78: 否 | Y78: 住宅 | Z78: 3 | AA78: 1 | AB78: 是 | AK78: 45597.533 | AL78: https://zc-item.taobao.com/auction/839953713857.htm | AM78: =LEN(B78) -> 2 | AN78: 个人
B79: 龙玉芹 | D79: 全椒县襄河镇万利路92号秦岗新村7幢6室 | E79: 安徽省 | F79: 滁州市 | G79: 全椒县 | H79: 安徽省滁州市全椒县全椒县襄河镇万利路92号秦岗新村7幢6室 | I79: 一拍 | J79: 成交 | K79: 房产 | L79: 671002 | M79: 958574 | N79: 857002 | O79: 居住用房 | P79: 135.43 | Q79: 117.31 | T79: 是 | W79: 否 | Y79: 住宅 | Z79: 2 | AA79: 1 | AB79: 是 | AF79: 混合结构 | AK79: 45596.435 | AL79: https://zc-item.taobao.com/auction/839504657390.htm | AM79: =LEN(B79) -> 3 | AN79: 个人
B80: 安徽德恒旺产业投资有限公司 | D80: 蚌埠市凤阳西路8号-1-16层及广场西路19号A1001、A1002号、A1003号、A2001号、A2002号 | E80: 安徽省 | F80: 蚌埠市 | G80: 龙子湖区 | H80: 安徽省蚌埠市龙子湖区凤阳西路8号-1-16层及广场西路19号A1001、A1002号、A1003号、A2001号、A2002号 | I80: 一拍 | J80: 成交 | K80: 房产 | L80: 26000000 | M80: 36978567 | N80: 26000000 | O80: 商业用房 | P80: 1804.15 | Q80: 0 | T80: 是 | W80: 是 | Y80: 酒店、地下室 | Z80: 17 | AA80: 4 | AB80: 是 | AK80: 45596.417 | AL80: http://paimai.jd.com/307569436 | AM80: =LEN(B80) -> 13 | AN80: 机构
B81: 施梅梅 | D81: 安徽省合肥市瑶海区临泉东路与王岗路交口恒大城4-5幢5-2801 | E81: 安徽省 | F81: 合肥市 | G81: 瑶海区 | H81: 安徽省合肥市瑶海区临泉东路与王岗路交口恒大城4-5幢5-2801 | I81: 变卖 | J81: 成交 | K81: 房产 | L81: 719567 | M81: 1058186 | N81: 719567 | O81: 居住用房 | P81: 90.86 | Q81: 0 | T81: 是 | W81: 否 | Y81: 住宅 | Z81: 32 | AA81: 28 | AB81: 是 | AK81: 45624.597 | AL81: https://zc-item.taobao.com/auction/838585923618.htm | AM81: =LEN(B81) -> 3 | AN81: 个人
B82: 王龙生 | D82: 合肥市瑶海区临泉路森海豪庭7幢1104室 | E82: 安徽省 | F82: 合肥市 | G82: 瑶海区 | H82: 安徽省合肥市瑶海区合肥市瑶海区临泉路森海豪庭7幢1104室 | I82: 一拍 | J82: 成交 | K82: 房产 | L82: 1330840 | M82: 1901200 | N82: 1330840 | O82: 居住用房 | P82: 129.32 | Q82: 0 | T82: 是 | W82: 否 | Y82: 住宅 | Z82: 11 | AA82: 11 | AB82: 是 | AF82: 钢混结构 | AK82: 45596.417 | AL82: https://zc-item.taobao.com/auction/839502973935.htm | AM82: =LEN(B82) -> 3 | AN82: 个人
B83: 姚朝纲 | D83: 桐城市桐潜路北侧上和家园5幢206室住宅房产 | E83: 安徽省 | F83: 安庆市 | G83: 桐城市 | H83: 安徽省安庆市桐城市桐潜路北侧上和家园5幢206室住宅房产 | I83: 变卖 | J83: 成交 | K83: 房产 | L83: 288360 | M83: 400500 | N83: 288360 | O83: 居住用房 | P83: 97.04 | Q83: 0 | T83: 是 | W83: 未知 | Y83: 住宅 | Z83: 19 | AA83: 2 | AB83: 是 | AE83: 2019 | AF83: 钢混结构 | AK83: 45622.034 | AL83: https://zc-item.taobao.com/auction/837356519830.htm | AM83: =LEN(B83) -> 3 | AN83: 个人
B84: 牛超 | D84: 明光市龙山路261号巴黎公馆1幢1单元501室房地产 | E84: 安徽省 | F84: 滁州市 | G84: 明光市 | H84: 安徽省滁州市明光市明光市龙山路261号巴黎公馆1幢1单元501室房地产 | I84: 一拍 | J84: 成交 | K84: 房产 | L84: 520000 | M84: 729100 | N84: 520000 | O84: 居住用房 | P84: 131.65 | Q84: 0 | T84: 未知 | W84: 否 | Y84: 住宅 | Z84: 22 | AA84: 5 | AB84: 是 | AD84: 司法裁定 | AF84: 框架结构 | AK84: 45596.417 | AL84: https://zc-item.taobao.com/auction/839820836332.htm | AM84: =LEN(B84) -> 2 | AN84: 个人
B85: 陈玲玲 | D85: 安徽省凤阳县府城镇南环路北侧一处房产 | E85: 安徽省 | F85: 滁州市 | G85: 凤阳县 | H85: 安徽省滁州市凤阳县府城镇南环路北侧一处房产 | I85: 变卖 | J85: 成交 | K85: 房产 | L85: 920000 | M85: 1310000 | N85: 920000 | O85: 居住用房 | P85: 199.06 | Q85: 0 | T85: 未知 | W85: 否 | Y85: 住宅 | Z85: 0 | AA85: 0 | AB85: 是 | AK85: 45605.74 | AL85: https://zc-item.taobao.com/auction/837430167633.htm | AM85: =LEN(B85) -> 3 | AN85: 个人
B86: 蚌埠市拓坚机电有限公司 | D86: 固镇县经济开发区纬四路南侧厂房及地上附着物 | E86: 安徽省 | F86: 蚌埠市 | G86: 固镇县 | H86: 安徽省蚌埠市固镇县经济开发区纬四路南侧厂房及地上附着物 | I86: 变卖 | J86: 成交 | K86: 房产 | L86: 2736328 | M86: 4886300 | N86: 2736328 | O86: 工业用房 | P86: 4586.66 | Q86: 0 | T86: 是 | W86: 未知 | Z86: 0 | AA86: 0 | AB86: 是 | AK86: 45636.412 | AL86: http://paimai.jd.com/307537043 | AM86: =LEN(B86) -> 11 | AN86: 机构
B87: 蚌埠市时雨科技有限公司 | D87: 固镇县连城镇纬四路南侧厂房及地上附着物 | E87: 安徽省 | F87: 蚌埠市 | G87: 固镇县 | H87: 安徽省蚌埠市固镇县连城镇纬四路南侧厂房及地上附着物 | I87: 变卖 | J87: 成交 | K87: 房产 | L87: 6963208 | M87: 12434300 | N87: 6963208 | O87: 工业用房 | P87: 37522.47 | Q87: 0 | T87: 是 | W87: 未知 | Z87: 0 | AA87: 0 | AB87: 是 | AK87: 45637.414 | AL87: http://paimai.jd.com/307537047 | AM87: =LEN(B87) -> 11 | AN87: 机构
B88: 盛业静 | D88: 和县历阳镇佳源中央城商业D1a幢125室 | E88: 安徽省 | F88: 马鞍山市 | G88: 和县 | H88: 安徽省马鞍山市和县历阳镇佳源中央城商业D1a幢125室 | I88: 一拍 | J88: 成交 | K88: 房产 | L88: 1341360 | M88: 1676700 | N88: 2056360 | O88: 商业用房 | P88: 137.11 | Q88: 0 | S88: 单独所有 | T88: 是 | W88: 未知 | Z88: 0 | AA88: 0 | AB88: 是 | AC88: 2054-3-17 | AD88: （2024）皖0523执恢409号 | AE88: 2023 | AF88: 钢筋混凝土结构 | AK88: 45597.435 | AL88: https://zc-item.taobao.com/auction/839514259822.htm | AM88: =LEN(B88) -> 3 | AN88: 个人
B89: 邓从保 | D89: 和县历阳镇佳源中央城商业D8幢109室 | E89: 安徽省 | F89: 马鞍山市 | G89: 和县 | H89: 安徽省马鞍山市和县历阳镇佳源中央城商业D8幢109室 | I89: 一拍 | J89: 成交 | K89: 房产 | L89: 673200 | M89: 841500 | N89: 861700 | O89: 商业用房 | P89: 93.1 | Q89: 0 | S89: 单独所有 | T89: 是 | W89: 未知 | Z89: 0 | AA89: 0 | AB89: 是 | AC89: 2054-3-17 | AD89: （2024）皖0523执恢409号 | AE89: 2023 | AF89: 钢筋混凝土结构 | AK89: 45597.424 | AL89: https://zc-item.taobao.com/auction/840065968099.htm | AM89: =LEN(B89) -> 3 | AN89: 个人
B90: 濮必花 | D90: 和县历阳镇佳源中央城商业D8幢103室不动产 | E90: 安徽省 | F90: 马鞍山市 | G90: 和县 | H90: 安徽省马鞍山市和县历阳镇佳源中央城商业D8幢103室不动产 | I90: 一拍 | J90: 成交 | K90: 房产 | L90: 673200 | M90: 841500 | N90: 887700 | O90: 商业用房 | P90: 93.1 | Q90: 0 | S90: 单独所有 | T90: 是 | W90: 未知 | Z90: 0 | AA90: 0 | AB90: 是 | AC90: 2054-3-17 | AD90: （2024）皖0523执恢409号 | AE90: 2023 | AF90: 钢筋混凝土结构 | AK90: 45597.42 | AL90: https://zc-item.taobao.com/auction/840065876221.htm | AM90: =LEN(B90) -> 3 | AN90: 个人
B91: 邓从保 | D91: 和县历阳镇佳源中央城商业D8幢110室 | E91: 安徽省 | F91: 马鞍山市 | G91: 和县 | H91: 安徽省马鞍山市和县历阳镇佳源中央城商业D8幢110室 | I91: 一拍 | J91: 成交 | K91: 房产 | L91: 673200 | M91: 841500 | N91: 881200 | O91: 商业用房 | P91: 93.1 | Q91: 0 | S91: 单独所有 | T91: 是 | W91: 未知 | Z91: 0 | AA91: 0 | AB91: 是 | AC91: 2054-3-17 | AD91: （2024）皖0523执恢409号 | AE91: 2023 | AF91: 钢筋混凝土结构 | AK91: 45597.428 | AL91: https://zc-item.taobao.com/auction/839548355706.htm | AM91: =LEN(B91) -> 3 | AN91: 个人
B92: 范文静 | D92: 和县历阳镇佳源中央城商业D8幢102室 | E92: 安徽省 | F92: 马鞍山市 | G92: 和县 | H92: 安徽省马鞍山市和县历阳镇佳源中央城商业D8幢102室 | I92: 一拍 | J92: 成交 | K92: 房产 | L92: 673200 | M92: 841500 | N92: 887700 | O92: 商业用房 | P92: 93.1 | Q92: 0 | S92: 单独所有 | T92: 是 | W92: 未知 | Z92: 0 | AA92: 0 | AB92: 是 | AC92: 2054-3-17 | AD92: （2024）皖0523执恢409号 | AE92: 2023 | AF92: 钢筋混凝土结构 | AK92: 45597.421 | AL92: https://zc-item.taobao.com/auction/839536743090.htm | AM92: =LEN(B92) -> 3 | AN92: 个人
B93: 夏明 | D93: 和县历阳镇佳源中央城商业D1a幢111室不动产 | E93: 安徽省 | F93: 马鞍山市 | G93: 和县 | H93: 安徽省马鞍山市和县历阳镇佳源中央城商业D1a幢111室不动产 | I93: 一拍 | J93: 成交 | K93: 房产 | L93: 1516320 | M93: 1895400 | N93: 2468820 | O93: 商业用房 | P93: 154.99 | Q93: 0 | S93: 单独所有 | T93: 是 | W93: 未知 | Z93: 0 | AA93: 0 | AB93: 是 | AC93: 2054-3-17 | AD93: （2024）皖0523执恢409号 | AE93: 2023 | AF93: 钢筋混凝土结构 | AK93: 45597.428 | AL93: https://zc-item.taobao.com/auction/840037532305.htm | AM93: =LEN(B93) -> 2 | AN93: 个人
B94: 夏明 | D94: 和县历阳镇佳源中央城商业D8幢105室不动产 | E94: 安徽省 | F94: 马鞍山市 | G94: 和县 | H94: 安徽省马鞍山市和县历阳镇佳源中央城商业D8幢105室不动产 | I94: 一拍 | J94: 成交 | K94: 房产 | L94: 673200 | M94: 841500 | N94: 809700 | O94: 商业用房 | P94: 93.1 | Q94: 0 | S94: 单独所有 | T94: 是 | W94: 未知 | Z94: 0 | AA94: 0 | AB94: 是 | AC94: 2054-3-17 | AD94: （2024）皖0523执恢409号 | AE94: 2023 | AF94: 钢筋混凝土结构 | AK94: 45597.423 | AL94: https://zc-item.taobao.com/auction/840066064028.htm | AM94: =LEN(B94) -> 2 | AN94: 个人
B95: 偰永红 | D95: 和县历阳镇佳源中央城商业D1a幢131室不动产 | E95: 安徽省 | F95: 马鞍山市 | G95: 和县 | H95: 安徽省马鞍山市和县历阳镇佳源中央城商业D1a幢131室不动产 | I95: 一拍 | J95: 成交 | K95: 房产 | L95: 916400 | M95: 1145500 | N95: 1375400 | O95: 商业用房 | P95: 103.38 | Q95: 0 | S95: 单独所有 | T95: 是 | W95: 未知 | Z95: 12 | AA95: 0 | AB95: 是 | AC95: 2054-3-17 | AD95: （2024）皖0523执恢409号 | AE95: 2023 | AF95: 钢筋混凝土结构 | AK95: 45597.447 | AL95: https://zc-item.taobao.com/auction/839900869658.htm | AM95: =LEN(B95) -> 3 | AN95: 个人
B96: 王梦醒 | D96: 淮北市相山区南黎路125号锦绣和庄8幢507房产 | E96: 安徽省 | F96: 淮北市 | G96: 相山区 | H96: 安徽省淮北市相山区南黎路125号锦绣和庄8幢507房产 | I96: 一拍 | J96: 成交 | K96: 房产 | L96: 632690.4 | M96: 790863 | N96: 733690.4 | O96: 居住用房 | P96: 119.55 | Q96: 0 | T96: 未知 | W96: 未知 | Y96: 住宅 | Z96: 12 | AA96: 5 | AB96: 未知 | AK96: 45597.444 | AL96: https://zc-item.taobao.com/auction/840021964825.htm | AM96: =LEN(B96) -> 3 | AN96: 个人
B97: 偰永红 | D97: 和县历阳镇佳源中央城商业D1a幢132室不动产 | E97: 安徽省 | F97: 马鞍山市 | G97: 和县 | H97: 安徽省马鞍山市和县历阳镇佳源中央城商业D1a幢132室不动产 | I97: 一拍 | J97: 成交 | K97: 房产 | L97: 916400 | M97: 1145500 | N97: 1384400 | O97: 商业用房 | P97: 103.38 | Q97: 0 | S97: 单独所有 | T97: 是 | W97: 未知 | Z97: 12 | AA97: 0 | AB97: 是 | AC97: 2054-3-17 | AD97: （2024）皖0523执恢409号 | AE97: 2023 | AF97: 钢筋混凝土结构 | AK97: 45597.445 | AL97: https://zc-item.taobao.com/auction/839635510954.htm | AM97: =LEN(B97) -> 3 | AN97: 个人
B98: 赵红 | D98: 安徽省金寨县关庙乡关庙街道裕民路的房产 | E98: 安徽省 | F98: 六安市 | G98: 金寨县 | H98: 安徽省六安市金寨县关庙乡015乡道 | I98: 变卖 | J98: 成交 | K98: 房产 | L98: 194488 | M98: 347300 | N98: 194488 | O98: 商业用房 | P98: 172.8 | Q98: 60 | T98: 未知 | W98: 未知 | Y98: 其他商服用地 | Z98: 3 | AA98: 1 | AB98: 未知 | AE98: 2014 | AK98: 45615.883 | AL98: https://zc-item.taobao.com/auction/835634983741.htm | AM98: =LEN(B98) -> 2 | AN98: 个人
B99: 白伟 | D99: 位于安徽省阜阳市颍东区向阳办幸福中路242号（铁四局二公司二区9#楼）不动产 | E99: 安徽省 | F99: 阜阳市 | G99: 颍东区 | H99: 安徽省阜阳市颍东区向阳办幸福中路242号（铁四局二公司二区9#楼） | I99: 变卖 | J99: 成交 | K99: 房产 | L99: 354000 | M99: 630080 | N99: 354000 | O99: 居住用房 | P99: 84.34 | Q99: 0 | T99: 未知 | W99: 否 | Y99: 城镇住宅用地/住宅 | Z99: 6 | AA99: 1 | AB99: 是 | AD99: 司法裁定 | AK99: 45603.91 | AL99: https://zc-item.taobao.com/auction/837922026035.htm | AM99: =LEN(B99) -> 2 | AN99: 个人
B100: 于东东 | D100: 安徽省阜阳市太和县富裕城8号楼212户 | E100: 安徽省 | F100: 阜阳市 | G100: 太和县 | H100: 安徽省阜阳市太和县富裕城8号楼212户 | I100: 变卖 | J100: 成交 | K100: 房产 | L100: 184892 | M100: 271900 | N100: 184892 | O100: 居住用房 | P100: 91.34 | Q100: 0 | S100: 共同共有 | T100: 未知 | W100: 否 | Y100: 住宅 | Z100: 6 | AA100: 2 | AB100: 是 | AF100: 钢混结构 | AK100: 45635.757 | AL100: https://zc-item.taobao.com/auction/838197457293.htm | AM100: =LEN(B100) -> 3 | AN100: 个人
B101: 王小平 | D101: 安徽省芜湖市鸠江区新华联鸠兹古镇DK04-H-08#楼02室房产 | E101: 安徽省 | F101: 芜湖市 | G101: 鸠江区 | H101: 安徽省芜湖市鸠江区新华联鸠兹古镇DK04-H-08#楼02室 | I101: 变卖 | J101: 成交 | K101: 房产 | L101: 1723344 | M101: 3077400 | N101: 1723344 | O101: 商业用房 | P101: 201.4 | Q101: 0 | T101: 未知 | W101: 否 | Y101: 商业 | Z101: 2 | AA101: 1 | AB101: 是 | AK101: 45626.345 | AL101: https://zc-item.taobao.com/auction/837665433700.htm | AM101: =LEN(B101) -> 3 | AN101: 个人
...

Sheet 抵质押物台账
A1: 抵质押物台账
A2: 序号 | B2: 资产编号 | C2: 是否终极处置 | D2: 债务人名称 | E2: 行业 | F2: 债权本金余额（万元） | G2: 债权利息余额（万元） | H2: 代垫费用余额（万元） | I2: 孳息余额（万元） | J2: 资产原值余额合计（万元） | K2: 担保形式 | L2: 保证人名称 | M2: 收购成本余额（万元） | N2: 抵（质）押物类型（一级） | O2: 抵（质）押物类型（二级） | P2: 抵（质）押物类型（三级） | Q2: 抵（质）押物处置进度 | R2: 抵（质）押人 | S2: 证件号码 | T2: 押品编号 | U2: 抵（质）押物名称 | V2: 他项权利证号/质押登记证明编号 | W2: 产权证或所有权到期日 | X2: 抵（质）押物数量 | Y2: 抵（质）押物计量单位 | Z2: 是否现场勘查 | AA2: 省、市、自治区（省级） | AB2: 市、区、州（地级） | AC2: 县、市、区（县级） | AD2: 详细位置 | AE2: 抵（质）押顺位 | AF2: 担保债权金额（万元） | AG2: 价值确认方式 | AH2: 价值评估基准日 | AI2: 抵（质）押物评估市场价值（万元） | AJ2: 瑕疵情况 | AK2: 瑕疵补充说明 | AL2: 法定优先受偿权情况 | AM2: 法定优先受偿权金额（万元） | AN2: 其他说明 | AO2: 管户经理 | AP2: 分公司 | AQ2: 所属项目 | AR2: 所属项目名称 | AS2: 投放日期 | AT2: 是否需要补录数据 | AU2: 剔除重复押品逻辑 | AV2: 考虑优先受偿和顺位剔除重复押品 | AX2: 匹配数量 不限 | AY2: 匹配数量 机构 | AZ2: 匹配数量 机构+区
A3: 316 | B3: 10240134000100000001 | C3: 否 | D3: 三胞集团有限公司 | E3: 其他未列明信息技术服务业 | F3: 197479.97 | G3: 147868.86 | H3: 17.2557 | I3: 0 | J3: 345366.09 | K3: 信用,抵押,质押,保证 | M3: 26496 | N3: 现房 | O3: 商业用房 | P3: 集中商业（购物中心，综合体商业等） | Q3: 已入库 | R3: 和县龙泉湖旅游开发有限公司 | S3: 2.4966678E8 | T3: 01012025090582043 | U3: 和县香泉镇七联小团山 | V3: 和县他项（2015）第011号 | W3: 商业2044年11月26日，综合2054年11月26日，居住2074年11月26日 | X3: 168660 | Y3: 平方米 | Z3: 是 | AA3: 安徽省 | AB3: 马鞍山市 | AC3: 和县 | AD3: 和县龙泉镇七联小团山 | AE3: 第一顺位 | AF3: 3609 | AG3: 外部评估 | AH3: 45657 | AI3: 1145 | AJ3: 否 | AL3: 不涉及 | AO3: 丁刘惠,俞恺博,史磊,吴中泽,周玲玲,尹苗 | AP3: 江苏分公司 | AQ3: 10240134 | AR3: 商业化收购中行江苏省分行对三胞集团有限公司等3户不良债权包 | AS3: 45657 | AU3: 11001 | AV3: 已剔重 | AX3: =COUNTIFS(拍卖数据!E:E,AA3,拍卖数据!F:F,AB3,拍卖数据!O:O,O3,拍卖数据!P:P,">"&X3*0.8,拍卖数据!P:P,"<"&X3*1.2) -> 0 | AY3: =COUNTIFS(拍卖数据!E:E,AA3,拍卖数据!F:F,AB3,拍卖数据!O:O,O3,拍卖数据!AN:AN,"机构",拍卖数据!P:P,">"&X3*0.8,拍卖数据!P:P,"<"&X3*1.2) -> 0 | AZ3: =COUNTIFS(拍卖数据!E:E,AA3,拍卖数据!F:F,AB3,拍卖数据!G:G,AC3,拍卖数据!O:O,O3,拍卖数据!AN:AN,"机构",拍卖数据!P:P,">"&X3*0.8,拍卖数据!P:P,"<"&X3*1.2) -> 0
A4: 317 | B4: 10240134000100000001 | C4: 否 | D4: 三胞集团有限公司 | E4: 其他未列明信息技术服务业 | F4: 197479.97 | G4: 147868.86 | H4: 17.2557 | I4: 0 | J4: 345366.09 | K4: 信用,抵押,质押,保证 | M4: 26496 | N4: 现房 | O4: 商业用房 | P4: 集中商业（购物中心，综合体商业等） | Q4: 已入库 | R4: 和县龙泉湖旅游开发有限公司 | S4: 2.4966678E8 | T4: 01012025090582042 | U4: 和县香泉镇七联小团山 | V4: 和县他项（2015）第011号 | W4: 旅游2046年5月16日，综合2056年5月16日，居住2076年5月16日 | X4: 286668 | Y4: 平方米 | Z4: 是 | AA4: 安徽省 | AB4: 马鞍山市 | AC4: 和县 | AD4: 和县龙泉镇七联小团山 | AE4: 第一顺位 | AF4: 6163 | AG4: 外部评估 | AH4: 45657 | AI4: 1145 | AJ4: 否 | AL4: 不涉及 | AO4: 丁刘惠,俞恺博,史磊,吴中泽,周玲玲,尹苗 | AP4: 江苏分公司 | AQ4: 10240134 | AR4: 商业化收购中行江苏省分行对三胞集团有限公司等3户不良债权包 | AS4: 45657 | AU4: 11001 | AV4: 已剔重 | AX4: =COUNTIFS(拍卖数据!E:E,AA4,拍卖数据!F:F,AB4,拍卖数据!O:O,O4,拍卖数据!P:P,">"&X4*0.8,拍卖数据!P:P,"<"&X4*1.2) -> 0 | AY4: =COUNTIFS(拍卖数据!E:E,AA4,拍卖数据!F:F,AB4,拍卖数据!O:O,O4,拍卖数据!AN:AN,"机构",拍卖数据!P:P,">"&X4*0.8,拍卖数据!P:P,"<"&X4*1.2) -> 0 | AZ4: =COUNTIFS(拍卖数据!E:E,AA4,拍卖数据!F:F,AB4,拍卖数据!G:G,AC4,拍卖数据!O:O,O4,拍卖数据!AN:AN,"机构",拍卖数据!P:P,">"&X4*0.8,拍卖数据!P:P,"<"&X4*1.2) -> 0
A5: 1044 | B5: 10210269000500000001 | C5: 否 | D5: 上海市兴戎石油制品有限公司 | E5: 石油及制品批发 | F5: 5996.2852 | G5: 1987.9672 | H5: 31.797802 | I5: 0 | J5: 8016.0502 | K5: 抵押,质押,保证 | M5: 52.440165 | N5: 现房 | O5: 商业用房 | P5: 集中商业（购物中心，综合体商业等） | Q5: 已入库 | R5: 安徽省金大陆房地产开发有限公司 | S5: 91340400711045010Q | T5: 01012025082720102 | U5: 安徽省淮南市田家庵区朝阳街道龙湖社区财富中心A区201室 | V5: 淮房地产他证淮田字第15008660号 | W5: 2046年5月8日 | X5: 2333.84 | Y5: 平方米 | Z5: 是 | AA5: 安徽省 | AB5: 淮南市 | AC5: 田家庵区 | AD5: 安徽省淮南市田家庵区朝阳街道龙湖社区财富中心A区201室 | AE5: 第二顺位 | AF5: 5400 | AG5: 内部测算 | AH5: 37590 | AI5: 5400 | AJ5: 否 | AL5: 不涉及 | AO5: 卢端,周若玮,宋灿可,张凯频,朱茜,李梦遥,杜旭东,杨琨(江苏分公司),王楷文,董理,谢宏娟,赵忆忆 | AP5: 江苏分公司 | AQ5: 10210269 | AR5: 商业化收购南京银行对神雾环保技术股份有限公司等8户不良资产包项目 | AS5: 44623 | AU5: 11002 | AV5: 重复内容 | AX5: =COUNTIFS(拍卖数据!E:E,AA5,拍卖数据!F:F,AB5,拍卖数据!O:O,O5,拍卖数据!P:P,">"&X5*0.8,拍卖数据!P:P,"<"&X5*1.2) -> 0 | AY5: =COUNTIFS(拍卖数据!E:E,AA5,拍卖数据!F:F,AB5,拍卖数据!O:O,O5,拍卖数据!AN:AN,"机构",拍卖数据!P:P,">"&X5*0.8,拍卖数据!P:P,"<"&X5*1.2) -> 0 | AZ5: =COUNTIFS(拍卖数据!E:E,AA5,拍卖数据!F:F,AB5,拍卖数据!G:G,AC5,拍卖数据!O:O,O5,拍卖数据!AN:AN,"机构",拍卖数据!P:P,">"&X5*0.8,拍卖数据!P:P,"<"&X5*1.2) -> 0
A6: 1054 | B6: 10210269000400000001 | C6: 否 | D6: 上海市振戎石油有限公司 | E6: 石油及制品批发 | F6: 2971.2007 | G6: 728.63018 | H6: 19.918471 | I6: 0 | J6: 3719.7494 | K6: 抵押,质押 | M6: 1685.0656 | N6: 现房 | O6: 商业用房 | P6: 集中商业（购物中心，综合体商业等） | Q6: 已入库 | R6: 安徽省金大陆房地产开发有限公司 | S6: 91340400711045010Q | T6: 01012025090581618 | U6: 安徽省淮南市田家庵区朝阳街道龙湖社区财富中心A区201室 | V6: 淮房地产他证淮田字第15004667号 | W6: 2046年5月8日 | X6: 2333.84 | Y6: 平方米 | Z6: 是 | AA6: 安徽省 | AB6: 淮南市 | AC6: 田家庵区 | AD6: 安徽省淮南市田家庵区朝阳街道龙湖社区财富中心A区201室 | AE6: 第一顺位 | AF6: 3000 | AG6: 内部测算 | AH6: 44583 | AI6: 8401.82 | AJ6: 否 | AL6: 不涉及 | AO6: 卢端,周若玮,宋灿可,张凯频,朱茜,李梦遥,杜旭东,杨琨(江苏分公司),王楷文,董理,谢宏娟,赵忆忆 | AP6: 江苏分公司 | AQ6: 10210269 | AR6: 商业化收购南京银行对神雾环保技术股份有限公司等8户不良资产包项目 | AS6: 44623 | AU6: 11001 | AV6: 已剔重 | AX6: =COUNTIFS(拍卖数据!E:E,AA6,拍卖数据!F:F,AB6,拍卖数据!O:O,O6,拍卖数据!P:P,">"&X6*0.8,拍卖数据!P:P,"<"&X6*1.2) -> 0 | AY6: =COUNTIFS(拍卖数据!E:E,AA6,拍卖数据!F:F,AB6,拍卖数据!O:O,O6,拍卖数据!AN:AN,"机构",拍卖数据!P:P,">"&X6*0.8,拍卖数据!P:P,"<"&X6*1.2) -> 0 | AZ6: =COUNTIFS(拍卖数据!E:E,AA6,拍卖数据!F:F,AB6,拍卖数据!G:G,AC6,拍卖数据!O:O,O6,拍卖数据!AN:AN,"机构",拍卖数据!P:P,">"&X6*0.8,拍卖数据!P:P,"<"&X6*1.2) -> 0
A7: 1822 | B7: 33253010010001 | C7: 否 | D7: 上海鑫泰房地产发展有限公司 | E7: 房地产业 | F7: 33560 | G7: 11864.392 | H7: 0 | J7: 45424.392 | K7: 抵押,质押,保证 | L7: 天津港天房地产投资有限公司,恒盛地产控股有限公司,恒盛天行建(天津)房地产投资有限公司,恒盛汇鑫(长春)置业有限公司,恒盛阳光鑫地(北京)置业有限公司 | M7: 9000 | N7: 现房 | O7: 商业用房 | P7: 独立商铺 | Q7: 新建 | R7: 恒盛恒茂（合肥）房地产开发有限公司 | S7: 913401006679174820 | T7: 01012025091631379 | U7: 安徽省合肥市瑶海区芜湖路2号坝上街环球中心C1R1幢商309 | V7: 皖（2021）合肥市不动产证明第11057767号 | W7: 2048/12/24 | X7: 864.82 | Y7: 平方米 | Z7: 是 | AA7: 安徽省 | AB7: 合肥市 | AC7: 瑶海区 | AD7: 芜湖路2号 | AE7: 第一顺位 | AG7: 外部评估 | AH7: 45800 | AI7: 558 | AJ7: 否 | AL7: 不涉及 | AO7: 刘瑛晖,卢涛,郑舒元 | AP7: 上海自贸区分公司 | AQ7: 33253010 | AR7: 收购爱建信托对鑫泰公司不良债权并反委托项目 | AS7: 45862 | AU7: 11001 | AV7: 已剔重 | AX7: =COUNTIFS(拍卖数据!E:E,AA7,拍卖数据!F:F,AB7,拍卖数据!O:O,O7,拍卖数据!P:P,">"&X7*0.8,拍卖数据!P:P,"<"&X7*1.2) -> 8 | AY7: =COUNTIFS(拍卖数据!E:E,AA7,拍卖数据!F:F,AB7,拍卖数据!O:O,O7,拍卖数据!AN:AN,"机构",拍卖数据!P:P,">"&X7*0.8,拍卖数据!P:P,"<"&X7*1.2) -> 3 | AZ7: =COUNTIFS(拍卖数据!E:E,AA7,拍卖数据!F:F,AB7,拍卖数据!G:G,AC7,拍卖数据!O:O,O7,拍卖数据!AN:AN,"机构",拍卖数据!P:P,">"&X7*0.8,拍卖数据!P:P,"<"&X7*1.2) -> 0
A8: 1901 | B8: 33253010010001 | C8: 否 | D8: 上海鑫泰房地产发展有限公司 | E8: 房地产业 | F8: 33560 | G8: 11864.392 | H8: 0 | J8: 45424.392 | K8: 抵押,质押,保证 | L8: 天津港天房地产投资有限公司,恒盛地产控股有限公司,恒盛天行建(天津)房地产投资有限公司,恒盛汇鑫(长春)置业有限公司,恒盛阳光鑫地(北京)置业有限公司 | M8: 9000 | N8: 现房 | O8: 商业用房 | P8: 独立商铺 | Q8: 新建 | R8: 恒盛恒茂（合肥）房地产开发有限公司 | S8: 913401006679174820 | T8: 01012025091631378 | U8: 安徽省合肥市瑶海区芜湖路2号坝上街环球中心C1R1幢商308 | V8: 皖（2021）合肥市不动产证明第11057767号 | W8: 2048/12/24 | X8: 102.12 | Y8: 平方米 | Z8: 是 | AA8: 安徽省 | AB8: 合肥市 | AC8: 瑶海区 | AD8: 芜湖路2号 | AE8: 第一顺位 | AG8: 外部评估 | AH8: 45800 | AI8: 69 | AJ8: 否 | AL8: 不涉及 | AO8: 刘瑛晖,卢涛,郑舒元 | AP8: 上海自贸区分公司 | AQ8: 33253010 | AR8: 收购爱建信托对鑫泰公司不良债权并反委托项目 | AS8: 45862 | AU8: 11001 | AV8: 已剔重 | AX8: =COUNTIFS(拍卖数据!E:E,AA8,拍卖数据!F:F,AB8,拍卖数据!O:O,O8,拍卖数据!P:P,">"&X8*0.8,拍卖数据!P:P,"<"&X8*1.2) -> 43 | AY8: =COUNTIFS(拍卖数据!E:E,AA8,拍卖数据!F:F,AB8,拍卖数据!O:O,O8,拍卖数据!AN:AN,"机构",拍卖数据!P:P,">"&X8*0.8,拍卖数据!P:P,"<"&X8*1.2) -> 4 | AZ8: =COUNTIFS(拍卖数据!E:E,AA8,拍卖数据!F:F,AB8,拍卖数据!G:G,AC8,拍卖数据!O:O,O8,拍卖数据!AN:AN,"机构",拍卖数据!P:P,">"&X8*0.8,拍卖数据!P:P,"<"&X8*1.2) -> 3
A9: 1902 | B9: 33253010010001 | C9: 否 | D9: 上海鑫泰房地产发展有限公司 | E9: 房地产业 | F9: 33560 | G9: 11864.392 | H9: 0 | J9: 45424.392 | K9: 抵押,质押,保证 | L9: 天津港天房地产投资有限公司,恒盛地产控股有限公司,恒盛天行建(天津)房地产投资有限公司,恒盛汇鑫(长春)置业有限公司,恒盛阳光鑫地(北京)置业有限公司 | M9: 9000 | N9: 现房 | O9: 商业用房 | P9: 独立商铺 | Q9: 新建 | R9: 恒盛恒茂（合肥）房地产开发有限公司 | S9: 913401006679174820 | T9: 01012025091631377 | U9: 安徽省合肥市瑶海区芜湖路2号坝上街环球中心C1R1幢商307 | V9: 皖（2021）合肥市不动产证明第11057767号 | W9: 2048/12/24 | X9: 155.27 | Y9: 平方米 | Z9: 是 | AA9: 安徽省 | AB9: 合肥市 | AC9: 瑶海区 | AD9: 芜湖路2号 | AE9: 第一顺位 | AG9: 外部评估 | AH9: 45800 | AI9: 104 | AJ9: 否 | AL9: 不涉及 | AO9: 刘瑛晖,卢涛,郑舒元 | AP9: 上海自贸区分公司 | AQ9: 33253010 | AR9: 收购爱建信托对鑫泰公司不良债权并反委托项目 | AS9: 45862 | AU9: 11001 | AV9: 已剔重 | AX9: =COUNTIFS(拍卖数据!E:E,AA9,拍卖数据!F:F,AB9,拍卖数据!O:O,O9,拍卖数据!P:P,">"&X9*0.8,拍卖数据!P:P,"<"&X9*1.2) -> 35 | AY9: =COUNTIFS(拍卖数据!E:E,AA9,拍卖数据!F:F,AB9,拍卖数据!O:O,O9,拍卖数据!AN:AN,"机构",拍卖数据!P:P,">"&X9*0.8,拍卖数据!P:P,"<"&X9*1.2) -> 4 | AZ9: =COUNTIFS(拍卖数据!E:E,AA9,拍卖数据!F:F,AB9,拍卖数据!G:G,AC9,拍卖数据!O:O,O9,拍卖数据!AN:AN,"机构",拍卖数据!P:P,">"&X9*0.8,拍卖数据!P:P,"<"&X9*1.2) -> 0
A10: 1903 | B10: 33253010010001 | C10: 否 | D10: 上海鑫泰房地产发展有限公司 | E10: 房地产业 | F10: 33560 | G10: 11864.392 | H10: 0 | J10: 45424.392 | K10: 抵押,质押,保证 | L10: 天津港天房地产投资有限公司,恒盛地产控股有限公司,恒盛天行建(天津)房地产投资有限公司,恒盛汇鑫(长春)置业有限公司,恒盛阳光鑫地(北京)置业有限公司 | M10: 9000 | N10: 现房 | O10: 商业用房 | P10: 独立商铺 | Q10: 新建 | R10: 恒盛恒茂（合肥）房地产开发有限公司 | S10: 913401006679174820 | T10: 01012025091631376 | U10: 安徽省合肥市瑶海区芜湖路2号坝上街环球中心C1R1幢商306 | V10: 皖（2021）合肥市不动产证明第11057767号 | W10: 2048/12/24 | X10: 318.96 | Y10: 平方米 | Z10: 是 | AA10: 安徽省 | AB10: 合肥市 | AC10: 瑶海区 | AD10: 芜湖路2号 | AE10: 第一顺位 | AG10: 外部评估 | AH10: 45800 | AI10: 214 | AJ10: 否 | AL10: 不涉及 | AO10: 刘瑛晖,卢涛,郑舒元 | AP10: 上海自贸区分公司 | AQ10: 33253010 | AR10: 收购爱建信托对鑫泰公司不良债权并反委托项目 | AS10: 45862 | AU10: 11001 | AV10: 已剔重 | AX10: =COUNTIFS(拍卖数据!E:E,AA10,拍卖数据!F:F,AB10,拍卖数据!O:O,O10,拍卖数据!P:P,">"&X10*0.8,拍卖数据!P:P,"<"&X10*1.2) -> 22 | AY10: =COUNTIFS(拍卖数据!E:E,AA10,拍卖数据!F:F,AB10,拍卖数据!O:O,O10,拍卖数据!AN:AN,"机构",拍卖数据!P:P,">"&X10*0.8,拍卖数据!P:P,"<"&X10*1.2) -> 4 | AZ10: =COUNTIFS(拍卖数据!E:E,AA10,拍卖数据!F:F,AB10,拍卖数据!G:G,AC10,拍卖数据!O:O,O10,拍卖数据!AN:AN,"机构",拍卖数据!P:P,">"&X10*0.8,拍卖数据!P:P,"<"&X10*1.2) -> 2
A11: 1904 | B11: 33253010010001 | C11: 否 | D11: 上海鑫泰房地产发展有限公司 | E11: 房地产业 | F11: 33560 | G11: 11864.392 | H11: 0 | J11: 45424.392 | K11: 抵押,质押,保证 | L11: 天津港天房地产投资有限公司,恒盛地产控股有限公司,恒盛天行建(天津)房地产投资有限公司,恒盛汇鑫(长春)置业有限公司,恒盛阳光鑫地(北京)置业有限公司 | M11: 9000 | N11: 现房 | O11: 商业用房 | P11: 独立商铺 | Q11: 新建 | R11: 恒盛恒茂（合肥）房地产开发有限公司 | S11: 913401006679174820 | T11: 01012025091631375 | U11: 安徽省合肥市瑶海区芜湖路2号坝上街环球中心C1R1幢商305 | V11: 皖（2021）合肥市不动产证明第11057767号 | W11: 2048/12/24 | X11: 161.03 | Y11: 平方米 | Z11: 是 | AA11: 安徽省 | AB11: 合肥市 | AC11: 瑶海区 | AD11: 芜湖路2号 | AE11: 第一顺位 | AG11: 外部评估 | AH11: 45800 | AI11: 108 | AJ11: 否 | AL11: 不涉及 | AO11: 刘瑛晖,卢涛,郑舒元 | AP11: 上海自贸区分公司 | AQ11: 33253010 | AR11: 收购爱建信托对鑫泰公司不良债权并反委托项目 | AS11: 45862 | AU11: 11001 | AV11: 已剔重 | AX11: =COUNTIFS(拍卖数据!E:E,AA11,拍卖数据!F:F,AB11,拍卖数据!O:O,O11,拍卖数据!P:P,">"&X11*0.8,拍卖数据!P:P,"<"&X11*1.2) -> 31 | AY11: =COUNTIFS(拍卖数据!E:E,AA11,拍卖数据!F:F,AB11,拍卖数据!O:O,O11,拍卖数据!AN:AN,"机构",拍卖数据!P:P,">"&X11*0.8,拍卖数据!P:P,"<"&X11*1.2) -> 2 | AZ11: =COUNTIFS(拍卖数据!E:E,AA11,拍卖数据!F:F,AB11,拍卖数据!G:G,AC11,拍卖数据!O:O,O11,拍卖数据!AN:AN,"机构",拍卖数据!P:P,">"&X11*0.8,拍卖数据!P:P,"<"&X11*1.2) -> 0
A12: 1905 | B12: 33253010010001 | C12: 否 | D12: 上海鑫泰房地产发展有限公司 | E12: 房地产业 | F12: 33560 | G12: 11864.392 | H12: 0 | J12: 45424.392 | K12: 抵押,质押,保证 | L12: 天津港天房地产投资有限公司,恒盛地产控股有限公司,恒盛天行建(天津)房地产投资有限公司,恒盛汇鑫(长春)置业有限公司,恒盛阳光鑫地(北京)置业有限公司 | M12: 9000 | N12: 现房 | O12: 商业用房 | P12: 独立商铺 | Q12: 新建 | R12: 恒盛恒茂（合肥）房地产开发有限公司 | S12: 913401006679174820 | T12: 01012025091631374 | U12: 安徽省合肥市瑶海区芜湖路2号坝上街环球中心C1R1幢商304 | V12: 皖（2021）合肥市不动产证明第11057767号 | W12: 2048/12/24 | X12: 2415.8 | Y12: 平方米 | Z12: 是 | AA12: 安徽省 | AB12: 合肥市 | AC12: 瑶海区 | AD12: 芜湖路2号 | AE12: 第一顺位 | AG12: 外部评估 | AH12: 45800 | AI12: 1429 | AJ12: 否 | AL12: 不涉及 | AO12: 刘瑛晖,卢涛,郑舒元 | AP12: 上海自贸区分公司 | AQ12: 33253010 | AR12: 收购爱建信托对鑫泰公司不良债权并反委托项目 | AS12: 45862 | AU12: 11001 | AV12: 已剔重 | AX12: =COUNTIFS(拍卖数据!E:E,AA12,拍卖数据!F:F,AB12,拍卖数据!O:O,O12,拍卖数据!P:P,">"&X12*0.8,拍卖数据!P:P,"<"&X12*1.2) -> 0 | AY12: =COUNTIFS(拍卖数据!E:E,AA12,拍卖数据!F:F,AB12,拍卖数据!O:O,O12,拍卖数据!AN:AN,"机构",拍卖数据!P:P,">"&X12*0.8,拍卖数据!P:P,"<"&X12*1.2) -> 0 | AZ12: =COUNTIFS(拍卖数据!E:E,AA12,拍卖数据!F:F,AB12,拍卖数据!G:G,AC12,拍卖数据!O:O,O12,拍卖数据!AN:AN,"机构",拍卖数据!P:P,">"&X12*0.8,拍卖数据!P:P,"<"&X12*1.2) -> 0
A13: 1906 | B13: 33253010010001 | C13: 否 | D13: 上海鑫泰房地产发展有限公司 | E13: 房地产业 | F13: 33560 | G13: 11864.392 | H13: 0 | J13: 45424.392 | K13: 抵押,质押,保证 | L13: 天津港天房地产投资有限公司,恒盛地产控股有限公司,恒盛天行建(天津)房地产投资有限公司,恒盛汇鑫(长春)置业有限公司,恒盛阳光鑫地(北京)置业有限公司 | M13: 9000 | N13: 现房 | O13: 商业用房 | P13: 独立商铺 | Q13: 新建 | R13: 恒盛恒茂（合肥）房地产开发有限公司 | S13: 913401006679174820 | T13: 01012025091631373 | U13: 安徽省合肥市瑶海区芜湖路2号坝上街环球中心C1R1幢商303 | V13: 皖（2021）合肥市不动产证明第11057767号 | W13: 2048/12/24 | X13: 1242.86 | Y13: 平方米 | Z13: 是 | AA13: 安徽省 | AB13: 合肥市 | AC13: 瑶海区 | AD13: 芜湖路2号 | AE13: 第一顺位 | AG13: 外部评估 | AH13: 45800 | AI13: 768 | AJ13: 否 | AL13: 不涉及 | AO13: 刘瑛晖,卢涛,郑舒元 | AP13: 上海自贸区分公司 | AQ13: 33253010 | AR13: 收购爱建信托对鑫泰公司不良债权并反委托项目 | AS13: 45862 | AU13: 11001 | AV13: 已剔重 | AX13: =COUNTIFS(拍卖数据!E:E,AA13,拍卖数据!F:F,AB13,拍卖数据!O:O,O13,拍卖数据!P:P,">"&X13*0.8,拍卖数据!P:P,"<"&X13*1.2) -> 5 | AY13: =COUNTIFS(拍卖数据!E:E,AA13,拍卖数据!F:F,AB13,拍卖数据!O:O,O13,拍卖数据!AN:AN,"机构",拍卖数据!P:P,">"&X13*0.8,拍卖数据!P:P,"<"&X13*1.2) -> 3 | AZ13: =COUNTIFS(拍卖数据!E:E,AA13,拍卖数据!F:F,AB13,拍卖数据!G:G,AC13,拍卖数据!O:O,O13,拍卖数据!AN:AN,"机构",拍卖数据!P:P,">"&X13*0.8,拍卖数据!P:P,"<"&X13*1.2) -> 0
A14: 1907 | B14: 33253010010001 | C14: 否 | D14: 上海鑫泰房地产发展有限公司 | E14: 房地产业 | F14: 33560 | G14: 11864.392 | H14: 0 | J14: 45424.392 | K14: 抵押,质押,保证 | L14: 天津港天房地产投资有限公司,恒盛地产控股有限公司,恒盛天行建(天津)房地产投资有限公司,恒盛汇鑫(长春)置业有限公司,恒盛阳光鑫地(北京)置业有限公司 | M14: 9000 | N14: 现房 | O14: 商业用房 | P14: 独立商铺 | Q14: 新建 | R14: 恒盛恒茂（合肥）房地产开发有限公司 | S14: 913401006679174820 | T14: 01012025091631372 | U14: 安徽省合肥市瑶海区芜湖路2号坝上街环球中心C1R1幢商302 | V14: 皖（2021）合肥市不动产证明第11057767号 | W14: 2048/12/24 | X14: 79.89 | Y14: 平方米 | Z14: 是 | AA14: 安徽省 | AB14: 合肥市 | AC14: 瑶海区 | AD14: 芜湖路2号 | AE14: 第一顺位 | AG14: 外部评估 | AH14: 45800 | AI14: 54 | AJ14: 否 | AL14: 不涉及 | AO14: 刘瑛晖,卢涛,郑舒元 | AP14: 上海自贸区分公司 | AQ14: 33253010 | AR14: 收购爱建信托对鑫泰公司不良债权并反委托项目 | AS14: 45862 | AU14: 11001 | AV14: 已剔重 | AX14: =COUNTIFS(拍卖数据!E:E,AA14,拍卖数据!F:F,AB14,拍卖数据!O:O,O14,拍卖数据!P:P,">"&X14*0.8,拍卖数据!P:P,"<"&X14*1.2) -> 80 | AY14: =COUNTIFS(拍卖数据!E:E,AA14,拍卖数据!F:F,AB14,拍卖数据!O:O,O14,拍卖数据!AN:AN,"机构",拍卖数据!P:P,">"&X14*0.8,拍卖数据!P:P,"<"&X14*1.2) -> 6 | AZ14: =COUNTIFS(拍卖数据!E:E,AA14,拍卖数据!F:F,AB14,拍卖数据!G:G,AC14,拍卖数据!O:O,O14,拍卖数据!AN:AN,"机构",拍卖数据!P:P,">"&X14*0.8,拍卖数据!P:P,"<"&X14*1.2) -> 2
A15: 1908 | B15: 33253010010001 | C15: 否 | D15: 上海鑫泰房地产发展有限公司 | E15: 房地产业 | F15: 33560 | G15: 11864.392 | H15: 0 | J15: 45424.392 | K15: 抵押,质押,保证 | L15: 天津港天房地产投资有限公司,恒盛地产控股有限公司,恒盛天行建(天津)房地产投资有限公司,恒盛汇鑫(长春)置业有限公司,恒盛阳光鑫地(北京)置业有限公司 | M15: 9000 | N15: 现房 | O15: 商业用房 | P15: 独立商铺 | Q15: 新建 | R15: 恒盛恒茂（合肥）房地产开发有限公司 | S15: 913401006679174820 | T15: 01012025091631371 | U15: 安徽省合肥市瑶海区芜湖路2号坝上街环球中心C1R1幢商301 | V15: 皖（2021）合肥市不动产证明第11057767号 | W15: 2048/12/24 | X15: 418.56 | Y15: 平方米 | Z15: 是 | AA15: 安徽省 | AB15: 合肥市 | AC15: 瑶海区 | AD15: 芜湖路2号 | AE15: 第一顺位 | AG15: 外部评估 | AH15: 45800 | AI15: 281 | AJ15: 否 | AL15: 不涉及 | AO15: 刘瑛晖,卢涛,郑舒元 | AP15: 上海自贸区分公司 | AQ15: 33253010 | AR15: 收购爱建信托对鑫泰公司不良债权并反委托项目 | AS15: 45862 | AU15: 11001 | AV15: 已剔重 | AX15: =COUNTIFS(拍卖数据!E:E,AA15,拍卖数据!F:F,AB15,拍卖数据!O:O,O15,拍卖数据!P:P,">"&X15*0.8,拍卖数据!P:P,"<"&X15*1.2) -> 4 | AY15: =COUNTIFS(拍卖数据!E:E,AA15,拍卖数据!F:F,AB15,拍卖数据!O:O,O15,拍卖数据!AN:AN,"机构",拍卖数据!P:P,">"&X15*0.8,拍卖数据!P:P,"<"&X15*1.2) -> 1 | AZ15: =COUNTIFS(拍卖数据!E:E,AA15,拍卖数据!F:F,AB15,拍卖数据!G:G,AC15,拍卖数据!O:O,O15,拍卖数据!AN:AN,"机构",拍卖数据!P:P,">"&X15*0.8,拍卖数据!P:P,"<"&X15*1.2) -> 1
A16: 1909 | B16: 33253010010001 | C16: 否 | D16: 上海鑫泰房地产发展有限公司 | E16: 房地产业 | F16: 33560 | G16: 11864.392 | H16: 0 | J16: 45424.392 | K16: 抵押,质押,保证 | L16: 天津港天房地产投资有限公司,恒盛地产控股有限公司,恒盛天行建(天津)房地产投资有限公司,恒盛汇鑫(长春)置业有限公司,恒盛阳光鑫地(北京)置业有限公司 | M16: 9000 | N16: 现房 | O16: 商业用房 | P16: 独立商铺 | Q16: 新建 | R16: 恒盛恒茂（合肥）房地产开发有限公司 | S16: 913401006679174820 | T16: 01012025091631370 | U16: 安徽省合肥市瑶海区芜湖路2号坝上街环球中心C1R1幢商219 | V16: 皖（2021）合肥市不动产证明第11057767号 | W16: 2048/12/24 | X16: 204.42 | Y16: 平方米 | Z16: 是 | AA16: 安徽省 | AB16: 合肥市 | AC16: 瑶海区 | AD16: 芜湖路2号 | AE16: 第一顺位 | AG16: 外部评估 | AH16: 45800 | AI16: 157 | AJ16: 否 | AL16: 不涉及 | AO16: 刘瑛晖,卢涛,郑舒元 | AP16: 上海自贸区分公司 | AQ16: 33253010 | AR16: 收购爱建信托对鑫泰公司不良债权并反委托项目 | AS16: 45862 | AU16: 11001 | AV16: 已剔重 | AX16: =COUNTIFS(拍卖数据!E:E,AA16,拍卖数据!F:F,AB16,拍卖数据!O:O,O16,拍卖数据!P:P,">"&X16*0.8,拍卖数据!P:P,"<"&X16*1.2) -> 22 | AY16: =COUNTIFS(拍卖数据!E:E,AA16,拍卖数据!F:F,AB16,拍卖数据!O:O,O16,拍卖数据!AN:AN,"机构",拍卖数据!P:P,">"&X16*0.8,拍卖数据!P:P,"<"&X16*1.2) -> 1 | AZ16: =COUNTIFS(拍卖数据!E:E,AA16,拍卖数据!F:F,AB16,拍卖数据!G:G,AC16,拍卖数据!O:O,O16,拍卖数据!AN:AN,"机构",拍卖数据!P:P,">"&X16*0.8,拍卖数据!P:P,"<"&X16*1.2) -> 0
A17: 1910 | B17: 33253010010001 | C17: 否 | D17: 上海鑫泰房地产发展有限公司 | E17: 房地产业 | F17: 33560 | G17: 11864.392 | H17: 0 | J17: 45424.392 | K17: 抵押,质押,保证 | L17: 天津港天房地产投资有限公司,恒盛地产控股有限公司,恒盛天行建(天津)房地产投资有限公司,恒盛汇鑫(长春)置业有限公司,恒盛阳光鑫地(北京)置业有限公司 | M17: 9000 | N17: 现房 | O17: 商业用房 | P17: 独立商铺 | Q17: 新建 | R17: 恒盛恒茂（合肥）房地产开发有限公司 | S17: 913401006679174820 | T17: 01012025091631369 | U17: 安徽省合肥市瑶海区芜湖路2号坝上街环球中心C1R1幢商218 | V17: 皖（2021）合肥市不动产证明第11057767号 | W17: 2048/12/24 | X17: 99.51 | Y17: 平方米 | Z17: 是 | AA17: 安徽省 | AB17: 合肥市 | AC17: 瑶海区 | AD17: 芜湖路2号 | AE17: 第一顺位 | AG17: 外部评估 | AH17: 45800 | AI17: 76 | AJ17: 否 | AL17: 不涉及 | AO17: 刘瑛晖,卢涛,郑舒元 | AP17: 上海自贸区分公司 | AQ17: 33253010 | AR17: 收购爱建信托对鑫泰公司不良债权并反委托项目 | AS17: 45862 | AU17: 11001 | AV17: 已剔重 | AX17: =COUNTIFS(拍卖数据!E:E,AA17,拍卖数据!F:F,AB17,拍卖数据!O:O,O17,拍卖数据!P:P,">"&X17*0.8,拍卖数据!P:P,"<"&X17*1.2) -> 47 | AY17: =COUNTIFS(拍卖数据!E:E,AA17,拍卖数据!F:F,AB17,拍卖数据!O:O,O17,拍卖数据!AN:AN,"机构",拍卖数据!P:P,">"&X17*0.8,拍卖数据!P:P,"<"&X17*1.2) -> 4 | AZ17: =COUNTIFS(拍卖数据!E:E,AA17,拍卖数据!F:F,AB17,拍卖数据!G:G,AC17,拍卖数据!O:O,O17,拍卖数据!AN:AN,"机构",拍卖数据!P:P,">"&X17*0.8,拍卖数据!P:P,"<"&X17*1.2) -> 3
A18: 1911 | B18: 33253010010001 | C18: 否 | D18: 上海鑫泰房地产发展有限公司 | E18: 房地产业 | F18: 33560 | G18: 11864.392 | H18: 0 | J18: 45424.392 | K18: 抵押,质押,保证 | L18: 天津港天房地产投资有限公司,恒盛地产控股有限公司,恒盛天行建(天津)房地产投资有限公司,恒盛汇鑫(长春)置业有限公司,恒盛阳光鑫地(北京)置业有限公司 | M18: 9000 | N18: 现房 | O18: 商业用房 | P18: 独立商铺 | Q18: 新建 | R18: 恒盛恒茂（合肥）房地产开发有限公司 | S18: 913401006679174820 | T18: 01012025091631368 | U18: 安徽省合肥市瑶海区芜湖路2号坝上街环球中心C1R1幢商217 | V18: 皖（2021）合肥市不动产证明第11057767号 | W18: 2048/12/24 | X18: 139.51 | Y18: 平方米 | Z18: 是 | AA18: 安徽省 | AB18: 合肥市 | AC18: 瑶海区 | AD18: 芜湖路2号 | AE18: 第一顺位 | AG18: 外部评估 | AH18: 45800 | AI18: 107 | AJ18: 否 | AL18: 不涉及 | AO18: 刘瑛晖,卢涛,郑舒元 | AP18: 上海自贸区分公司 | AQ18: 33253010 | AR18: 收购爱建信托对鑫泰公司不良债权并反委托项目 | AS18: 45862 | AU18: 11001 | AV18: 已剔重 | AX18: =COUNTIFS(拍卖数据!E:E,AA18,拍卖数据!F:F,AB18,拍卖数据!O:O,O18,拍卖数据!P:P,">"&X18*0.8,拍卖数据!P:P,"<"&X18*1.2) -> 33 | AY18: =COUNTIFS(拍卖数据!E:E,AA18,拍卖数据!F:F,AB18,拍卖数据!O:O,O18,拍卖数据!AN:AN,"机构",拍卖数据!P:P,">"&X18*0.8,拍卖数据!P:P,"<"&X18*1.2) -> 5 | AZ18: =COUNTIFS(拍卖数据!E:E,AA18,拍卖数据!F:F,AB18,拍卖数据!G:G,AC18,拍卖数据!O:O,O18,拍卖数据!AN:AN,"机构",拍卖数据!P:P,">"&X18*0.8,拍卖数据!P:P,"<"&X18*1.2) -> 0
... A78: 1973 | B78: 33253010010001 | C78: 否 | D78: 上海鑫泰房地产发展有限公司 | E78: 房地产业 | F78: 33560 | G78: 11864.392 | H78: 0 | J78: 45424.392 | K78: 抵押,质押,保证 | L78: 天津港天房地产投资有限公司,恒盛地产控股有限公司,恒盛天行建(天津)房地产投资有限公司,恒盛汇鑫(长春)置业有限公司,恒盛阳光鑫地(北京)置业有限公司 | M78: 9000 | N78: 现房 | O78: 商业用房 | P78: 独立商铺 | Q78: 新建 | R78: 恒盛恒茂（合肥）房地产开发有限公司 | S78: 913401006679174820 | T78: 01012025091631380 | U78: 安徽省合肥市瑶海区芜湖路2号坝上街环球中心C1R1幢商401 | V78: 皖（2021）合肥市不动产证明第11057767号 | W78: 2048/12/24 | X78: 362.78 | Y78: 平方米 | Z78: 是 | AA78: 安徽省 | AB78: 合肥市 | AC78: 瑶海区 | AD78: 芜湖路2号 | AE78: 第一顺位 | AG78: 外部评估 | AH78: 45800 | AI78: 209 | AJ78: 否 | AL78: 不涉及 | AO78: 刘瑛晖,卢涛,郑舒元 | AP78: 上海自贸区分公司 | AQ78: 33253010 | AR78: 收购爱建信托对鑫泰公司不良债权并反委托项目 | AS78: 45862 | AU78: 11001 | AV78: 已剔重 | AX78: =COUNTIFS(拍卖数据!E:E,AA78,拍卖数据!F:F,AB78,拍卖数据!O:O,O78,拍卖数据!P:P,">"&X78*0.8,拍卖数据!P:P,"<"&X78*1.2) -> 8 | AY78: =COUNTIFS(拍卖数据!E:E,AA78,拍卖数据!F:F,AB78,拍卖数据!O:O,O78,拍卖数据!AN:AN,"机构",拍卖数据!P:P,">"&X78*0.8,拍卖数据!P:P,"<"&X78*1.2) -> 2 | AZ78: =COUNTIFS(拍卖数据!E:E,AA78,拍卖数据!F:F,AB78,拍卖数据!G:G,AC78,拍卖数据!O:O,O78,拍卖数据!AN:AN,"机构",拍卖数据!P:P,">"&X78*0.8,拍卖数据!P:P,"<"&X78*1.2) -> 2
A79: 2094 | B79: 09180125000700000001 | C79: 否 | D79: 上海龙德资源股份有限公司 | E79: 金属及金属矿批发 | F79: 6317.6904 | G79: 1512.301 | H79: 0 | I79: 0 | J79: 7829.9914 | K79: 抵押,保证 | L79: 广东振戎能源有限公司 | M79: 2574.1348 | N79: 现房 | O79: 商业用房 | P79: 集中商业（购物中心，综合体商业等） | Q79: 新建 | R79: 安徽省金大陆房地产开发有限公司 | S79: 91340400711045010Q | T79: 01012025081220008 | U79: 安徽省淮南市田家庵区朝阳街道龙湖社区财富中心B区101室的商业地产 | V79: 淮房地产他证淮田字第1421618号 | W79: 2046/5/8 | X79: 2745.22 | Y79: 平方米 | Z79: 是 | AA79: 安徽省 | AB79: 淮南市 | AC79: 田家庵区 | AD79: 田家庵区朝阳街道龙湖社区财富中心B区101室 | AE79: 第一顺位 | AF79: 10000 | AG79: 内部测算 | AH79: 43415 | AI79: 6902.5502 | AJ79: 是 | AK79: A01.押品非首位查封 | AL79: 不涉及 | AO79: 吴薇(上海分公司),张咏梅,徐工婷,杨晓峰,沈家伦,王军(上海分公司),蔡薇,邓秋韵,郦亨利 | AP79: 上海分公司 | AQ79: 09180125 | AR79: 商业化收购中信银行上海分行对上海常信实业有限公司等17户不良资产项目 | AS79: 43440 | AU79: 11001 | AV79: 已剔重 | AX79: =COUNTIFS(拍卖数据!E:E,AA79,拍卖数据!F:F,AB79,拍卖数据!O:O,O79,拍卖数据!P:P,">"&X79*0.8,拍卖数据!P:P,"<"&X79*1.2) -> 0 | AY79: =COUNTIFS(拍卖数据!E:E,AA79,拍卖数据!F:F,AB79,拍卖数据!O:O,O79,拍卖数据!AN:AN,"机构",拍卖数据!P:P,">"&X79*0.8,拍卖数据!P:P,"<"&X79*1.2) -> 0 | AZ79: =COUNTIFS(拍卖数据!E:E,AA79,拍卖数据!F:F,AB79,拍卖数据!G:G,AC79,拍卖数据!O:O,O79,拍卖数据!AN:AN,"机构",拍卖数据!P:P,">"&X79*0.8,拍卖数据!P:P,"<"&X79*1.2) -> 0
A80: 4161 | B80: 12190065002100000001 | C80: 否 | D80: 中建永顺集团有限公司 | E80: 园林绿化工程施工 | F80: 630 | G80: 108.96453 | H80: 0 | I80: 0 | J80: 738.96453 | K80: 抵押,质押,保证 | M80: 410.22393 | N80: 现房 | O80: 商业用房 | P80: 集中商业（购物中心，综合体商业等） | Q80: 新建 | R80: 中建永顺集团有限公司 | S80: 913411036849594573 | T80: 01012025081220436 | U80: 定远县定城镇东城南路绿园小区30幢1-5至1-12 室皖（2016）定远县不动产权第0004884号 | V80: 皖（2016）定远县不动产证明第0008753号 | W80: 2047/1/1 | X80: 1109.34 | Y80: 平方米 | Z80: 是 | AA80: 安徽省 | AB80: 滁州市 | AC80: 定远县 | AD80: 定远县定城镇东城南路绿园小区30幢1-5至1-12 室 | AE80: 第一顺位 | AF80: 3671.02 | AG80: 外部评估 | AH80: 43689 | AI80: 1211.95 | AJ80: 否 | AL80: 不涉及 | AO80: 刘伟(安徽分公司),姜碧霏,张乐群,张梅,戴宁,牛琪,许之玮,赵艳(安徽分公司),郑蓓,陈文轩,齐奥 | AP80: 安徽分公司 | AQ80: 12190065 | AR80: 收购安徽工行对安徽豪森纸业等29户企业持有的金融不良债权项目 | AS80: 43795 | AU80: 11001 | AV80: 已剔重 | AX80: =COUNTIFS(拍卖数据!E:E,AA80,拍卖数据!F:F,AB80,拍卖数据!O:O,O80,拍卖数据!P:P,">"&X80*0.8,拍卖数据!P:P,"<"&X80*1.2) -> 0 | AY80: =COUNTIFS(拍卖数据!E:E,AA80,拍卖数据!F:F,AB80,拍卖数据!O:O,O80,拍卖数据!AN:AN,"机构",拍卖数据!P:P,">"&X80*0.8,拍卖数据!P:P,"<"&X80*1.2) -> 0 | AZ80: =COUNTIFS(拍卖数据!E:E,AA80,拍卖数据!F:F,AB80,拍卖数据!G:G,AC80,拍卖数据!O:O,O80,拍卖数据!AN:AN,"机构",拍卖数据!P:P,">"&X80*0.8,拍卖数据!P:P,"<"&X80*1.2) -> 0
A81: 4162 | B81: 12190065002100000001 | C81: 否 | D81: 中建永顺集团有限公司 | E81: 园林绿化工程施工 | F81: 630 | G81: 108.96453 | H81: 0 | I81: 0 | J81: 738.96453 | K81: 抵押,质押,保证 | M81: 410.22393 | N81: 现房 | O81: 商业用房 | P81: 集中商业（购物中心，综合体商业等） | Q81: 新建 | R81: 中建永顺集团有限公司 | S81: 913411036849594573 | T81: 01012025081220439 | U81: 定远县定城镇东城南路绿园小区30幢2-13室皖（2016）定远县不动产权第0004893号 | V81: 皖（2016）定远县不动产证明第0008749号 | W81: 2047/1/1 | X81: 19.69 | Y81: 平方米 | Z81: 是 | AA81: 安徽省 | AB81: 滁州市 | AC81: 定远县 | AD81: 定远县定城镇东城南路绿园小区30幢2-13室 | AE81: 第一顺位 | AF81: 3671.02 | AG81: 外部评估 | AH81: 43689 | AI81: 11.32 | AJ81: 否 | AL81: 不涉及 | AO81: 刘伟(安徽分公司),姜碧霏,张乐群,张梅,戴宁,牛琪,许之玮,赵艳(安徽分公司),郑蓓,陈文轩,齐奥 | AP81: 安徽分公司 | AQ81: 12190065 | AR81: 收购安徽工行对安徽豪森纸业等29户企业持有的金融不良债权项目 | AS81: 43795 | AU81: 11001 | AV81: 已剔重 | AX81: =COUNTIFS(拍卖数据!E:E,AA81,拍卖数据!F:F,AB81,拍卖数据!O:O,O81,拍卖数据!P:P,">"&X81*0.8,拍卖数据!P:P,"<"&X81*1.2) -> 1 | AY81: =COUNTIFS(拍卖数据!E:E,AA81,拍卖数据!F:F,AB81,拍卖数据!O:O,O81,拍卖数据!AN:AN,"机构",拍卖数据!P:P,">"&X81*0.8,拍卖数据!P:P,"<"&X81*1.2) -> 0 | AZ81: =COUNTIFS(拍卖数据!E:E,AA81,拍卖数据!F:F,AB81,拍卖数据!G:G,AC81,拍卖数据!O:O,O81,拍卖数据!AN:AN,"机构",拍卖数据!P:P,">"&X81*0.8,拍卖数据!P:P,"<"&X81*1.2) -> 0
A82: 4163 | B82: 12190065002100000002 | C82: 否 | D82: 中建永顺集团有限公司 | E82: 园林绿化工程施工 | F82: 627 | G82: 107.44316 | H82: 0 | I82: 0 | J82: 734.44316 | K82: 抵押,质押,保证 | M82: 408.27048 | N82: 现房 | O82: 商业用房 | P82: 集中商业（购物中心，综合体商业等） | Q82: 新建 | R82: 中建永顺集团有限公司 | S82: 913411036849594573 | T82: 01012025081220437 | U82: 定远县定城镇东城南路绿园小区30幢1-4 室皖（2016）定远县不动产权第0004891号 | V82: 皖（2016）定远县不动产证明第0008748号 | W82: 2047/1/1 | X82: 57.47 | Y82: 平方米 | Z82: 是 | AA82: 安徽省 | AB82: 滁州市 | AC82: 定远县 | AD82: 定远县定城镇东城南路绿园小区30幢1-4 室 | AE82: 第一顺位 | AF82: 3671.02 | AG82: 外部评估 | AH82: 43689 | AI82: 66.09 | AJ82: 否 | AL82: 不涉及 | AO82: 刘伟(安徽分公司),姜碧霏,张乐群,张梅,戴宁,牛琪,许之玮,赵艳(安徽分公司),郑蓓,陈文轩,齐奥 | AP82: 安徽分公司 | AQ82: 12190065 | AR82: 收购安徽工行对安徽豪森纸业等29户企业持有的金融不良债权项目 | AS82: 43795 | AU82: 11001 | AV82: 已剔重 | AX82: =COUNTIFS(拍卖数据!E:E,AA82,拍卖数据!F:F,AB82,拍卖数据!O:O,O82,拍卖数据!P:P,">"&X82*0.8,拍卖数据!P:P,"<"&X82*1.2) -> 31 | AY82: =COUNTIFS(拍卖数据!E:E,AA82,拍卖数据!F:F,AB82,拍卖数据!O:O,O82,拍卖数据!AN:AN,"机构",拍卖数据!P:P,">"&X82*0.8,拍卖数据!P:P,"<"&X82*1.2) -> 0 | AZ82: =COUNTIFS(拍卖数据!E:E,AA82,拍卖数据!F:F,AB82,拍卖数据!G:G,AC82,拍卖数据!O:O,O82,拍卖数据!AN:AN,"机构",拍卖数据!P:P,">"&X82*0.8,拍卖数据!P:P,"<"&X82*1.2) -> 0
A83: 4164 | B83: 12190065002100000002 | C83: 否 | D83: 中建永顺集团有限公司 | E83: 园林绿化工程施工 | F83: 627 | G83: 107.44316 | H83: 0 | I83: 0 | J83: 734.44316 | K83: 抵押,质押,保证 | M83: 408.27048 | N83: 现房 | O83: 商业用房 | P83: 集中商业（购物中心，综合体商业等） | Q83: 新建 | R83: 中建永顺集团有限公司 | S83: 913411036849594573 | T83: 01012025081220440 | U83: 定远县定城镇东城南路绿园小区33幢北10室皖（2016）定远县不动产权第0004890号 | V83: 皖（2016）定远县不动产证明第0008750号 | W83: 2047/1/1 | X83: 115.58 | Y83: 平方米 | Z83: 是 | AA83: 安徽省 | AB83: 滁州市 | AC83: 定远县 | AD83: 定远县定城镇东城南路绿园小区33幢北10室 | AE83: 第一顺位 | AF83: 3671.02 | AG83: 外部评估 | AH83: 43689 | AI83: 121.36 | AJ83: 否 | AL83: 不涉及 | AO83: 刘伟(安徽分公司),姜碧霏,张乐群,张梅,戴宁,牛琪,许之玮,赵艳(安徽分公司),郑蓓,陈文轩,齐奥 | AP83: 安徽分公司 | AQ83: 12190065 | AR83: 收购安徽工行对安徽豪森纸业等29户企业持有的金融不良债权项目 | AS83: 43795 | AU83: 11001 | AV83: 已剔重 | AX83: =COUNTIFS(拍卖数据!E:E,AA83,拍卖数据!F:F,AB83,拍卖数据!O:O,O83,拍卖数据!P:P,">"&X83*0.8,拍卖数据!P:P,"<"&X83*1.2) -> 48 | AY83: =COUNTIFS(拍卖数据!E:E,AA83,拍卖数据!F:F,AB83,拍卖数据!O:O,O83,拍卖数据!AN:AN,"机构",拍卖数据!P:P,">"&X83*0.8,拍卖数据!P:P,"<"&X83*1.2) -> 0 | AZ83: =COUNTIFS(拍卖数据!E:E,AA83,拍卖数据!F:F,AB83,拍卖数据!G:G,AC83,拍卖数据!O:O,O83,拍卖数据!AN:AN,"机构",拍卖数据!P:P,">"&X83*0.8,拍卖数据!P:P,"<"&X83*1.2) -> 0
A84: 4165 | B84: 12190065002100000003 | C84: 否 | D84: 中建永顺集团有限公司 | E84: 园林绿化工程施工 | F84: 440 | G84: 72.246319 | H84: 0 | I84: 0 | J84: 512.24632 | K84: 抵押,质押,保证 | M84: 286.5056 | N84: 现房 | O84: 商业用房 | P84: 集中商业（购物中心，综合体商业等） | Q84: 新建 | R84: 中建永顺集团有限公司 | S84: 913411036849594573 | T84: 01012025081220438 | U84: 定远县定城镇东城南路绿园小区30幢2-1、2-4室皖（2016）定远县不动产权第0004892号 | V84: 皖（2016）定远县不动产证明第0008747号 | W84: 2047/1/1 | X84: 157.06 | Y84: 平方米 | Z84: 是 | AA84: 安徽省 | AB84: 滁州市 | AC84: 定远县 | AD84: 定远县定城镇东城南路绿园小区30幢2-1、2-4室 | AE84: 第一顺位 | AF84: 3671.02 | AG84: 外部评估 | AH84: 43689 | AI84: 90.31 | AJ84: 否 | AL84: 不涉及 | AO84: 刘伟(安徽分公司),姜碧霏,张乐群,张梅,戴宁,牛琪,许之玮,赵艳(安徽分公司),郑蓓,陈文轩,齐奥 | AP84: 安徽分公司 | AQ84: 12190065 | AR84: 收购安徽工行对安徽豪森纸业等29户企业持有的金融不良债权项目 | AS84: 43795 | AU84: 11001 | AV84: 已剔重 | AX84: =COUNTIFS(拍卖数据!E:E,AA84,拍卖数据!F:F,AB84,拍卖数据!O:O,O84,拍卖数据!P:P,">"&X84*0.8,拍卖数据!P:P,"<"&X84*1.2) -> 42 | AY84: =COUNTIFS(拍卖数据!E:E,AA84,拍卖数据!F:F,AB84,拍卖数据!O:O,O84,拍卖数据!AN:AN,"机构",拍卖数据!P:P,">"&X84*0.8,拍卖数据!P:P,"<"&X84*1.2) -> 0 | AZ84: =COUNTIFS(拍卖数据!E:E,AA84,拍卖数据!F:F,AB84,拍卖数据!G:G,AC84,拍卖数据!O:O,O84,拍卖数据!AN:AN,"机构",拍卖数据!P:P,">"&X84*0.8,拍卖数据!P:P,"<"&X84*1.2) -> 0
A85: 4166 | B85: 12190065002100000003 | C85: 否 | D85: 中建永顺集团有限公司 | E85: 园林绿化工程施工 | F85: 440 | G85: 72.246319 | H85: 0 | I85: 0 | J85: 512.24632 | K85: 抵押,质押,保证 | M85: 286.5056 | N85: 现房 | O85: 商业用房 | P85: 集中商业（购物中心，综合体商业等） | Q85: 新建 | R85: 中建永顺集团有限公司 | S85: 913411036849594573 | T85: 01012025081220442 | U85: 定远县定城镇东城南路绿园小区33幢北13室皖（2016）定远县不动产权第0004887号 | V85: 皖（2016）定远县不动产证明第0008752号 | W85: 2047/1/1 | X85: 1325.99 | Y85: 平方米 | Z85: 是 | AA85: 安徽省 | AB85: 滁州市 | AC85: 定远县 | AD85: 定远县定城镇东城南路绿园小区33幢北13室 | AE85: 第一顺位 | AF85: 3671.02 | AG85: 外部评估 | AH85: 43689 | AI85: 991.84 | AJ85: 否 | AL85: 不涉及 | AO85: 刘伟(安徽分公司),姜碧霏,张乐群,张梅,戴宁,牛琪,许之玮,赵艳(安徽分公司),郑蓓,陈文轩,齐奥 | AP85: 安徽分公司 | AQ85: 12190065 | AR85: 收购安徽工行对安徽豪森纸业等29户企业持有的金融不良债权项目 | AS85: 43795 | AU85: 11001 | AV85: 已剔重 | AX85: =COUNTIFS(拍卖数据!E:E,AA85,拍卖数据!F:F,AB85,拍卖数据!O:O,O85,拍卖数据!P:P,">"&X85*0.8,拍卖数据!P:P,"<"&X85*1.2) -> 1 | AY85: =COUNTIFS(拍卖数据!E:E,AA85,拍卖数据!F:F,AB85,拍卖数据!O:O,O85,拍卖数据!AN:AN,"机构",拍卖数据!P:P,">"&X85*0.8,拍卖数据!P:P,"<"&X85*1.2) -> 0 | AZ85: =COUNTIFS(拍卖数据!E:E,AA85,拍卖数据!F:F,AB85,拍卖数据!G:G,AC85,拍卖数据!O:O,O85,拍卖数据!AN:AN,"机构",拍卖数据!P:P,">"&X85*0.8,拍卖数据!P:P,"<"&X85*1.2) -> 0
A86: 4167 | B86: 12190065002100000003 | C86: 否 | D86: 中建永顺集团有限公司 | E86: 园林绿化工程施工 | F86: 440 | G86: 72.246319 | H86: 0 | I86: 0 | J86: 512.24632 | K86: 抵押,质押,保证 | M86: 286.5056 | N86: 现房 | O86: 商业用房 | P86: 集中商业（购物中心，综合体商业等） | Q86: 新建 | R86: 中建永顺集团有限公司 | S86: 913411036849594573 | T86: 01012025081220441 | U86: 定远县定城镇东城南路绿园小区33幢北7室皖（2016）定远县不动产权第0004889号 | V86: 皖（2016）定远县不动产证明第0008751号 | W86: 2047/1/1 | X86: 92.98 | Y86: 平方米 | Z86: 是 | AA86: 安徽省 | AB86: 滁州市 | AC86: 定远县 | AD86: 定远县定城镇东城南路绿园小区33幢北7室 | AE86: 第一顺位 | AF86: 3671.02 | AG86: 外部评估 | AH86: 43689 | AI86: 73.22 | AJ86: 否 | AL86: 不涉及 | AO86: 刘伟(安徽分公司),姜碧霏,张乐群,张梅,戴宁,牛琪,许之玮,赵艳(安徽分公司),郑蓓,陈文轩,齐奥 | AP86: 安徽分公司 | AQ86: 12190065 | AR86: 收购安徽工行对安徽豪森纸业等29户企业持有的金融不良债权项目 | AS86: 43795 | AU86: 11001 | AV86: 已剔重 | AX86: =COUNTIFS(拍卖数据!E:E,AA86,拍卖数据!F:F,AB86,拍卖数据!O:O,O86,拍卖数据!P:P,">"&X86*0.8,拍卖数据!P:P,"<"&X86*1.2) -> 35 | AY86: =COUNTIFS(拍卖数据!E:E,AA86,拍卖数据!F:F,AB86,拍卖数据!O:O,O86,拍卖数据!AN:AN,"机构",拍卖数据!P:P,">"&X86*0.8,拍卖数据!P:P,"<"&X86*1.2) -> 0 | AZ86: =COUNTIFS(拍卖数据!E:E,AA86,拍卖数据!F:F,AB86,拍卖数据!G:G,AC86,拍卖数据!O:O,O86,拍卖数据!AN:AN,"机构",拍卖数据!P:P,">"&X86*0.8,拍卖数据!P:P,"<"&X86*1.2) -> 0
A87: 4479 | B87: 19190128000100000001 | C87: 否 | D87: 中福天工建设集团有限公司 | E87: 住宅房屋建筑 | F87: 57425.297 | G87: 0 | H87: 0 | I87: 0 | J87: 57425.297 | K87: 信用 | M87: 56484.997 | N87: 在建工程 | O87: 商业用房在建工程 | P87: 商业用房在建工程 | Q87: 已入库 | R87: 安徽安粮金属市场投资有限公司 | S87: 91340122684984388T | T87: 01032025090699359 | U87: 位于合肥市华商国际名优特产交易中心项目的873套面积合计32,027.92平方米的商铺在建工程 | V87: 皖（2020）肥东县不动产证明第0000126号 | W87: Sat Jul 15 00:00:00 CST 2051 | X87: 32027.92 | Y87: 平方米 | Z87: 是 | AA87: 安徽省 | AB87: 合肥市 | AC87: 肥东县 | AD87: 撮镇镇裕溪路南 | AE87: 第一顺位 | AF87: 29636.21 | AG87: 外部评估 | AH87: 44111 | AI87: 29636.21 | AJ87: 否 | AL87: 涉及 | AM87: 30837576 | AN87: 根据破产管理人报告，截至2022年10月31日，管理人审查认定特定财产担保类14599634.4元，职工债权5570319.65元，税款债权10667622.04元。 | AO87: 李裕泽,梁洁容,莫志闻 | AP87: 广东分公司 | AQ87: 19190128 | AR87: 收购处置中核伟业对中核工建设集团持有的不良债权项目 | AS87: 43825 | AU87: 10001 | AV87: 已剔重 | AX87: =COUNTIFS(拍卖数据!E:E,AA87,拍卖数据!F:F,AB87,拍卖数据!O:O,O87,拍卖数据!P:P,">"&X87*0.8,拍卖数据!P:P,"<"&X87*1.2) -> 0 | AY87: =COUNTIFS(拍卖数据!E:E,AA87,拍卖数据!F:F,AB87,拍卖数据!O:O,O87,拍卖数据!AN:AN,"机构",拍卖数据!P:P,">"&X87*0.8,拍卖数据!P:P,"<"&X87*1.2) -> 0 | AZ87: =COUNTIFS(拍卖数据!E:E,AA87,拍卖数据!F:F,AB87,拍卖数据!G:G,AC87,拍卖数据!O:O,O87,拍卖数据!AN:AN,"机构",拍卖数据!P:P,">"&X87*0.8,拍卖数据!P:P,"<"&X87*1.2) -> 0
A88: 4480 | B88: 19190128000100000001 | C88: 否 | D88: 中福天工建设集团有限公司 | E88: 住宅房屋建筑 | F88: 57425.297 | G88: 0 | H88: 0 | I88: 0 | J88: 57425.297 | K88: 信用 | M88: 56484.997 | N88: 在建工程 | O88: 商业用房在建工程 | P88: 商业用房在建工程 | Q88: 已入库 | R88: 安徽安粮金属市场投资有限公司 | S88: 91340122684984388T | T88: 01032025090699360 | U88: 位于合肥市华商国际名优特产交易中心项目的873套面积合计32,027.92平方米的商铺在建工程 | V88: 皖（2020）肥东县不动产证明第0000126号 | W88: Sat Jul 15 00:00:00 CST 2051 | X88: 32027.92 | Y88: 平方米 | Z88: 是 | AA88: 安徽省 | AB88: 合肥市 | AC88: 肥东县 | AD88: 撮镇镇裕溪路南 | AE88: 第一顺位 | AF88: 29636.21 | AG88: 外部评估 | AH88: 44111 | AI88: 29636.21 | AJ88: 否 | AL88: 涉及 | AM88: 30837576 | AN88: 根据破产管理人报告，截至2022年10月31日，管理人审查认定特定财产担保类14599634.4元，职工债权5570319.65元，税款债权10667622.04元。 | AO88: 李裕泽,梁洁容,莫志闻 | AP88: 广东分公司 | AQ88: 19190128 | AR88: 收购处置中核伟业对中核工建设集团持有的不良债权项目 | AS88: 43825 | AU88: 10001 | AV88: 重复内容 | AX88: =COUNTIFS(拍卖数据!E:E,AA88,拍卖数据!F:F,AB88,拍卖数据!O:O,O88,拍卖数据!P:P,">"&X88*0.8,拍卖数据!P:P,"<"&X88*1.2) -> 0 | AY88: =COUNTIFS(拍卖数据!E:E,AA88,拍卖数据!F:F,AB88,拍卖数据!O:O,O88,拍卖数据!AN:AN,"机构",拍卖数据!P:P,">"&X88*0.8,拍卖数据!P:P,"<"&X88*1.2) -> 0 | AZ88: =COUNTIFS(拍卖数据!E:E,AA88,拍卖数据!F:F,AB88,拍卖数据!G:G,AC88,拍卖数据!O:O,O88,拍卖数据!AN:AN,"机构",拍卖数据!P:P,">"&X88*0.8,拍卖数据!P:P,"<"&X88*1.2) -> 0
A89: 4780 | B89: 12240029000200000001 | C89: 否 | D89: 中豪建设股份有限公司 | E89: 房屋建筑业 | F89: 1000 | G89: 51.884012 | H89: 4.5 | I89: 0 | J89: 1056.384 | K89: 抵押,质押,保证 | L89: 安徽顺风(集团)房地产开发有限公司,王学成,袁智荣 | M89: 369 | N89: 现房 | O89: 商业用房 | P89: 集中商业（购物中心，综合体商业等） | Q89: 新建 | R89: 安徽顺风（集团）房地产开发有限公司 | S89: 91341102152627611G | T89: 01012025081220645 | U89: 滁州市南谯北路615号（顺风大厦）综合楼（商服）二层房地权滁字第2008007683号 | V89: 皖（2019）滁州市不动产证明第0036482号 | W89: 51399 | X89: 1644.39 | Y89: 平方米 | Z89: 是 | AA89: 安徽省 | AB89: 滁州市 | AC89: 南谯区 | AD89: 滁州市南谯北路615号（顺风大厦）综合楼（商服）二层 | AE89: 第一顺位 | AF89: 2660 | AG89: 外部评估 | AH89: 45443 | AI89: 1372.57 | AJ89: 否 | AL89: 不涉及 | AO89: 张梅,赵艳(安徽分公司),陈文轩,齐奥 | AP89: 安徽分公司 | AQ89: 12240029 | AR89: 收购安徽建行2024年第二季度4户不良资产包项目 | AS89: 45469 | AU89: 11001 | AV89: 已剔重 | AX89: =COUNTIFS(拍卖数据!E:E,AA89,拍卖数据!F:F,AB89,拍卖数据!O:O,O89,拍卖数据!P:P,">"&X89*0.8,拍卖数据!P:P,"<"&X89*1.2) -> 2 | AY89: =COUNTIFS(拍卖数据!E:E,AA89,拍卖数据!F:F,AB89,拍卖数据!O:O,O89,拍卖数据!AN:AN,"机构",拍卖数据!P:P,">"&X89*0.8,拍卖数据!P:P,"<"&X89*1.2) -> 1 | AZ89: =COUNTIFS(拍卖数据!E:E,AA89,拍卖数据!F:F,AB89,拍卖数据!G:G,AC89,拍卖数据!O:O,O89,拍卖数据!AN:AN,"机构",拍卖数据!P:P,">"&X89*0.8,拍卖数据!P:P,"<"&X89*1.2) -> 0
A90: 5243 | B90: 12240053003900000001 | C90: 否 | D90: 临泉县金城国际实业有限公司 | E90: 其他未列明零售业 | F90: 500 | G90: 158.65507 | H90: 0.5 | I90: 0 | J90: 659.15507 | K90: 抵押,质押,保证 | L90: 代旭,戴驰 | M90: 0 | N90: 在建工程 | O90: 商业用房在建工程 | P90: 商业用房在建工程 | Q90: 新建 | R90: 临泉县金城国际实业有限公司 | S90: 91341221MA2MX1K358 | T90: 01032025091430001 | U90: 临泉县光明路与前进路交叉口西北侧金城大厦501、516、517、518、521A、522、538A、539、544、601、617、619、638A、643、701、717、721A、738A、1201、1701、2403、2501、2504、2604室（在建工程）皖（2021）临泉县不动产证明第0012619号 | V90: 皖（2021）临泉县不动产证明第0012619号 | W90: 2056/1/1 | X90: 1418.66 | Y90: 平方米 | Z90: 是 | AA90: 安徽省 | AB90: 阜阳市 | AC90: 临泉县 | AD90: 临泉县光明路与前进路交叉口西北侧金城大厦501、516、517、518、521A、522、538A、539、544、601、617、619、638A、643、701、717、721A、738A、1201、1701、2403、2501、2504、2604室（在建工程） | AE90: 第一顺位 | AF90: 500 | AG90: 外部评估 | AH90: 44355 | AI90: 1217.1 | AJ90: 是 | AK90: A03.押品被私售、抵债、转移或占用，难以追讨或清退 | AL90: 不涉及 | AO90: 张乐群,曹吉峰,董俣顺,许之玮,邹熠峰,郑舒凌 | AP90: 安徽分公司 | AQ90: 12240053 | AR90: 收购颍东农商行2024年第1批12户不良资产包项目 | AS90: 45587 | AU90: 11001 | AV90: 已剔重 | AX90: =COUNTIFS(拍卖数据!E:E,AA90,拍卖数据!F:F,AB90,拍卖数据!O:O,O90,拍卖数据!P:P,">"&X90*0.8,拍卖数据!P:P,"<"&X90*1.2) -> 0 | AY90: =COUNTIFS(拍卖数据!E:E,AA90,拍卖数据!F:F,AB90,拍卖数据!O:O,O90,拍卖数据!AN:AN,"机构",拍卖数据!P:P,">"&X90*0.8,拍卖数据!P:P,"<"&X90*1.2) -> 0 | AZ90: =COUNTIFS(拍卖数据!E:E,AA90,拍卖数据!F:F,AB90,拍卖数据!G:G,AC90,拍卖数据!O:O,O90,拍卖数据!AN:AN,"机构",拍卖数据!P:P,">"&X90*0.8,拍卖数据!P:P,"<"&X90*1.2) -> 0
A91: 7798 | B91: 12230013026400000001 | C91: 否 | D91: 五河县双丰面粉有限公司 | E91: 小麦加工 | F91: 400 | G91: 750.80494 | H91: 0 | I91: 0 | J91: 1150.8049 | K91: 抵押,质押,保证 | L91: 武怀兰,王庆伟,王玉亮,蚌埠融资担保集团有限公司 | M91: 332 | N91: 现房 | O91: 工业用房 | P91: 标准工业厂房及仓储 | Q91: 新建 | R91: 五河县双丰面粉有限公司 | S91: 913403228501646423 | T91: 01012025091430238 | U91: 五河县武桥镇界沟村（104国道东侧)房地权五公字第212053-3号 | V91: 房他证五公字第212053-3号 | W91: 2061/3/31 | X91: 2340 | Y91: 平方米 | Z91: 是 | AA91: 安徽省 | AB91: 蚌埠市 | AC91: 五河县 | AD91: 五河县武桥镇界沟村（104国道东侧) | AE91: 第一顺位 | AF91: 330 | AG91: 外部评估 | AH91: 45071 | AI91: 257.4 | AJ91: 否 | AL91: 不涉及 | AM91: 0 | AO91: 张乐群,曹吉峰,董俣顺,许之玮,邹熠峰,郑舒凌 | AP91: 安徽分公司 | AQ91: 12230013 | AR91: 收购徽商银行2023年第2批133户不良资产包项目 | AS91: 45170 | AU91: 11001 | AV91: 已剔重 | AX91: =COUNTIFS(拍卖数据!E:E,AA91,拍卖数据!F:F,AB91,拍卖数据!O:O,O91,拍卖数据!P:P,">"&X91*0.8,拍卖数据!P:P,"<"&X91*1.2) -> 2 | AY91: =COUNTIFS(拍卖数据!E:E,AA91,拍卖数据!F:F,AB91,拍卖数据!O:O,O91,拍卖数据!AN:AN,"机构",拍卖数据!P:P,">"&X91*0.8,拍卖数据!P:P,"<"&X91*1.2) -> 2 | AZ91: =COUNTIFS(拍卖数据!E:E,AA91,拍卖数据!F:F,AB91,拍卖数据!G:G,AC91,拍卖数据!O:O,O91,拍卖数据!AN:AN,"机构",拍卖数据!P:P,">"&X91*0.8,拍卖数据!P:P,"<"&X91*1.2) -> 0
A92: 7799 | B92: 12230013026400000001 | C92: 否 | D92: 五河县双丰面粉有限公司 | E92: 小麦加工 | F92: 400 | G92: 750.80494 | H92: 0 | I92: 0 | J92: 1150.8049 | K92: 抵押,质押,保证 | L92: 武怀兰,王庆伟,王玉亮,蚌埠融资担保集团有限公司 | M92: 332 | N92: 土地使用权 | O92: 工业用地 | P92: 工业用地 | Q92: 新建 | R92: 五河县双丰面粉有限公司 | S92: 913403228501646423 | T92: 01022025091430006 | U92: 五河县武桥镇界沟村（104国道东侧)五国用（2011）第2102号 | V92: 五他项（2014）第088号 | W92: 2061/3/31 | X92: 6671 | Y92: 平方米 | Z92: 是 | AA92: 安徽省 | AB92: 蚌埠市 | AC92: 五河县 | AD92: 五河县武桥镇界沟村（104国道东侧) | AE92: 第一顺位 | AF92: 70 | AG92: 外部评估 | AH92: 45071 | AI92: 60.04 | AJ92: 否 | AL92: 不涉及 | AO92: 张乐群,曹吉峰,董俣顺,许之玮,邹熠峰,郑舒凌 | AP92: 安徽分公司 | AQ92: 12230013 | AR92: 收购徽商银行2023年第2批133户不良资产包项目 | AS92: 45170 | AU92: 11001 | AV92: 已剔重 | AX92: =COUNTIFS(拍卖数据!E:E,AA92,拍卖数据!F:F,AB92,拍卖数据!O:O,O92,拍卖数据!P:P,">"&X92*0.8,拍卖数据!P:P,"<"&X92*1.2) -> 0 | AY92: =COUNTIFS(拍卖数据!E:E,AA92,拍卖数据!F:F,AB92,拍卖数据!O:O,O92,拍卖数据!AN:AN,"机构",拍卖数据!P:P,">"&X92*0.8,拍卖数据!P:P,"<"&X92*1.2) -> 0 | AZ92: =COUNTIFS(拍卖数据!E:E,AA92,拍卖数据!F:F,AB92,拍卖数据!G:G,AC92,拍卖数据!O:O,O92,拍卖数据!AN:AN,"机构",拍卖数据!P:P,">"&X92*0.8,拍卖数据!P:P,"<"&X92*1.2) -> 0
A93: 7800 | B93: 12230013026400000001 | C93: 否 | D93: 五河县双丰面粉有限公司 | E93: 小麦加工 | F93: 400 | G93: 750.80494 | H93: 0 | I93: 0 | J93: 1150.8049 | K93: 抵押,质押,保证 | L93: 武怀兰,王庆伟,王玉亮,蚌埠融资担保集团有限公司 | M93: 332 | N93: 现房 | O93: 工业用房 | P93: 标准工业厂房及仓储 | Q93: 新建 | R93: 五河县双丰面粉有限公司 | S93: 913403228501646423 | T93: 01012025091430239 | U93: 五河县武桥镇界沟村（104国道东侧)房地权五公字第212053-4号 | V93: 房他证五公字第212053-4号 | W93: 2061/3/31 | X93: 2757.2 | Y93: 平方米 | Z93: 是 | AA93: 安徽省 | AB93: 蚌埠市 | AC93: 五河县 | AD93: 五河县武桥镇界沟村（104国道东侧) | AE93: 第一顺位 | AF93: 330 | AG93: 外部评估 | AH93: 45071 | AI93: 303.29 | AJ93: 否 | AL93: 不涉及 | AM93: 0 | AO93: 张乐群,曹吉峰,董俣顺,许之玮,邹熠峰,郑舒凌 | AP93: 安徽分公司 | AQ93: 12230013 | AR93: 收购徽商银行2023年第2批133户不良资产包项目 | AS93: 45170 | AU93: 11001 | AV93: 已剔重 | AX93: =COUNTIFS(拍卖数据!E:E,AA93,拍卖数据!F:F,AB93,拍卖数据!O:O,O93,拍卖数据!P:P,">"&X93*0.8,拍卖数据!P:P,"<"&X93*1.2) -> 3 | AY93: =COUNTIFS(拍卖数据!E:E,AA93,拍卖数据!F:F,AB93,拍卖数据!O:O,O93,拍卖数据!AN:AN,"机构",拍卖数据!P:P,">"&X93*0.8,拍卖数据!P:P,"<"&X93*1.2) -> 2 | AZ93: =COUNTIFS(拍卖数据!E:E,AA93,拍卖数据!F:F,AB93,拍卖数据!G:G,AC93,拍卖数据!O:O,O93,拍卖数据!AN:AN,"机构",拍卖数据!P:P,">"&X93*0.8,拍卖数据!P:P,"<"&X93*1.2) -> 0
A94: 12217 | B94: 12253005010006 | C94: 否 | D94: 六安市东怡商贸有限公司 | E94: 批发和零售业 | F94: 1445 | G94: 1277.0939 | H94: 10.5 | J94: 2732.5939 | K94: 抵押,保证 | L94: 刘幼红,刘幼红,王庆淮,王庆淮,王敬雪,王敬雪 | M94: 840.96301 | N94: 现房 | O94: 商业用房 | P94: 集中商业（购物中心，综合体商业等） | Q94: 已入库 | R94: 六安市东川房地产开发有限责任公司 | S94: 91341500584562612K | T94: 01012025071130001 | U94: 御财广场商业房产一层 | V94: 皖（2018）六安市不动产证明第3044958号 | W94: 2051-09-23 | X94: 1036.41 | Y94: 平方米 | Z94: 是 | AA94: 安徽省 | AB94: 六安市 | AC94: 金安区 | AD94: 正阳路以西纬三路以北御财广场项目 | AE94: 第零顺位 | AF94: 920 | AG94: 外部评估 | AH94: 45776 | AI94: 804.67 | AJ94: 否 | AL94: 不涉及 | AM94: 0 | AO94: 许之玮,陈文轩 | AP94: 安徽分公司 | AQ94: 12253005 | AR94: 收购九江银行合肥分行2025年第1批3户不良资产包项目 | AS94: 45834 | AU94: 11000 | AV94: 已剔重 | AX94: =COUNTIFS(拍卖数据!E:E,AA94,拍卖数据!F:F,AB94,拍卖数据!O:O,O94,拍卖数据!P:P,">"&X94*0.8,拍卖数据!P:P,"<"&X94*1.2) -> 0 | AY94: =COUNTIFS(拍卖数据!E:E,AA94,拍卖数据!F:F,AB94,拍卖数据!O:O,O94,拍卖数据!AN:AN,"机构",拍卖数据!P:P,">"&X94*0.8,拍卖数据!P:P,"<"&X94*1.2) -> 0 | AZ94: =COUNTIFS(拍卖数据!E:E,AA94,拍卖数据!F:F,AB94,拍卖数据!G:G,AC94,拍卖数据!O:O,O94,拍卖数据!AN:AN,"机构",拍卖数据!P:P,">"&X94*0.8,拍卖数据!P:P,"<"&X94*1.2) -> 0
A95: 12218 | B95: 12253005010006 | C95: 否 | D95: 六安市东怡商贸有限公司 | E95: 批发和零售业 | F95: 1445 | G95: 1277.0939 | H95: 10.5 | J95: 2732.5939 | K95: 抵押,保证 | L95: 刘幼红,刘幼红,王庆淮,王庆淮,王敬雪,王敬雪 | M95: 840.96301 | N95: 现房 | O95: 商业用房 | P95: 集中商业（购物中心，综合体商业等） | Q95: 已入库 | R95: 六安市东川房地产开发有限责任公司 | S95: 91341500584562612K | T95: 01012025071130002 | U95: 御财广场商业房产二层 | V95: 皖（2018）六安市不动产证明第3044959号 | W95: 2051-09-23 | X95: 1027.42 | Y95: 平方米 | Z95: 是 | AA95: 安徽省 | AB95: 六安市 | AC95: 金安区 | AD95: 正阳路以西纬三路以北御财广场项目 | AE95: 第零顺位 | AF95: 530 | AG95: 外部评估 | AH95: 45776 | AI95: 478.57 | AJ95: 否 | AL95: 不涉及 | AM95: 0 | AO95: 许之玮,陈文轩 | AP95: 安徽分公司 | AQ95: 12253005 | AR95: 收购九江银行合肥分行2025年第1批3户不良资产包项目 | AS95: 45834 | AU95: 11000 | AV95: 已剔重 | AX95: =COUNTIFS(拍卖数据!E:E,AA95,拍卖数据!F:F,AB95,拍卖数据!O:O,O95,拍卖数据!P:P,">"&X95*0.8,拍卖数据!P:P,"<"&X95*1.2) -> 0 | AY95: =COUNTIFS(拍卖数据!E:E,AA95,拍卖数据!F:F,AB95,拍卖数据!O:O,O95,拍卖数据!AN:AN,"机构",拍卖数据!P:P,">"&X95*0.8,拍卖数据!P:P,"<"&X95*1.2) -> 0 | AZ95: =COUNTIFS(拍卖数据!E:E,AA95,拍卖数据!F:F,AB95,拍卖数据!G:G,AC95,拍卖数据!O:O,O95,拍卖数据!AN:AN,"机构",拍卖数据!P:P,">"&X95*0.8,拍卖数据!P:P,"<"&X95*1.2) -> 0
A96: 12219 | B96: 12240053002700000001 | C96: 否 | D96: 六安市星星矿业有限公司 | E96: 其他非金属矿物制品制造 | F96: 500 | G96: 324.90137 | H96: 2.12 | I96: 0 | J96: 827.02137 | K96: 抵押,质押,保证 | L96: 郭旭东,马艳 | M96: 172.44 | N96: 现房 | O96: 商业用房 | P96: 集中商业（购物中心，综合体商业等） | Q96: 新建 | R96: 郭旭东 | S96: 342401196801262218 | T96: 01012025091430112 | U96: 六安市经济开发区上东·阳光城10号楼5铺(1-2层）皖（2017）六安市市不动产权第0066160号 | V96: 皖（2018）六安市市不动产证明第3055340号 | W96: 2047/10/20 | X96: 124.13 | Y96: 平方米 | Z96: 是 | AA96: 安徽省 | AB96: 六安市 | AC96: 金安区 | AD96: 六安市经济开发区上东·阳光城10号楼5铺(1-2层） | AE96: 第一顺位 | AF96: 95 | AG96: 外部评估 | AH96: 45558 | AI96: 101.79 | AJ96: 否 | AL96: 不涉及 | AO96: 张乐群,曹吉峰,董俣顺,许之玮,邹熠峰,郑舒凌 | AP96: 安徽分公司 | AQ96: 12240053 | AR96: 收购颍东农商行2024年第1批12户不良资产包项目 | AS96: 45587 | AU96: 11001 | AV96: 已剔重 | AX96: =COUNTIFS(拍卖数据!E:E,AA96,拍卖数据!F:F,AB96,拍卖数据!O:O,O96,拍卖数据!P:P,">"&X96*0.8,拍卖数据!P:P,"<"&X96*1.2) -> 7 | AY96: =COUNTIFS(拍卖数据!E:E,AA96,拍卖数据!F:F,AB96,拍卖数据!O:O,O96,拍卖数据!AN:AN,"机构",拍卖数据!P:P,">"&X96*0.8,拍卖数据!P:P,"<"&X96*1.2) -> 0 | AZ96: =COUNTIFS(拍卖数据!E:E,AA96,拍卖数据!F:F,AB96,拍卖数据!G:G,AC96,拍卖数据!O:O,O96,拍卖数据!AN:AN,"机构",拍卖数据!P:P,">"&X96*0.8,拍卖数据!P:P,"<"&X96*1.2) -> 0
A97: 12220 | B97: 12240053002700000001 | C97: 否 | D97: 六安市星星矿业有限公司 | E97: 其他非金属矿物制品制造 | F97: 500 | G97: 324.90137 | H97: 2.12 | I97: 0 | J97: 827.02137 | K97: 抵押,质押,保证 | L97: 郭旭东,马艳 | M97: 172.44 | N97: 现房 | O97: 商业用房 | P97: 集中商业（购物中心，综合体商业等） | Q97: 新建 | R97: 郭旭东 | S97: 342401196801262218 | T97: 01012025091430122 | U97: 六安市经济开发区上东·阳光城13号楼二层12铺皖（2017）六安市市不动产权第0066165号 | V97: 皖（2018）六安市市不动产证明第3055337号 | W97: 2047/10/20 | X97: 74.57 | Y97: 平方米 | Z97: 是 | AA97: 安徽省 | AB97: 六安市 | AC97: 金安区 | AD97: 六安市经济开发区上东·阳光城13号楼二层12铺 | AE97: 第一顺位 | AF97: 40 | AG97: 外部评估 | AH97: 45558 | AI97: 26.85 | AJ97: 否 | AL97: 不涉及 | AO97: 张乐群,曹吉峰,董俣顺,许之玮,邹熠峰,郑舒凌 | AP97: 安徽分公司 | AQ97: 12240053 | AR97: 收购颍东农商行2024年第1批12户不良资产包项目 | AS97: 45587 | AU97: 11001 | AV97: 已剔重 | AX97: =COUNTIFS(拍卖数据!E:E,AA97,拍卖数据!F:F,AB97,拍卖数据!O:O,O97,拍卖数据!P:P,">"&X97*0.8,拍卖数据!P:P,"<"&X97*1.2) -> 2 | AY97: =COUNTIFS(拍卖数据!E:E,AA97,拍卖数据!F:F,AB97,拍卖数据!O:O,O97,拍卖数据!AN:AN,"机构",拍卖数据!P:P,">"&X97*0.8,拍卖数据!P:P,"<"&X97*1.2) -> 0 | AZ97: =COUNTIFS(拍卖数据!E:E,AA97,拍卖数据!F:F,AB97,拍卖数据!G:G,AC97,拍卖数据!O:O,O97,拍卖数据!AN:AN,"机构",拍卖数据!P:P,">"&X97*0.8,拍卖数据!P:P,"<"&X97*1.2) -> 0
A98: 12221 | B98: 12240053002700000001 | C98: 否 | D98: 六安市星星矿业有限公司 | E98: 其他非金属矿物制品制造 | F98: 500 | G98: 324.90137 | H98: 2.12 | I98: 0 | J98: 827.02137 | K98: 抵押,质押,保证 | L98: 郭旭东,马艳 | M98: 172.44 | N98: 现房 | O98: 商业用房 | P98: 集中商业（购物中心，综合体商业等） | Q98: 新建 | R98: 郭旭东 | S98: 342401196801262218 | T98: 01012025091430121 | U98: 六安市经济开发区上东·阳光城13号楼二层11铺皖（2017）六安市市不动产权第0066169号 | V98: 皖（2018）六安市市不动产证明第3055335号 | W98: 2047/10/20 | X98: 79.9 | Y98: 平方米 | Z98: 是 | AA98: 安徽省 | AB98: 六安市 | AC98: 金安区 | AD98: 六安市经济开发区上东·阳光城13号楼二层11铺 | AE98: 第一顺位 | AF98: 45 | AG98: 外部评估 | AH98: 45558 | AI98: 28.76 | AJ98: 否 | AL98: 不涉及 | AO98: 张乐群,曹吉峰,董俣顺,许之玮,邹熠峰,郑舒凌 | AP98: 安徽分公司 | AQ98: 12240053 | AR98: 收购颍东农商行2024年第1批12户不良资产包项目 | AS98: 45587 | AU98: 11001 | AV98: 已剔重 | AX98: =COUNTIFS(拍卖数据!E:E,AA98,拍卖数据!F:F,AB98,拍卖数据!O:O,O98,拍卖数据!P:P,">"&X98*0.8,拍卖数据!P:P,"<"&X98*1.2) -> 3 | AY98: =COUNTIFS(拍卖数据!E:E,AA98,拍卖数据!F:F,AB98,拍卖数据!O:O,O98,拍卖数据!AN:AN,"机构",拍卖数据!P:P,">"&X98*0.8,拍卖数据!P:P,"<"&X98*1.2) -> 0 | AZ98: =COUNTIFS(拍卖数据!E:E,AA98,拍卖数据!F:F,AB98,拍卖数据!G:G,AC98,拍卖数据!O:O,O98,拍卖数据!AN:AN,"机构",拍卖数据!P:P,">"&X98*0.8,拍卖数据!P:P,"<"&X98*1.2) -> 0
A99: 12222 | B99: 12240053002700000001 | C99: 否 | D99: 六安市星星矿业有限公司 | E99: 其他非金属矿物制品制造 | F99: 500 | G99: 324.90137 | H99: 2.12 | I99: 0 | J99: 827.02137 | K99: 抵押,质押,保证 | L99: 郭旭东,马艳 | M99: 172.44 | N99: 现房 | O99: 商业用房 | P99: 集中商业（购物中心，综合体商业等） | Q99: 新建 | R99: 郭旭东 | S99: 342401196801262218 | T99: 01012025091430120 | U99: 六安市经济开发区上东·阳光城13号楼二层10铺皖（2017）六安市市不动产权第0066168号 | V99: 皖（2018）六安市市不动产证明第3055334号 | W99: 2047/10/20 | X99: 61.89 | Y99: 平方米 | Z99: 是 | AA99: 安徽省 | AB99: 六安市 | AC99: 金安区 | AD99: 六安市经济开发区上东·阳光城13号楼二层10铺 | AE99: 第一顺位 | AF99: 35 | AG99: 外部评估 | AH99: 45558 | AI99: 22.28 | AJ99: 否 | AL99: 不涉及 | AO99: 张乐群,曹吉峰,董俣顺,许之玮,邹熠峰,郑舒凌 | AP99: 安徽分公司 | AQ99: 12240053 | AR99: 收购颍东农商行2024年第1批12户不良资产包项目 | AS99: 45587 | AU99: 11001 | AV99: 已剔重 | AX99: =COUNTIFS(拍卖数据!E:E,AA99,拍卖数据!F:F,AB99,拍卖数据!O:O,O99,拍卖数据!P:P,">"&X99*0.8,拍卖数据!P:P,"<"&X99*1.2) -> 0 | AY99: =COUNTIFS(拍卖数据!E:E,AA99,拍卖数据!F:F,AB99,拍卖数据!O:O,O99,拍卖数据!AN:AN,"机构",拍卖数据!P:P,">"&X99*0.8,拍卖数据!P:P,"<"&X99*1.2) -> 0 | AZ99: =COUNTIFS(拍卖数据!E:E,AA99,拍卖数据!F:F,AB99,拍卖数据!G:G,AC99,拍卖数据!O:O,O99,拍卖数据!AN:AN,"机构",拍卖数据!P:P,">"&X99*0.8,拍卖数据!P:P,"<"&X99*1.2) -> 0
A100: 12223 | B100: 12240053002700000001 | C100: 否 | D100: 六安市星星矿业有限公司 | E100: 其他非金属矿物制品制造 | F100: 500 | G100: 324.90137 | H100: 2.12 | I100: 0 | J100: 827.02137 | K100: 抵押,质押,保证 | L100: 郭旭东,马艳 | M100: 172.44 | N100: 现房 | O100: 商业用房 | P100: 集中商业（购物中心，综合体商业等） | Q100: 新建 | R100: 郭旭东 | S100: 342401196801262218 | T100: 01012025091430119 | U100: 六安市经济开发区上东·阳光城10号楼二层30铺皖（2017）六安市市不动产权第0066188号 | V100: 皖（2018）六安市市不动产证明第3055336号 | W100: 2047/10/20 | X100: 47.06 | Y100: 平方米 | Z100: 是 | AA100: 安徽省 | AB100: 六安市 | AC100: 金安区 | AD100: 六安市经济开发区上东·阳光城10号楼二层30铺 | AE100: 第一顺位 | AF100: 25 | AG100: 外部评估 | AH100: 45558 | AI100: 16.94 | AJ100: 否 | AL100: 不涉及 | AO100: 张乐群,曹吉峰,董俣顺,许之玮,邹熠峰,郑舒凌 | AP100: 安徽分公司 | AQ100: 12240053 | AR100: 收购颍东农商行2024年第1批12户不良资产包项目 | AS100: 45587 | AU100: 11001 | AV100: 已剔重 | AX100: =COUNTIFS(拍卖数据!E:E,AA100,拍卖数据!F:F,AB100,拍卖数据!O:O,O100,拍卖数据!P:P,">"&X100*0.8,拍卖数据!P:P,"<"&X100*1.2) -> 1 | AY100: =COUNTIFS(拍卖数据!E:E,AA100,拍卖数据!F:F,AB100,拍卖数据!O:O,O100,拍卖数据!AN:AN,"机构",拍卖数据!P:P,">"&X100*0.8,拍卖数据!P:P,"<"&X100*1.2) -> 0 | AZ100: =COUNTIFS(拍卖数据!E:E,AA100,拍卖数据!F:F,AB100,拍卖数据!G:G,AC100,拍卖数据!O:O,O100,拍卖数据!AN:AN,"机构",拍卖数据!P:P,">"&X100*0.8,拍卖数据!P:P,"<"&X100*1.2) -> 0
A101: 12224 | B101: 12240053002700000001 | C101: 否 | D101: 六安市星星矿业有限公司 | E101: 其他非金属矿物制品制造 | F101: 500 | G101: 324.90137 | H101: 2.12 | I101: 0 | J101: 827.02137 | K101: 抵押,质押,保证 | L101: 郭旭东,马艳 | M101: 172.44 | N101: 现房 | O101: 商业用房 | P101: 集中商业（购物中心，综合体商业等） | Q101: 新建 | R101: 郭旭东 | S101: 342401196801262218 | T101: 01012025091430118 | U101: 六安市经济开发区上东·阳光城10号楼二层29铺皖（2017）六安市市不动产权第0066159号 | V101: 皖（2018）六安市市不动产证明第3055333号 | W101: 2047/10/20 | X101: 49.41 | Y101: 平方米 | Z101: 是 | AA101: 安徽省 | AB101: 六安市 | AC101: 金安区 | AD101: 六安市经济开发区上东·阳光城10号楼二层29铺 | AE101: 第一顺位 | AF101: 25 | AG101: 外部评估 | AH101: 45558 | AI101: 17.79 | AJ101: 否 | AL101: 不涉及 | AO101: 张乐群,曹吉峰,董俣顺,许之玮,邹熠峰,郑舒凌 | AP101: 安徽分公司 | AQ101: 12240053 | AR101: 收购颍东农商行2024年第1批12户不良资产包项目 | AS101: 45587 | AU101: 11001 | AV101: 已剔重 | AX101: =COUNTIFS(拍卖数据!E:E,AA101,拍卖数据!F:F,AB101,拍卖数据!O:O,O101,拍卖数据!P:P,">"&X101*0.8,拍卖数据!P:P,"<"&X101*1.2) -> 0 | AY101: =COUNTIFS(拍卖数据!E:E,AA101,拍卖数据!F:F,AB101,拍卖数据!O:O,O101,拍卖数据!AN:AN,"机构",拍卖数据!P:P,">"&X101*0.8,拍卖数据!P:P,"<"&X101*1.2) -> 0 | AZ101: =COUNTIFS(拍卖数据!E:E,AA101,拍卖数据!F:F,AB101,拍卖数据!G:G,AC101,拍卖数据!O:O,O101,拍卖数据!AN:AN,"机构",拍卖数据!P:P,">"&X101*0.8,拍卖数据!P:P,"<"&X101*1.2) -> 0
A102: 12225 | B102: 12240053002700000001 | C102: 否 | D102: 六安市星星矿业有限公司 | E102: 其他非金属矿物制品制造 | F102: 500 | G102: 324.90137 | H102: 2.12 | I102: 0 | J102: 827.02137 | K102: 抵押,质押,保证 | L102: 郭旭东,马艳 | M102: 172.44 | N102: 现房 | O102: 商业用房 | P102: 集中商业（购物中心，综合体商业等） | Q102: 新建 | R102: 郭旭东 | S102: 342401196801262218 | T102: 01012025091430117 | U102: 六安市经济开发区上东·阳光城10号楼二层28铺皖（2017）六安市市不动产权第0066161号 | V102: 皖（2018）六安市市不动产证明第3055341号 | W102: 2047/10/20 | X102: 47.73 | Y102: 平方米 | Z102: 是 | AA102: 安徽省 | AB102: 六安市 | AC102: 金安区 | AD102: 六安市经济开发区上东·阳光城10号楼二层28铺 | AE102: 第一顺位 | AF102: 25 | AG102: 外部评估 | AH102: 45558 | AI102: 17.18 | AJ102: 否 | AL102: 不涉及 | AO102: 张乐群,曹吉峰,董俣顺,许之玮,邹熠峰,郑舒凌 | AP102: 安徽分公司 | AQ102: 12240053 | AR102: 收购颍东农商行2024年第1批12户不良资产包项目 | AS102: 45587 | AU102: 11001 | AV102: 已剔重 | AX102: =COUNTIFS(拍卖数据!E:E,AA102,拍卖数据!F:F,AB102,拍卖数据!O:O,O102,拍卖数据!P:P,">"&X102*0.8,拍卖数据!P:P,"<"&X102*1.2) -> 1 | AY102: =COUNTIFS(拍卖数据!E:E,AA102,拍卖数据!F:F,AB102,拍卖数据!O:O,O102,拍卖数据!AN:AN,"机构",拍卖数据!P:P,">"&X102*0.8,拍卖数据!P:P,"<"&X102*1.2) -> 0 | AZ102: =COUNTIFS(拍卖数据!E:E,AA102,拍卖数据!F:F,AB102,拍卖数据!G:G,AC102,拍卖数据!O:O,O102,拍卖数据!AN:AN,"机构",拍卖数据!P:P,">"&X102*0.8,拍卖数据!P:P,"<"&X102*1.2) -> 0
A103: 12226 | B103: 12240053002700000001 | C103: 否 | D103: 六安市星星矿业有限公司 | E103: 其他非金属矿物制品制造 | F103: 500 | G103: 324.90137 | H103: 2.12 | I103: 0 | J103: 827.02137 | K103: 抵押,质押,保证 | L103: 郭旭东,马艳 | M103: 172.44 | N103: 现房 | O103: 商业用房 | P103: 集中商业（购物中心，综合体商业等） | Q103: 新建 | R103: 郭旭东 | S103: 342401196801262218 | T103: 01012025091430116 | U103: 六安市经济开发区上东·阳光城10号楼2层7铺皖（2017）六安市市不动产权第0066164号 | V103: 皖（2018）六安市市不动产证明第3055338号 | W103: 2047/10/20 | X103: 76.36 | Y103: 平方米 | Z103: 是 | AA103: 安徽省 | AB103: 六安市 | AC103: 金安区 | AD103: 六安市经济开发区上东·阳光城10号楼2层7铺 | AE103: 第一顺位 | AF103: 40 | AG103: 外部评估 | AH103: 45558 | AI103: 27.49 | AJ103: 否 | AL103: 不涉及 | AO103: 张乐群,曹吉峰,董俣顺,许之玮,邹熠峰,郑舒凌 | AP103: 安徽分公司 | AQ103: 12240053 | AR103: 收购颍东农商行2024年第1批12户不良资产包项目 | AS103: 45587 | AU103: 11001 | AV103: 已剔重 | AX103: =COUNTIFS(拍卖数据!E:E,AA103,拍卖数据!F:F,AB103,拍卖数据!O:O,O103,拍卖数据!P:P,">"&X103*0.8,拍卖数据!P:P,"<"&X103*1.2) -> 2 | AY103: =COUNTIFS(拍卖数据!E:E,AA103,拍卖数据!F:F,AB103,拍卖数据!O:O,O103,拍卖数据!AN:AN,"机构",拍卖数据!P:P,">"&X103*0.8,拍卖数据!P:P,"<"&X103*1.2) -> 0 | AZ103: =COUNTIFS(拍卖数据!E:E,AA103,拍卖数据!F:F,AB103,拍卖数据!G:G,AC103,拍卖数据!O:O,O103,拍卖数据!AN:AN,"机构",拍卖数据!P:P,">"&X103*0.8,拍卖数据!P:P,"<"&X103*1.2) -> 0
A104: 12227 | B104: 12240053002700000001 | C104: 否 | D104: 六安市星星矿业有限公司 | E104: 其他非金属矿物制品制造 | F104: 500 | G104: 324.90137 | H104: 2.12 | I104: 0 | J104: 827.02137 | K104: 抵押,质押,保证 | L104: 郭旭东,马艳 | M104: 172.44 | N104: 现房 | O104: 商业用房 | P104: 集中商业（购物中心，综合体商业等） | Q104: 新建 | R104: 郭旭东 | S104: 342401196801262218 | T104: 01012025091430115 | U104: 六安市经济开发区上东·阳光城10号楼2层6铺皖（2017）六安市市不动产权第0066147号 | V104: 皖（2018）六安市市不动产证明第3055339号 | W104: 2047/10/20 | X104: 66.82 | Y104: 平方米 | Z104: 是 | AA104: 安徽省 | AB104: 六安市 | AC104: 金安区 | AD104: 六安市经济开发区上东·阳光城10号楼2层6铺 | AE104: 第一顺位 | AF104: 30 | AG104: 外部评估 | AH104: 45558 | AI104: 24.06 | AJ104: 否 | AL104: 不涉及 | AO104: 张乐群,曹吉峰,董俣顺,许之玮,邹熠峰,郑舒凌 | AP104: 安徽分公司 | AQ104: 12240053 | AR104: 收购颍东农商行2024年第1批12户不良资产包项目 | AS104: 45587 | AU104: 11001 | AV104: 已剔重 | AX104: =COUNTIFS(拍卖数据!E:E,AA104,拍卖数据!F:F,AB104,拍卖数据!O:O,O104,拍卖数据!P:P,">"&X104*0.8,拍卖数据!P:P,"<"&X104*1.2) -> 0 | AY104: =COUNTIFS(拍卖数据!E:E,AA104,拍卖数据!F:F,AB104,拍卖数据!O:O,O104,拍卖数据!AN:AN,"机构",拍卖数据!P:P,">"&X104*0.8,拍卖数据!P:P,"<"&X104*1.2) -> 0 | AZ104: =COUNTIFS(拍卖数据!E:E,AA104,拍卖数据!F:F,AB104,拍卖数据!G:G,AC104,拍卖数据!O:O,O104,拍卖数据!AN:AN,"机构",拍卖数据!P:P,">"&X104*0.8,拍卖数据!P:P,"<"&X104*1.2) -> 0
A105: 12228 | B105: 12240053002700000001 | C105: 否 | D105: 六安市星星矿业有限公司 | E105: 其他非金属矿物制品制造 | F105: 500 | G105: 324.90137 | H105: 2.12 | I105: 0 | J105: 827.02137 | K105: 抵押,质押,保证 | L105: 郭旭东,马艳 | M105: 172.44 | N105: 现房 | O105: 商业用房 | P105: 集中商业（购物中心，综合体商业等） | Q105: 新建 | R105: 郭旭东 | S105: 342401196801262218 | T105: 01012025091430114 | U105: 六安市经济开发区上东·阳光城10号楼24铺（1-2层）皖（2017）六安市市不动产权第0066163号 | V105: 皖（2018）六安市市不动产证明第3055342号 | W105: 2047/10/20 | X105: 95.46 | Y105: 平方米 | Z105: 是 | AA105: 安徽省 | AB105: 六安市 | AC105: 金安区 | AD105: 六安市经济开发区上东·阳光城10号楼24铺（1-2层） | AE105: 第一顺位 | AF105: 70 | AG105: 外部评估 | AH105: 45558 | AI105: 78.28 | AJ105: 否 | AL105: 不涉及 | AO105: 张乐群,曹吉峰,董俣顺,许之玮,邹熠峰,郑舒凌 | AP105: 安徽分公司 | AQ105: 12240053 | AR105: 收购颍东农商行2024年第1批12户不良资产包项目 | AS105: 45587 | AU105: 11001 | AV105: 已剔重 | AX105: =COUNTIFS(拍卖数据!E:E,AA105,拍卖数据!F:F,AB105,拍卖数据!O:O,O105,拍卖数据!P:P,">"&X105*0.8,拍卖数据!P:P,"<"&X105*1.2) -> 9 | AY105: =COUNTIFS(拍卖数据!E:E,AA105,拍卖数据!F:F,AB105,拍卖数据!O:O,O105,拍卖数据!AN:AN,"机构",拍卖数据!P:P,">"&X105*0.8,拍卖数据!P:P,"<"&X105*1.2) -> 0 | AZ105: =COUNTIFS(拍卖数据!E:E,AA105,拍卖数据!F:F,AB105,拍卖数据!G:G,AC105,拍卖数据!O:O,O105,拍卖数据!AN:AN,"机构",拍卖数据!P:P,">"&X105*0.8,拍卖数据!P:P,"<"&X105*1.2) -> 0
A106: 12229 | B106: 12240053002700000001 | C106: 否 | D106: 六安市星星矿业有限公司 | E106: 其他非金属矿物制品制造 | F106: 500 | G106: 324.90137 | H106: 2.12 | I106: 0 | J106: 827.02137 | K106: 抵押,质押,保证 | L106: 郭旭东,马艳 | M106: 172.44 | N106: 现房 | O106: 商业用房 | P106: 集中商业（购物中心，综合体商业等） | Q106: 新建 | R106: 郭旭东 | S106: 342401196801262218 | T106: 01012025091430113 | U106: 六安市经济开发区上东·阳光城10号楼23铺（1-2层）皖（2017）六安市市不动产权第0066162号 | V106: 皖（2018）六安市市不动产证明第3055343号 | W106: 2047/10/20 | X106: 97.48 | Y106: 平方米 | Z106: 是 | AA106: 安徽省 | AB106: 六安市 | AC106: 金安区 | AD106: 六安市经济开发区上东·阳光城10号楼23铺（1-2层） | AE106: 第一顺位 | AF106: 70 | AG106: 外部评估 | AH106: 45558 | AI106: 79.93 | AJ106: 否 | AL106: 不涉及 | AO106: 张乐群,曹吉峰,董俣顺,许之玮,邹熠峰,郑舒凌 | AP106: 安徽分公司 | AQ106: 12240053 | AR106: 收购颍东农商行2024年第1批12户不良资产包项目 | AS106: 45587 | AU106: 11001 | AV106: 已剔重 | AX106: =COUNTIFS(拍卖数据!E:E,AA106,拍卖数据!F:F,AB106,拍卖数据!O:O,O106,拍卖数据!P:P,">"&X106*0.8,拍卖数据!P:P,"<"&X106*1.2) -> 9 | AY106: =COUNTIFS(拍卖数据!E:E,AA106,拍卖数据!F:F,AB106,拍卖数据!O:O,O106,拍卖数据!AN:AN,"机构",拍卖数据!P:P,">"&X106*0.8,拍卖数据!P:P,"<"&X106*1.2) -> 0 | AZ106: =COUNTIFS(拍卖数据!E:E,AA106,拍卖数据!F:F,AB106,拍卖数据!G:G,AC106,拍卖数据!O:O,O106,拍卖数据!AN:AN,"机构",拍卖数据!P:P,">"&X106*0.8,拍卖数据!P:P,"<"&X106*1.2) -> 0
A107: 13150 | B107: 05180054000100000001 | C107: 否 | D107: 内蒙古旭通实业有限公司 | E107: 农业 | F107: 9917.4329 | G107: 299.32102 | H107: 0 | I107: 1749.6758 | J107: 10216.754 | K107: 抵押,质押,保证 | L107: 刘振峰 | M107: 4690.7374 | N107: 现房 | O107: 商业用房 | P107: 集中商业（购物中心，综合体商业等） | Q107: 已入库 | R107: 南陵江南国际置业有限公司 | S107: 913402235592258415 | T107: 01012025091230206 | U107: 南陵县籍山镇江南国际A3幢404室房产 | V107: 房地产他证南陵县字第20160287号 | W107: 2055/12/31 | X107: 104.78 | Y107: 平方米 | Z107: 是 | AA107: 安徽省 | AB107: 芜湖市 | AC107: 南陵县 | AD107: 籍山镇江南国际A3幢404室 | AE107: 第一顺位 | AG107: 外部评估 | AH107: 44209 | AI107: 46.059368 | AJ107: 是 | AK107: A03.押品被私售、抵债、转移或占用，难以追讨或清退 | AL107: 不涉及 | AO107: 刘秀丽,张彤(内蒙古分公司),李伊军,李鑫,杨婷婷,梅森,王雪琰,贺汝德,郭利德,陈丽 | AP107: 内蒙古分公司 | AQ107: 05180054 | AR107: 收购国家开发银行内蒙古分行旭通实业有限公司等3户不良资产包项目 | AS107: 43473 | AU107: 11001 | AV107: 已剔重 | AX107: =COUNTIFS(拍卖数据!E:E,AA107,拍卖数据!F:F,AB107,拍卖数据!O:O,O107,拍卖数据!P:P,">"&X107*0.8,拍卖数据!P:P,"<"&X107*1.2) -> 6 | AY107: =COUNTIFS(拍卖数据!E:E,AA107,拍卖数据!F:F,AB107,拍卖数据!O:O,O107,拍卖数据!AN:AN,"机构",拍卖数据!P:P,">"&X107*0.8,拍卖数据!P:P,"<"&X107*1.2) -> 0 | AZ107: =COUNTIFS(拍卖数据!E:E,AA107,拍卖数据!F:F,AB107,拍卖数据!G:G,AC107,拍卖数据!O:O,O107,拍卖数据!AN:AN,"机构",拍卖数据!P:P,">"&X107*0.8,拍卖数据!P:P,"<"&X107*1.2) -> 0
A108: 13151 | B108: 05180054000100000001 | C108: 否 | D108: 内蒙古旭通实业有限公司 | E108: 农业 | F108: 9917.4329 | G108: 299.32102 | H108: 0 | I108: 1749.6758 | J108: 10216.754 | K108: 抵押,质押,保证 | L108: 刘振峰 | M108: 4690.7374 | N108: 现房 | O108: 商业用房 | P108: 集中商业（购物中心，综合体商业等） | Q108: 已入库 | R108: 南陵江南国际置业有限公司 | S108: 913402235592258415 | T108: 01012025091230425 | U108: 南陵县籍山镇江南国际F1幢131室房产 | V108: 房地产他证南陵县字第20160287号 | W108: 2055/12/31 | X108: 48.67 | Y108: 平方米 | Z108: 是 | AA108: 安徽省 | AB108: 芜湖市 | AC108: 南陵县 | AD108: 籍山镇江南国际F1幢131室 | AE108: 第一顺位 | AG108: 外部评估 | AH108: 44209 | AI108: 46.059368 | AJ108: 是 | AK108: A03.押品被私售、抵债、转移或占用，难以追讨或清退 | AL108: 不涉及 | AO108: 刘秀丽,张彤(内蒙古分公司),李伊军,李鑫,杨婷婷,梅森,王雪琰,贺汝德,郭利德,陈丽 | AP108: 内蒙古分公司 | AQ108: 05180054 | AR108: 收购国家开发银行内蒙古分行旭通实业有限公司等3户不良资产包项目 | AS108: 43473 | AU108: 11001 | AV108: 已剔重 | AX108: =COUNTIFS(拍卖数据!E:E,AA108,拍卖数据!F:F,AB108,拍卖数据!O:O,O108,拍卖数据!P:P,">"&X108*0.8,拍卖数据!P:P,"<"&X108*1.2) -> 20 | AY108: =COUNTIFS(拍卖数据!E:E,AA108,拍卖数据!F:F,AB108,拍卖数据!O:O,O108,拍卖数据!AN:AN,"机构",拍卖数据!P:P,">"&X108*0.8,拍卖数据!P:P,"<"&X108*1.2) -> 0 | AZ108: =COUNTIFS(拍卖数据!E:E,AA108,拍卖数据!F:F,AB108,拍卖数据!G:G,AC108,拍卖数据!O:O,O108,拍卖数据!AN:AN,"机构",拍卖数据!P:P,">"&X108*0.8,拍卖数据!P:P,"<"&X108*1.2) -> 0
A109: 13152 | B109: 05180054000100000001 | C109: 否 | D109: 内蒙古旭通实业有限公司 | E109: 农业 | F109: 9917.4329 | G109: 299.32102 | H109: 0 | I109: 1749.6758 | J109: 10216.754 | K109: 抵押,质押,保证 | L109: 刘振峰 | M109: 4690.7374 | N109: 现房 | O109: 商业用房 | P109: 集中商业（购物中心，综合体商业等） | Q109: 已入库 | R109: 南陵江南国际置业有限公司 | S109: 913402235592258415 | T109: 01012025091230424 | U109: 南陵县籍山镇江南国际F1幢130室房产 | V109: 房地产他证南陵县字第20160287号 | W109: 2055/12/31 | X109: 48.67 | Y109: 平方米 | Z109: 是 | AA109: 安徽省 | AB109: 芜湖市 | AC109: 南陵县 | AD109: 籍山镇江南国际F1幢130室 | AE109: 第一顺位 | AG109: 外部评估 | AH109: 44209 | AI109: 46.059368 | AJ109: 是 | AK109: A03.押品被私售、抵债、转移或占用，难以追讨或清退 | AL109: 不涉及 | AO109: 刘秀丽,张彤(内蒙古分公司),李伊军,李鑫,杨婷婷,梅森,王雪琰,贺汝德,郭利德,陈丽 | AP109: 内蒙古分公司 | AQ109: 05180054 | AR109: 收购国家开发银行内蒙古分行旭通实业有限公司等3户不良资产包项目 | AS109: 43473 | AU109: 11001 | AV109: 已剔重 | AX109: =COUNTIFS(拍卖数据!E:E,AA109,拍卖数据!F:F,AB109,拍卖数据!O:O,O109,拍卖数据!P:P,">"&X109*0.8,拍卖数据!P:P,"<"&X109*1.2) -> 20 | AY109: =COUNTIFS(拍卖数据!E:E,AA109,拍卖数据!F:F,AB109,拍卖数据!O:O,O109,拍卖数据!AN:AN,"机构",拍卖数据!P:P,">"&X109*0.8,拍卖数据!P:P,"<"&X109*1.2) -> 0 | AZ109: =COUNTIFS(拍卖数据!E:E,AA109,拍卖数据!F:F,AB109,拍卖数据!G:G,AC109,拍卖数据!O:O,O109,拍卖数据!AN:AN,"机构",拍卖数据!P:P,">"&X109*0.8,拍卖数据!P:P,"<"&X109*1.2) -> 0
A110: 13153 | B110: 05180054000100000001 | C110: 否 | D110: 内蒙古旭通实业有限公司 | E110: 农业 | F110: 9917.4329 | G110: 299.32102 | H110: 0 | I110: 1749.6758 | J110: 10216.754 | K110: 抵押,质押,保证 | L110: 刘振峰 | M110: 4690.7374 | N110: 现房 | O110: 商业用房 | P110: 集中商业（购物中心，综合体商业等） | Q110: 已入库 | R110: 南陵江南国际置业有限公司 | S110: 913402235592258415 | T110: 01012025091230423 | U110: 南陵县籍山镇江南国际F1幢129室房产 | V110: 房地产他证南陵县字第20160287号 | W110: 2055/12/31 | X110: 48.67 | Y110: 平方米 | Z110: 是 | AA110: 安徽省 | AB110: 芜湖市 | AC110: 南陵县 | AD110: 籍山镇江南国际F1幢129室 | AE110: 第一顺位 | AG110: 外部评估 | AH110: 44209 | AI110: 46.059368 | AJ110: 是 | AK110: A03.押品被私售、抵债、转移或占用，难以追讨或清退 | AL110: 不涉及 | AO110: 刘秀丽,张彤(内蒙古分公司),李伊军,李鑫,杨婷婷,梅森,王雪琰,贺汝德,郭利德,陈丽 | AP110: 内蒙古分公司 | AQ110: 05180054 | AR110: 收购国家开发银行内蒙古分行旭通实业有限公司等3户不良资产包项目 | AS110: 43473 | AU110: 11001 | AV110: 已剔重 | AX110: =COUNTIFS(拍卖数据!E:E,AA110,拍卖数据!F:F,AB110,拍卖数据!O:O,O110,拍卖数据!P:P,">"&X110*0.8,拍卖数据!P:P,"<"&X110*1.2) -> 20 | AY110: =COUNTIFS(拍卖数据!E:E,AA110,拍卖数据!F:F,AB110,拍卖数据!O:O,O110,拍卖数据!AN:AN,"机构",拍卖数据!P:P,">"&X110*0.8,拍卖数据!P:P,"<"&X110*1.2) -> 0 | AZ110: =COUNTIFS(拍卖数据!E:E,AA110,拍卖数据!F:F,AB110,拍卖数据!G:G,AC110,拍卖数据!O:O,O110,拍卖数据!AN:AN,"机构",拍卖数据!P:P,">"&X110*0.8,拍卖数据!P:P,"<"&X110*1.2) -> 0
A111: 13154 | B111: 05180054000100000001 | C111: 否 | D111: 内蒙古旭通实业有限公司 | E111: 农业 | F111: 9917.4329 | G111: 299.32102 | H111: 0 | I111: 1749.6758 | J111: 10216.754 | K111: 抵押,质押,保证 | L111: 刘振峰 | M111: 4690.7374 | N111: 现房 | O111: 商业用房 | P111: 集中商业（购物中心，综合体商业等） | Q111: 已入库 | R111: 南陵江南国际置业有限公司 | S111: 913402235592258415 | T111: 01012025091230422 | U111: 南陵县籍山镇江南国际F1幢128室房产 | V111: 房地产他证南陵县字第20160287号 | W111: 2055/12/31 | X111: 24.33 | Y111: 平方米 | Z111: 是 | AA111: 安徽省 | AB111: 芜湖市 | AC111: 南陵县 | AD111: 籍山镇江南国际F1幢128室 | AE111: 第一顺位 | AG111: 外部评估 | AH111: 44209 | AI111: 46.059368 | AJ111: 是 | AK111: A03.押品被私售、抵债、转移或占用，难以追讨或清退 | AL111: 不涉及 | AO111: 刘秀丽,张彤(内蒙古分公司),李伊军,李鑫,杨婷婷,梅森,王雪琰,贺汝德,郭利德,陈丽 | AP111: 内蒙古分公司 | AQ111: 05180054 | AR111: 收购国家开发银行内蒙古分行旭通实业有限公司等3户不良资产包项目 | AS111: 43473 | AU111: 11001 | AV111: 已剔重 | AX111: =COUNTIFS(拍卖数据!E:E,AA111,拍卖数据!F:F,AB111,拍卖数据!O:O,O111,拍卖数据!P:P,">"&X111*0.8,拍卖数据!P:P,"<"&X111*1.2) -> 0 | AY111: =COUNTIFS(拍卖数据!E:E,AA111,拍卖数据!F:F,AB111,拍卖数据!O:O,O111,拍卖数据!AN:AN,"机构",拍卖数据!P:P,">"&X111*0.8,拍卖数据!P:P,"<"&X111*1.2) -> 0 | AZ111: =COUNTIFS(拍卖数据!E:E,AA111,拍卖数据!F:F,AB111,拍卖数据!G:G,AC111,拍卖数据!O:O,O111,拍卖数据!AN:AN,"机构",拍卖数据!P:P,">"&X111*0.8,拍卖数据!P:P,"<"&X111*1.2) -> 0
A112: 13155 | B112: 05180054000100000001 | C112: 否 | D112: 内蒙古旭通实业有限公司 | E112: 农业 | F112: 9917.4329 | G112: 299.32102 | H112: 0 | I112: 1749.6758 | J112: 10216.754 | K112: 抵押,质押,保证 | L112: 刘振峰 | M112: 4690.7374 | N112: 现房 | O112: 商业用房 | P112: 集中商业（购物中心，综合体商业等） | Q112: 已入库 | R112: 南陵江南国际置业有限公司 | S112: 913402235592258415 | T112: 01012025091230421 | U112: 南陵县籍山镇江南国际F1幢127室房产 | V112: 房地产他证南陵县字第20160287号 | W112: 2055/12/31 | X112: 36.02 | Y112: 平方米 | Z112: 是 | AA112: 安徽省 | AB112: 芜湖市 | AC112: 南陵县 | AD112: 籍山镇江南国际F1幢127室 | AE112: 第一顺位 | AG112: 外部评估 | AH112: 44209 | AI112: 46.059368 | AJ112: 是 | AK112: A03.押品被私售、抵债、转移或占用，难以追讨或清退 | AL112: 不涉及 | AO112: 刘秀丽,张彤(内蒙古分公司),李伊军,李鑫,杨婷婷,梅森,王雪琰,贺汝德,郭利德,陈丽 | AP112: 内蒙古分公司 | AQ112: 05180054 | AR112: 收购国家开发银行内蒙古分行旭通实业有限公司等3户不良资产包项目 | AS112: 43473 | AU112: 11001 | AV112: 已剔重 | AX112: =COUNTIFS(拍卖数据!E:E,AA112,拍卖数据!F:F,AB112,拍卖数据!O:O,O112,拍卖数据!P:P,">"&X112*0.8,拍卖数据!P:P,"<"&X112*1.2) -> 2 | AY112: =COUNTIFS(拍卖数据!E:E,AA112,拍卖数据!F:F,AB112,拍卖数据!O:O,O112,拍卖数据!AN:AN,"机构",拍卖数据!P:P,">"&X112*0.8,拍卖数据!P:P,"<"&X112*1.2) -> 0 | AZ112: =COUNTIFS(拍卖数据!E:E,AA112,拍卖数据!F:F,AB112,拍卖数据!G:G,AC112,拍卖数据!O:O,O112,拍卖数据!AN:AN,"机构",拍卖数据!P:P,">"&X112*0.8,拍卖数据!P:P,"<"&X112*1.2) -> 0
A113: 13156 | B113: 05180054000100000001 | C113: 否 | D113: 内蒙古旭通实业有限公司 | E113: 农业 | F113: 9917.4329 | G113: 299.32102 | H113: 0 | I113: 1749.6758 | J113: 10216.754 | K113: 抵押,质押,保证 | L113: 刘振峰 | M113: 4690.7374 | N113: 现房 | O113: 商业用房 | P113: 集中商业（购物中心，综合体商业等） | Q113: 已入库 | R113: 南陵江南国际置业有限公司 | S113: 913402235592258415 | T113: 01012025091230420 | U113: 南陵县籍山镇江南国际F1幢126室房产 | V113: 房地产他证南陵县字第20160287号 | W113: 2055/12/31 | X113: 36.02 | Y113: 平方米 | Z113: 是 | AA113: 安徽省 | AB113: 芜湖市 | AC113: 南陵县 | AD113: 籍山镇江南国际F1幢126室 | AE113: 第一顺位 | AG113: 外部评估 | AH113: 44209 | AI113: 46.059368 | AJ113: 是 | AK113: A03.押品被私售、抵债、转移或占用，难以追讨或清退 | AL113: 不涉及 | AO113: 刘秀丽,张彤(内蒙古分公司),李伊军,李鑫,杨婷婷,梅森,王雪琰,贺汝德,郭利德,陈丽 | AP113: 内蒙古分公司 | AQ113: 05180054 | AR113: 收购国家开发银行内蒙古分行旭通实业有限公司等3户不良资产包项目 | AS113: 43473 | AU113: 11001 | AV113: 已剔重 | AX113: =COUNTIFS(拍卖数据!E:E,AA113,拍卖数据!F:F,AB113,拍卖数据!O:O,O113,拍卖数据!P:P,">"&X113*0.8,拍卖数据!P:P,"<"&X113*1.2) -> 2 | AY113: =COUNTIFS(拍卖数据!E:E,AA113,拍卖数据!F:F,AB113,拍卖数据!O:O,O113,拍卖数据!AN:AN,"机构",拍卖数据!P:P,">"&X113*0.8,拍卖数据!P:P,"<"&X113*1.2) -> 0 | AZ113: =COUNTIFS(拍卖数据!E:E,AA113,拍卖数据!F:F,AB113,拍卖数据!G:G,AC113,拍卖数据!O:O,O113,拍卖数据!AN:AN,"机构",拍卖数据!P:P,">"&X113*0.8,拍卖数据!P:P,"<"&X113*1.2) -> 0
A114: 13157 | B114: 05180054000100000001 | C114: 否 | D114: 内蒙古旭通实业有限公司 | E114: 农业 | F114: 9917.4329 | G114: 299.32102 | H114: 0 | I114: 1749.6758 | J114: 10216.754 | K114: 抵押,质押,保证 | L114: 刘振峰 | M114: 4690.7374 | N114: 现房 | O114: 商业用房 | P114: 集中商业（购物中心，综合体商业等） | Q114: 已入库 | R114: 南陵江南国际置业有限公司 | S114: 913402235592258415 | T114: 01012025091230419 | U114: 南陵县籍山镇江南国际F1幢125室房产 | V114: 房地产他证南陵县字第20160287号 | W114: 2055/12/31 | X114: 48.03 | Y114: 平方米 | Z114: 是 | AA114: 安徽省 | AB114: 芜湖市 | AC114: 南陵县 | AD114: 籍山镇江南国际F1幢125室 | AE114: 第一顺位 | AG114: 外部评估 | AH114: 44209 | AI114: 46.059368 | AJ114: 是 | AK114: A03.押品被私售、抵债、转移或占用，难以追讨或清退 | AL114: 不涉及 | AO114: 刘秀丽,张彤(内蒙古分公司),李伊军,李鑫,杨婷婷,梅森,王雪琰,贺汝德,郭利德,陈丽 | AP114: 内蒙古分公司 | AQ114: 05180054 | AR114: 收购国家开发银行内蒙古分行旭通实业有限公司等3户不良资产包项目 | AS114: 43473 | AU114: 11001 | AV114: 已剔重 | AX114: =COUNTIFS(拍卖数据!E:E,AA114,拍卖数据!F:F,AB114,拍卖数据!O:O,O114,拍卖数据!P:P,">"&X114*0.8,拍卖数据!P:P,"<"&X114*1.2) -> 20 | AY114: =COUNTIFS(拍卖数据!E:E,AA114,拍卖数据!F:F,AB114,拍卖数据!O:O,O114,拍卖数据!AN:AN,"机构",拍卖数据!P:P,">"&X114*0.8,拍卖数据!P:P,"<"&X114*1.2) -> 0 | AZ114: =COUNTIFS(拍卖数据!E:E,AA114,拍卖数据!F:F,AB114,拍卖数据!G:G,AC114,拍卖数据!O:O,O114,拍卖数据!AN:AN,"机构",拍卖数据!P:P,">"&X114*0.8,拍卖数据!P:P,"<"&X114*1.2) -> 0
A115: 13158 | B115: 05180054000100000001 | C115: 否 | D115: 内蒙古旭通实业有限公司 | E115: 农业 | F115: 9917.4329 | G115: 299.32102 | H115: 0 | I115: 1749.6758 | J115: 10216.754 | K115: 抵押,质押,保证 | L115: 刘振峰 | M115: 4690.7374 | N115: 现房 | O115: 商业用房 | P115: 集中商业（购物中心，综合体商业等） | Q115: 已入库 | R115: 南陵江南国际置业有限公司 | S115: 913402235592258415 | T115: 01012025091230418 | U115: 南陵县籍山镇江南国际F1幢124室房产 | V115: 房地产他证南陵县字第20160287号 | W115: 2055/12/31 | X115: 48.03 | Y115: 平方米 | Z115: 是 | AA115: 安徽省 | AB115: 芜湖市 | AC115: 南陵县 | AD115: 籍山镇江南国际F1幢124室 | AE115: 第一顺位 | AG115: 外部评估 | AH115: 44209 | AI115: 46.059368 | AJ115: 是 | AK115: A03.押品被私售、抵债、转移或占用，难以追讨或清退 | AL115: 不涉及 | AO115: 刘秀丽,张彤(内蒙古分公司),李伊军,李鑫,杨婷婷,梅森,王雪琰,贺汝德,郭利德,陈丽 | AP115: 内蒙古分公司 | AQ115: 05180054 | AR115: 收购国家开发银行内蒙古分行旭通实业有限公司等3户不良资产包项目 | AS115: 43473 | AU115: 11001 | AV115: 已剔重 | AX115: =COUNTIFS(拍卖数据!E:E,AA115,拍卖数据!F:F,AB115,拍卖数据!O:O,O115,拍卖数据!P:P,">"&X115*0.8,拍卖数据!P:P,"<"&X115*1.2) -> 20 | AY115: =COUNTIFS(拍卖数据!E:E,AA115,拍卖数据!F:F,AB115,拍卖数据!O:O,O115,拍卖数据!AN:AN,"机构",拍卖数据!P:P,">"&X115*0.8,拍卖数据!P:P,"<"&X115*1.2) -> 0 | AZ115: =COUNTIFS(拍卖数据!E:E,AA115,拍卖数据!F:F,AB115,拍卖数据!G:G,AC115,拍卖数据!O:O,O115,拍卖数据!AN:AN,"机构",拍卖数据!P:P,">"&X115*0.8,拍卖数据!P:P,"<"&X115*1.2) -> 0
A116: 13159 | B116: 05180054000100000001 | C116: 否 | D116: 内蒙古旭通实业有限公司 | E116: 农业 | F116: 9917.4329 | G116: 299.32102 | H116: 0 | I116: 1749.6758 | J116: 10216.754 | K116: 抵押,质押,保证 | L116: 刘振峰 | M116: 4690.7374 | N116: 现房 | O116: 商业用房 | P116: 集中商业（购物中心，综合体商业等） | Q116: 已入库 | R116: 南陵江南国际置业有限公司 | S116: 913402235592258415 | T116: 01012025091230417 | U116: 南陵县籍山镇江南国际F1幢123室房产 | V116: 房地产他证南陵县字第20160287号 | W116: 2055/12/31 | X116: 48.03 | Y116: 平方米 | Z116: 是 | AA116: 安徽省 | AB116: 芜湖市 | AC116: 南陵县 | AD116: 籍山镇江南国际F1幢123室 | AE116: 第一顺位 | AG116: 外部评估 | AH116: 44209 | AI116: 46.059368 | AJ116: 是 | AK116: A03.押品被私售、抵债、转移或占用，难以追讨或清退 | AL116: 不涉及 | AO116: 刘秀丽,张彤(内蒙古分公司),李伊军,李鑫,杨婷婷,梅森,王雪琰,贺汝德,郭利德,陈丽 | AP116: 内蒙古分公司 | AQ116: 05180054 | AR116: 收购国家开发银行内蒙古分行旭通实业有限公司等3户不良资产包项目 | AS116: 43473 | AU116: 11001 | AV116: 已剔重 | AX116: =COUNTIFS(拍卖数据!E:E,AA116,拍卖数据!F:F,AB116,拍卖数据!O:O,O116,拍卖数据!P:P,">"&X116*0.8,拍卖数据!P:P,"<"&X116*1.2) -> 20 | AY116: =COUNTIFS(拍卖数据!E:E,AA116,拍卖数据!F:F,AB116,拍卖数据!O:O,O116,拍卖数据!AN:AN,"机构",拍卖数据!P:P,">"&X116*0.8,拍卖数据!P:P,"<"&X116*1.2) -> 0 | AZ116: =COUNTIFS(拍卖数据!E:E,AA116,拍卖数据!F:F,AB116,拍卖数据!G:G,AC116,拍卖数据!O:O,O116,拍卖数据!AN:AN,"机构",拍卖数据!P:P,">"&X116*0.8,拍卖数据!P:P,"<"&X116*1.2) -> 0
A117: 13160 | B117: 05180054000100000001 | C117: 否 | D117: 内蒙古旭通实业有限公司 | E117: 农业 | F117: 9917.4329 | G117: 299.32102 | H117: 0 | I117: 1749.6758 | J117: 10216.754 | K117: 抵押,质押,保证 | L117: 刘振峰 | M117: 4690.7374 | N117: 现房 | O117: 商业用房 | P117: 集中商业（购物中心，综合体商业等） | Q117: 已入库 | R117: 南陵江南国际置业有限公司 | S117: 913402235592258415 | T117: 01012025091230416 | U117: 南陵县籍山镇江南国际F1幢122室房产 | V117: 房地产他证南陵县字第20160287号 | W117: 2055/12/31 | X117: 48.03 | Y117: 平方米 | Z117: 是 | AA117: 安徽省 | AB117: 芜湖市 | AC117: 南陵县 | AD117: 籍山镇江南国际F1幢122室 | AE117: 第一顺位 | AG117: 外部评估 | AH117: 44209 | AI117: 46.059368 | AJ117: 是 | AK117: A03.押品被私售、抵债、转移或占用，难以追讨或清退 | AL117: 不涉及 | AO117: 刘秀丽,张彤(内蒙古分公司),李伊军,李鑫,杨婷婷,梅森,王雪琰,贺汝德,郭利德,陈丽 | AP117: 内蒙古分公司 | AQ117: 05180054 | AR117: 收购国家开发银行内蒙古分行旭通实业有限公司等3户不良资产包项目 | AS117: 43473 | AU117: 11001 | AV117: 已剔重 | AX117: =COUNTIFS(拍卖数据!E:E,AA117,拍卖数据!F:F,AB117,拍卖数据!O:O,O117,拍卖数据!P:P,">"&X117*0.8,拍卖数据!P:P,"<"&X117*1.2) -> 20 | AY117: =COUNTIFS(拍卖数据!E:E,AA117,拍卖数据!F:F,AB117,拍卖数据!O:O,O117,拍卖数据!AN:AN,"机构",拍卖数据!P:P,">"&X117*0.8,拍卖数据!P:P,"<"&X117*1.2) -> 0 | AZ117: =COUNTIFS(拍卖数据!E:E,AA117,拍卖数据!F:F,AB117,拍卖数据!G:G,AC117,拍卖数据!O:O,O117,拍卖数据!AN:AN,"机构",拍卖数据!P:P,">"&X117*0.8,拍卖数据!P:P,"<"&X117*1.2) -> 0
A118: 13161 | B118: 05180054000100000001 | C118: 否 | D118: 内蒙古旭通实业有限公司 | E118: 农业 | F118: 9917.4329 | G118: 299.32102 | H118: 0 | I118: 1749.6758 | J118: 10216.754 | K118: 抵押,质押,保证 | L118: 刘振峰 | M118: 4690.7374 | N118: 现房 | O118: 商业用房 | P118: 集中商业（购物中心，综合体商业等） | Q118: 已入库 | R118: 南陵江南国际置业有限公司 | S118: 913402235592258415 | T118: 01012025091230415 | U118: 南陵县籍山镇江南国际F1幢121室房产 | V118: 房地产他证南陵县字第20160287号 | W118: 2055/12/31 | X118: 48.03 | Y118: 平方米 | Z118: 是 | AA118: 安徽省 | AB118: 芜湖市 | AC118: 南陵县 | AD118: 籍山镇江南国际F1幢121室 | AE118: 第一顺位 | AG118: 外部评估 | AH118: 44209 | AI118: 46.059368 | AJ118: 是 | AK118: A03.押品被私售、抵债、转移或占用，难以追讨或清退 | AL118: 不涉及 | AO118: 刘秀丽,张彤(内蒙古分公司),李伊军,李鑫,杨婷婷,梅森,王雪琰,贺汝德,郭利德,陈丽 | AP118: 内蒙古分公司 | AQ118: 05180054 | AR118: 收购国家开发银行内蒙古分行旭通实业有限公司等3户不良资产包项目 | AS118: 43473 | AU118: 11001 | AV118: 已剔重 | AX118: =COUNTIFS(拍卖数据!E:E,AA118,拍卖数据!F:F,AB118,拍卖数据!O:O,O118,拍卖数据!P:P,">"&X118*0.8,拍卖数据!P:P,"<"&X118*1.2) -> 20 | AY118: =COUNTIFS(拍卖数据!E:E,AA118,拍卖数据!F:F,AB118,拍卖数据!O:O,O118,拍卖数据!AN:AN,"机构",拍卖数据!P:P,">"&X118*0.8,拍卖数据!P:P,"<"&X118*1.2) -> 0 | AZ118: =COUNTIFS(拍卖数据!E:E,AA118,拍卖数据!F:F,AB118,拍卖数据!G:G,AC118,拍卖数据!O:O,O118,拍卖数据!AN:AN,"机构",拍卖数据!P:P,">"&X118*0.8,拍卖数据!P:P,"<"&X118*1.2) -> 0
... A391: 13435 | B391: 05180054000100000001 | C391: 否 | D391: 内蒙古旭通实业有限公司 | E391: 农业 | F391: 9917.4329 | G391: 299.32102 | H391: 0 | I391: 1749.6758 | J391: 10216.754 | K391: 抵押,质押,保证 | L391: 刘振峰 | M391: 4690.7374 | N391: 现房 | O391: 商业用房 | P391: 集中商业（购物中心，综合体商业等） | Q391: 已入库 | R391: 南陵江南国际置业有限公司 | S391: 913402235592258415 | T391: 01012025091230207 | U391: 南陵县籍山镇江南国际A3幢405室房产 | V391: 房地产他证南陵县字第20160287号 | W391: 2055/12/31 | X391: 75.63 | Y391: 平方米 | Z391: 是 | AA391: 安徽省 | AB391: 芜湖市 | AC391: 南陵县 | AD391: 籍山镇江南国际A3幢405室 | AE391: 第一顺位 | AG391: 外部评估 | AH391: 44209 | AI391: 46.059368 | AJ391: 是 | AK391: A03.押品被私售、抵债、转移或占用，难以追讨或清退 | AL391: 不涉及 | AO391: 刘秀丽,张彤(内蒙古分公司),李伊军,李鑫,杨婷婷,梅森,王雪琰,贺汝德,郭利德,陈丽 | AP391: 内蒙古分公司 | AQ391: 05180054 | AR391: 收购国家开发银行内蒙古分行旭通实业有限公司等3户不良资产包项目 | AS391: 43473 | AU391: 11001 | AV391: 已剔重 | AX391: =COUNTIFS(拍卖数据!E:E,AA391,拍卖数据!F:F,AB391,拍卖数据!O:O,O391,拍卖数据!P:P,">"&X391*0.8,拍卖数据!P:P,"<"&X391*1.2) -> 15 | AY391: =COUNTIFS(拍卖数据!E:E,AA391,拍卖数据!F:F,AB391,拍卖数据!O:O,O391,拍卖数据!AN:AN,"机构",拍卖数据!P:P,">"&X391*0.8,拍卖数据!P:P,"<"&X391*1.2) -> 0 | AZ391: =COUNTIFS(拍卖数据!E:E,AA391,拍卖数据!F:F,AB391,拍卖数据!G:G,AC391,拍卖数据!O:O,O391,拍卖数据!AN:AN,"机构",拍卖数据!P:P,">"&X391*0.8,拍卖数据!P:P,"<"&X391*1.2) -> 0
A392: 13647 | B392: 1217N072002300000001 | C392: 否 | D392: 凤台县明友物贸有限责任公司 | E392: 煤炭及制品批发 | F392: 0 | G392: 129.83511 | H392: 0 | I392: 0 | J392: 129.83511 | K392: 抵押,质押,保证 | M392: 103.87426 | N392: 现房 | O392: 商业用房 | P392: 集中商业（购物中心，综合体商业等） | Q392: 新建 | R392: 刘洋 | S392: 340404195703010095 | T392: 01012025081220401 | U392: 原胜发大厦（瑞金大厦）综合楼23层房地权淮田字第01021819号 | V392: 淮房地产他证淮田字第13024155号 | W392: 2042/1/1 | X392: 1061.42 | Y392: 平方米 | Z392: 是 | AA392: 安徽省 | AB392: 淮南市 | AC392: 田家庵区 | AD392: 原胜发大厦（瑞金大厦）综合楼23层 | AE392: 第一顺位 | AF392: 350 | AG392: 外部评估 | AH392: 43002 | AI392: 354.51 | AJ392: 否 | AL392: 不涉及 | AO392: 刘伟(安徽分公司),姜碧霏,张乐群,张梅,戴宁,牛琪,许之玮,赵艳(安徽分公司),郑蓓,陈文轩,齐奥 | AP392: 安徽分公司 | AQ392: 12170072 | AR392: 收购处置徽商银行2017年三季度资产包项目 | AS392: 43026 | AU392: 11001 | AV392: 已剔重 | AX392: =COUNTIFS(拍卖数据!E:E,AA392,拍卖数据!F:F,AB392,拍卖数据!O:O,O392,拍卖数据!P:P,">"&X392*0.8,拍卖数据!P:P,"<"&X392*1.2) -> 1 | AY392: =COUNTIFS(拍卖数据!E:E,AA392,拍卖数据!F:F,AB392,拍卖数据!O:O,O392,拍卖数据!AN:AN,"机构",拍卖数据!P:P,">"&X392*0.8,拍卖数据!P:P,"<"&X392*1.2) -> 0 | AZ392: =COUNTIFS(拍卖数据!E:E,AA392,拍卖数据!F:F,AB392,拍卖数据!G:G,AC392,拍卖数据!O:O,O392,拍卖数据!AN:AN,"机构",拍卖数据!P:P,">"&X392*0.8,拍卖数据!P:P,"<"&X392*1.2) -> 0
A393: 13655 | B393: 12230013027100000001 | C393: 否 | D393: 凤阳县龙兴矿业有限公司 | E393: 其他非金属矿物制品制造 | F393: 894.24806 | G393: 1431.6755 | H393: 0 | I393: 0 | J393: 2325.9236 | K393: 抵押,质押,保证 | L393: 凤阳县龙兴玻璃有限公司,孙宗梅,王从兆 | M393: 400 | N393: 土地使用权 | O393: 工业用地 | P393: 工业用地 | Q393: 新建 | R393: 凤阳县龙兴玻璃有限公司 | S393: 91341126MA2N6TAR8D | T393: 01022025091430005 | U393: 凤阳县府城镇山后村凤门路西侧凤国用（2008)第0350号 | V393: 凤他项（2014）第042号 | W393: 2058/1/24 | X393: 81179 | Y393: 平方米 | Z393: 是 | AA393: 安徽省 | AB393: 滁州市 | AC393: 凤阳县 | AD393: 凤阳县府城镇山后村凤门路西侧 | AE393: 第一顺位 | AF393: 2021.36 | AG393: 外部评估 | AH393: 45071 | AI393: 811.79 | AJ393: 否 | AL393: 不涉及 | AM393: 0 | AO393: 张乐群,曹吉峰,董俣顺,许之玮,邹熠峰,郑舒凌 | AP393: 安徽分公司 | AQ393: 12230013 | AR393: 收购徽商银行2023年第2批133户不良资产包项目 | AS393: 45170 | AU393: 11001 | AV393: 已剔重 | AX393: =COUNTIFS(拍卖数据!E:E,AA393,拍卖数据!F:F,AB393,拍卖数据!O:O,O393,拍卖数据!P:P,">"&X393*0.8,拍卖数据!P:P,"<"&X393*1.2) -> 0 | AY393: =COUNTIFS(拍卖数据!E:E,AA393,拍卖数据!F:F,AB393,拍卖数据!O:O,O393,拍卖数据!AN:AN,"机构",拍卖数据!P:P,">"&X393*0.8,拍卖数据!P:P,"<"&X393*1.2) -> 0 | AZ393: =COUNTIFS(拍卖数据!E:E,AA393,拍卖数据!F:F,AB393,拍卖数据!G:G,AC393,拍卖数据!O:O,O393,拍卖数据!AN:AN,"机构",拍卖数据!P:P,">"&X393*0.8,拍卖数据!P:P,"<"&X393*1.2) -> 0
A394: 17939 | B394: 10230145000100000001 | C394: 否 | D394: 南京同曦假日百货有限责任公司 | E394: 零售业 | F394: 12818 | G394: 177.70782 | H394: 0 | I394: 0 | J394: 12995.708 | K394: 抵押,质押,保证 | M394: 8450.5906 | N394: 现房 | O394: 商业用房 | P394: 独立商铺 | Q394: 已入库 | R394: 宣城同曦房地产开发有限公司 | S394: 91341800355190608C | T394: 01012025090582123 | U394: 宣城市宣州区水阳江大道与昭亭南路交叉口东南角黄金时代3幢302 | V394: 无 | W394: 0000/00/00 | X394: 205.09 | Y394: 平方米 | Z394: 是 | AA394: 安徽省 | AB394: 宣城市 | AC394: 宣州区 | AD394: 宣城市宣州区水阳江大道与昭亭南路交叉口东南角黄金时代3幢302 | AE394: 第一顺位 | AF394: 188 | AG394: 外部评估 | AH394: 45117 | AI394: 194.8355 | AJ394: 否 | AL394: 不涉及 | AO394: 丁刘惠,俞恺博,史磊,吴中泽,周玲玲,尹苗,柏开杰 | AP394: 江苏分公司 | AQ394: 10230145 | AR394: 商业化收购恒丰银行对南京同曦假日百货有限责任公司等3户不良债权资产包项目 | AS394: 45274 | AU394: 11001 | AV394: 已剔重 | AX394: =COUNTIFS(拍卖数据!E:E,AA394,拍卖数据!F:F,AB394,拍卖数据!O:O,O394,拍卖数据!P:P,">"&X394*0.8,拍卖数据!P:P,"<"&X394*1.2) -> 9 | AY394: =COUNTIFS(拍卖数据!E:E,AA394,拍卖数据!F:F,AB394,拍卖数据!O:O,O394,拍卖数据!AN:AN,"机构",拍卖数据!P:P,">"&X394*0.8,拍卖数据!P:P,"<"&X394*1.2) -> 0 | AZ394: =COUNTIFS(拍卖数据!E:E,AA394,拍卖数据!F:F,AB394,拍卖数据!G:G,AC394,拍卖数据!O:O,O394,拍卖数据!AN:AN,"机构",拍卖数据!P:P,">"&X394*0.8,拍卖数据!P:P,"<"&X394*1.2) -> 0
A395: 17940 | B395: 10230145000100000001 | C395: 否 | D395: 南京同曦假日百货有限责任公司 | E395: 零售业 | F395: 12818 | G395: 177.70782 | H395: 0 | I395: 0 | J395: 12995.708 | K395: 抵押,质押,保证 | M395: 8450.5906 | N395: 现房 | O395: 商业用房 | P395: 独立商铺 | Q395: 已入库 | R395: 宣城同曦房地产开发有限公司 | S395: 91341800355190608C | T395: 01012025090582122 | U395: 宣城市宣州区水阳江大道与昭亭南路交叉口东南角黄金时代2幢302 | V395: 无 | W395: 0000/00/00 | X395: 232.58 | Y395: 平方米 | Z395: 是 | AA395: 安徽省 | AB395: 宣城市 | AC395: 宣州区 | AD395: 宣城市宣州区水阳江大道与昭亭南路交叉口东南角黄金时代2幢302 | AE395: 第一顺位 | AF395: 188 | AG395: 外部评估 | AH395: 45117 | AI395: 220.951 | AJ395: 否 | AL395: 不涉及 | AO395: 丁刘惠,俞恺博,史磊,吴中泽,周玲玲,尹苗,柏开杰 | AP395: 江苏分公司 | AQ395: 10230145 | AR395: 商业化收购恒丰银行对南京同曦假日百货有限责任公司等3户不良债权资产包项目 | AS395: 45274 | AU395: 11001 | AV395: 已剔重 | AX395: =COUNTIFS(拍卖数据!E:E,AA395,拍卖数据!F:F,AB395,拍卖数据!O:O,O395,拍卖数据!P:P,">"&X395*0.8,拍卖数据!P:P,"<"&X395*1.2) -> 12 | AY395: =COUNTIFS(拍卖数据!E:E,AA395,拍卖数据!F:F,AB395,拍卖数据!O:O,O395,拍卖数据!AN:AN,"机构",拍卖数据!P:P,">"&X395*0.8,拍卖数据!P:P,"<"&X395*1.2) -> 0 | AZ395: =COUNTIFS(拍卖数据!E:E,AA395,拍卖数据!F:F,AB395,拍卖数据!G:G,AC395,拍卖数据!O:O,O395,拍卖数据!AN:AN,"机构",拍卖数据!P:P,">"&X395*0.8,拍卖数据!P:P,"<"&X395*1.2) -> 0
A396: 18218 | B396: 10190260000700000001 | C396: 否 | D396: 南京航油实业有限公司 | E396: 零售业 | F396: 10500 | G396: 1989.0373 | H396: 0 | I396: 86.7447 | J396: 12489.037 | K396: 抵押,质押,保证 | M396: 7345.6343 | N396: 股权 | O396: 非上市公司股权 | P396: 非上市公司股权 | Q396: 已入库 | R396: 梁金达 | S396: 342301197007060212 | T396: 05052025082720042 | U396: 滁州金达公司5280万元出资对应的股权 | V396: （2014）第032号 | W396: 0000/00/00 | X396: 44 | Y396: ％ | Z396: 是 | AA396: 安徽省 | AB396: 滁州市 | AC396: 南谯区 | AD396: 安徽省滁州市凤阳路677号 | AE396: 第一顺位 | AF396: 5280 | AG396: 内部测算 | AH396: 37590 | AI396: 5280 | AJ396: 否 | AL396: 不涉及 | AO396: 卢端,周若玮,宋灿可,杨琨(江苏分公司),谢宏娟,陈姗,陈怀明 | AP396: 江苏分公司 | AQ396: 10190260 | AR396: 商业化收购民生银行南京分行对江苏金翔石油化工有限公司等7户不良债权资产包 | AS396: 43823 | AU396: 11001 | AV396: 已剔重 | AX396: =COUNTIFS(拍卖数据!E:E,AA396,拍卖数据!F:F,AB396,拍卖数据!O:O,O396,拍卖数据!P:P,">"&X396*0.8,拍卖数据!P:P,"<"&X396*1.2) -> 0 | AY396: =COUNTIFS(拍卖数据!E:E,AA396,拍卖数据!F:F,AB396,拍卖数据!O:O,O396,拍卖数据!AN:AN,"机构",拍卖数据!P:P,">"&X396*0.8,拍卖数据!P:P,"<"&X396*1.2) -> 0 | AZ396: =COUNTIFS(拍卖数据!E:E,AA396,拍卖数据!F:F,AB396,拍卖数据!G:G,AC396,拍卖数据!O:O,O396,拍卖数据!AN:AN,"机构",拍卖数据!P:P,">"&X396*0.8,拍卖数据!P:P,"<"&X396*1.2) -> 0
A397: 18374 | B397: 10190220000500000001 | C397: 否 | D397: 南京雨润食品有限公司 | E397: 速冻食品制造 | F397: 30000 | G397: 6012.3909 | H397: 0 | I397: 0 | J397: 36012.391 | K397: 抵押,质押,保证 | M397: 18835.966 | N397: 现房 | O397: 工业用房 | P397: 非标准工业厂房及仓储 | Q397: 已入库 | R397: 定远县福润肉类加工有限公司 | S397: 91341125695731650E | T397: 01012025090588698 | U397: 安徽省滁州市定远县定城经济开发区泉坞山路168号 | V397: 皖（2015）定远县不动产证明第0002075号 | W397: 0000/00/00 | X397: 464.52 | Y397: 平方米 | Z397: 是 | AA397: 安徽省 | AB397: 滁州市 | AC397: 定远县 | AD397: 安徽省滁州市定远县定城经济开发区泉坞山路168号 | AE397: 第一顺位 | AF397: 116.13 | AG397: 外部评估 | AH397: 44705 | AI397: 44 | AJ397: 否 | AL397: 不涉及 | AO397: 卢端,周若玮,宋灿可,李静(江苏分公司),杜旭东,王含西,王楷文,谢宏娟,陈姗,陈怀明 | AP397: 江苏分公司 | AQ397: 10190220 | AR397: 商业化收购中信银行南京分行对江苏雨润肉类产业集团有限公司等7户不良债权资产包项目 | AS397: 43822 | AU397: 11001 | AV397: 已剔重 | AX397: =COUNTIFS(拍卖数据!E:E,AA397,拍卖数据!F:F,AB397,拍卖数据!O:O,O397,拍卖数据!P:P,">"&X397*0.8,拍卖数据!P:P,"<"&X397*1.2) -> 0 | AY397: =COUNTIFS(拍卖数据!E:E,AA397,拍卖数据!F:F,AB397,拍卖数据!O:O,O397,拍卖数据!AN:AN,"机构",拍卖数据!P:P,">"&X397*0.8,拍卖数据!P:P,"<"&X397*1.2) -> 0 | AZ397: =COUNTIFS(拍卖数据!E:E,AA397,拍卖数据!F:F,AB397,拍卖数据!G:G,AC397,拍卖数据!O:O,O397,拍卖数据!AN:AN,"机构",拍卖数据!P:P,">"&X397*0.8,拍卖数据!P:P,"<"&X397*1.2) -> 0
A398: 18375 | B398: 10190220000500000001 | C398: 否 | D398: 南京雨润食品有限公司 | E398: 速冻食品制造 | F398: 30000 | G398: 6012.3909 | H398: 0 | I398: 0 | J398: 36012.391 | K398: 抵押,质押,保证 | M398: 18835.966 | N398: 现房 | O398: 工业用房 | P398: 非标准工业厂房及仓储 | Q398: 已入库 | R398: 定远县福润肉类加工有限公司 | S398: 91341125695731650E | T398: 01012025090588697 | U398: 安徽省滁州市定远县定城经济开发区泉坞山路168号 | V398: 皖（2015）定远县不动产证明第0002071号 | W398: 0000/00/00 | X398: 3451.51 | Y398: 平方米 | Z398: 是 | AA398: 安徽省 | AB398: 滁州市 | AC398: 定远县 | AD398: 安徽省滁州市定远县定城经济开发区泉坞山路168号 | AE398: 第一顺位 | AF398: 862.8775 | AG398: 外部评估 | AH398: 44705 | AI398: 376 | AJ398: 否 | AL398: 不涉及 | AO398: 卢端,周若玮,宋灿可,李静(江苏分公司),杜旭东,王含西,王楷文,谢宏娟,陈姗,陈怀明 | AP398: 江苏分公司 | AQ398: 10190220 | AR398: 商业化收购中信银行南京分行对江苏雨润肉类产业集团有限公司等7户不良债权资产包项目 | AS398: 43822 | AU398: 11001 | AV398: 已剔重 | AX398: =COUNTIFS(拍卖数据!E:E,AA398,拍卖数据!F:F,AB398,拍卖数据!O:O,O398,拍卖数据!P:P,">"&X398*0.8,拍卖数据!P:P,"<"&X398*1.2) -> 0 | AY398: =COUNTIFS(拍卖数据!E:E,AA398,拍卖数据!F:F,AB398,拍卖数据!O:O,O398,拍卖数据!AN:AN,"机构",拍卖数据!P:P,">"&X398*0.8,拍卖数据!P:P,"<"&X398*1.2) -> 0 | AZ398: =COUNTIFS(拍卖数据!E:E,AA398,拍卖数据!F:F,AB398,拍卖数据!G:G,AC398,拍卖数据!O:O,O398,拍卖数据!AN:AN,"机构",拍卖数据!P:P,">"&X398*0.8,拍卖数据!P:P,"<"&X398*1.2) -> 0
A399: 18376 | B399: 10190220000500000001 | C399: 否 | D399: 南京雨润食品有限公司 | E399: 速冻食品制造 | F399: 30000 | G399: 6012.3909 | H399: 0 | I399: 0 | J399: 36012.391 | K399: 抵押,质押,保证 | M399: 18835.966 | N399: 现房 | O399: 工业用房 | P399: 非标准工业厂房及仓储 | Q399: 已入库 | R399: 定远县福润肉类加工有限公司 | S399: 91341125695731650E | T399: 01012025090588696 | U399: 安徽省滁州市定远县定城经济开发区泉坞山路168号 | V399: 皖（2015）定远县不动产证明第0002077号 | W399: 0000/00/00 | X399: 84.58 | Y399: 平方米 | Z399: 是 | AA399: 安徽省 | AB399: 滁州市 | AC399: 定远县 | AD399: 安徽省滁州市定远县定城经济开发区泉坞山路168号 | AE399: 第一顺位 | AF399: 21.145 | AG399: 外部评估 | AH399: 44705 | AI399: 8 | AJ399: 否 | AL399: 不涉及 | AO399: 卢端,周若玮,宋灿可,李静(江苏分公司),杜旭东,王含西,王楷文,谢宏娟,陈姗,陈怀明 | AP399: 江苏分公司 | AQ399: 10190220 | AR399: 商业化收购中信银行南京分行对江苏雨润肉类产业集团有限公司等7户不良债权资产包项目 | AS399: 43822 | AU399: 11001 | AV399: 已剔重 | AX399: =COUNTIFS(拍卖数据!E:E,AA399,拍卖数据!F:F,AB399,拍卖数据!O:O,O399,拍卖数据!P:P,">"&X399*0.8,拍卖数据!P:P,"<"&X399*1.2) -> 0 | AY399: =COUNTIFS(拍卖数据!E:E,AA399,拍卖数据!F:F,AB399,拍卖数据!O:O,O399,拍卖数据!AN:AN,"机构",拍卖数据!P:P,">"&X399*0.8,拍卖数据!P:P,"<"&X399*1.2) -> 0 | AZ399: =COUNTIFS(拍卖数据!E:E,AA399,拍卖数据!F:F,AB399,拍卖数据!G:G,AC399,拍卖数据!O:O,O399,拍卖数据!AN:AN,"机构",拍卖数据!P:P,">"&X399*0.8,拍卖数据!P:P,"<"&X399*1.2) -> 0
A400: 18377 | B400: 10190220000500000001 | C400: 否 | D400: 南京雨润食品有限公司 | E400: 速冻食品制造 | F400: 30000 | G400: 6012.3909 | H400: 0 | I400: 0 | J400: 36012.391 | K400: 抵押,质押,保证 | M400: 18835.966 | N400: 现房 | O400: 工业用房 | P400: 非标准工业厂房及仓储 | Q400: 已入库 | R400: 定远县福润肉类加工有限公司 | S400: 91341125695731650E | T400: 01012025090588695 | U400: 安徽省滁州市定远县定城经济开发区泉坞山路168号 | V400: 皖（2015）定远县不动产证明第0002072号 | W400: 0000/00/00 | X400: 689.46 | Y400: 平方米 | Z400: 是 | AA400: 安徽省 | AB400: 滁州市 | AC400: 定远县 | AD400: 安徽省滁州市定远县定城经济开发区泉坞山路168号 | AE400: 第一顺位 | AF400: 172.365 | AG400: 外部评估 | AH400: 44705 | AI400: 66 | AJ400: 否 | AL400: 不涉及 | AO400: 卢端,周若玮,宋灿可,李静(江苏分公司),杜旭东,王含西,王楷文,谢宏娟,陈姗,陈怀明 | AP400: 江苏分公司 | AQ400: 10190220 | AR400: 商业化收购中信银行南京分行对江苏雨润肉类产业集团有限公司等7户不良债权资产包项目 | AS400: 43822 | AU400: 11001 | AV400: 已剔重 | AX400: =COUNTIFS(拍卖数据!E:E,AA400,拍卖数据!F:F,AB400,拍卖数据!O:O,O400,拍卖数据!P:P,">"&X400*0.8,拍卖数据!P:P,"<"&X400*1.2) -> 1 | AY400: =COUNTIFS(拍卖数据!E:E,AA400,拍卖数据!F:F,AB400,拍卖数据!O:O,O400,拍卖数据!AN:AN,"机构",拍卖数据!P:P,">"&X400*0.8,拍卖数据!P:P,"<"&X400*1.2) -> 0 | AZ400: =COUNTIFS(拍卖数据!E:E,AA400,拍卖数据!F:F,AB400,拍卖数据!G:G,AC400,拍卖数据!O:O,O400,拍卖数据!AN:AN,"机构",拍卖数据!P:P,">"&X400*0.8,拍卖数据!P:P,"<"&X400*1.2) -> 0
A401: 18378 | B401: 10190220000500000001 | C401: 否 | D401: 南京雨润食品有限公司 | E401: 速冻食品制造 | F401: 30000 | G401: 6012.3909 | H401: 0 | I401: 0 | J401: 36012.391 | K401: 抵押,质押,保证 | M401: 18835.966 | N401: 现房 | O401: 工业用房 | P401: 非标准工业厂房及仓储 | Q401: 已入库 | R401: 定远县福润肉类加工有限公司 | S401: 91341125695731650E | T401: 01012025090588694 | U401: 安徽省滁州市定远县定城经济开发区泉坞山路168号 | V401: 皖（2015）定远县不动产证明第0002076号 | W401: 0000/00/00 | X401: 2827.98 | Y401: 平方米 | Z401: 是 | AA401: 安徽省 | AB401: 滁州市 | AC401: 定远县 | AD401: 安徽省滁州市定远县定城经济开发区泉坞山路168号 | AE401: 第一顺位 | AF401: 718.245 | AG401: 外部评估 | AH401: 44705 | AI401: 313 | AJ401: 否 | AL401: 不涉及 | AO401: 卢端,周若玮,宋灿可,李静(江苏分公司),杜旭东,王含西,王楷文,谢宏娟,陈姗,陈怀明 | AP401: 江苏分公司 | AQ401: 10190220 | AR401: 商业化收购中信银行南京分行对江苏雨润肉类产业集团有限公司等7户不良债权资产包项目 | AS401: 43822 | AU401: 11001 | AV401: 已剔重 | AX401: =COUNTIFS(拍卖数据!E:E,AA401,拍卖数据!F:F,AB401,拍卖数据!O:O,O401,拍卖数据!P:P,">"&X401*0.8,拍卖数据!P:P,"<"&X401*1.2) -> 1 | AY401: =COUNTIFS(拍卖数据!E:E,AA401,拍卖数据!F:F,AB401,拍卖数据!O:O,O401,拍卖数据!AN:AN,"机构",拍卖数据!P:P,">"&X401*0.8,拍卖数据!P:P,"<"&X401*1.2) -> 1 | AZ401: =COUNTIFS(拍卖数据!E:E,AA401,拍卖数据!F:F,AB401,拍卖数据!G:G,AC401,拍卖数据!O:O,O401,拍卖数据!AN:AN,"机构",拍卖数据!P:P,">"&X401*0.8,拍卖数据!P:P,"<"&X401*1.2) -> 0
A402: 18379 | B402: 10190220000500000001 | C402: 否 | D402: 南京雨润食品有限公司 | E402: 速冻食品制造 | F402: 30000 | G402: 6012.3909 | H402: 0 | I402: 0 | J402: 36012.391 | K402: 抵押,质押,保证 | M402: 18835.966 | N402: 现房 | O402: 工业用房 | P402: 非标准工业厂房及仓储 | Q402: 已入库 | R402: 定远县福润肉类加工有限公司 | S402: 91341125695731650E | T402: 01012025090588693 | U402: 安徽省滁州市定远县定城经济开发区泉坞山路168号 | V402: 皖（2015）定远县不动产证明第0002073号 | W402: 0000/00/00 | X402: 9234 | Y402: 平方米 | Z402: 是 | AA402: 安徽省 | AB402: 滁州市 | AC402: 定远县 | AD402: 安徽省滁州市定远县定城经济开发区泉坞山路168号 | AE402: 第一顺位 | AF402: 2308.5 | AG402: 外部评估 | AH402: 44705 | AI402: 1005 | AJ402: 否 | AL402: 不涉及 | AO402: 卢端,周若玮,宋灿可,李静(江苏分公司),杜旭东,王含西,王楷文,谢宏娟,陈姗,陈怀明 | AP402: 江苏分公司 | AQ402: 10190220 | AR402: 商业化收购中信银行南京分行对江苏雨润肉类产业集团有限公司等7户不良债权资产包项目 | AS402: 43822 | AU402: 11001 | AV402: 已剔重 | AX402: =COUNTIFS(拍卖数据!E:E,AA402,拍卖数据!F:F,AB402,拍卖数据!O:O,O402,拍卖数据!P:P,">"&X402*0.8,拍卖数据!P:P,"<"&X402*1.2) -> 2 | AY402: =COUNTIFS(拍卖数据!E:E,AA402,拍卖数据!F:F,AB402,拍卖数据!O:O,O402,拍卖数据!AN:AN,"机构",拍卖数据!P:P,">"&X402*0.8,拍卖数据!P:P,"<"&X402*1.2) -> 2 | AZ402: =COUNTIFS(拍卖数据!E:E,AA402,拍卖数据!F:F,AB402,拍卖数据!G:G,AC402,拍卖数据!O:O,O402,拍卖数据!AN:AN,"机构",拍卖数据!P:P,">"&X402*0.8,拍卖数据!P:P,"<"&X402*1.2) -> 0
A403: 18380 | B403: 10190220000500000001 | C403: 否 | D403: 南京雨润食品有限公司 | E403: 速冻食品制造 | F403: 30000 | G403: 6012.3909 | H403: 0 | I403: 0 | J403: 36012.391 | K403: 抵押,质押,保证 | M403: 18835.966 | N403: 现房 | O403: 工业用房 | P403: 非标准工业厂房及仓储 | Q403: 已入库 | R403: 定远县福润肉类加工有限公司 | S403: 91341125695731650E | T403: 01012025090588692 | U403: 安徽省滁州市定远县定城经济开发区泉坞山路168号 | V403: 皖（2015）定远县不动产证明第0002070号 | W403: 0000/00/00 | X403: 463.16 | Y403: 平方米 | Z403: 是 | AA403: 安徽省 | AB403: 滁州市 | AC403: 定远县 | AD403: 安徽省滁州市定远县定城经济开发区泉坞山路168号 | AE403: 第一顺位 | AF403: 115.79 | AG403: 外部评估 | AH403: 44705 | AI403: 44 | AJ403: 否 | AL403: 不涉及 | AO403: 卢端,周若玮,宋灿可,李静(江苏分公司),杜旭东,王含西,王楷文,谢宏娟,陈姗,陈怀明 | AP403: 江苏分公司 | AQ403: 10190220 | AR403: 商业化收购中信银行南京分行对江苏雨润肉类产业集团有限公司等7户不良债权资产包项目 | AS403: 43822 | AU403: 11001 | AV403: 已剔重 | AX403: =COUNTIFS(拍卖数据!E:E,AA403,拍卖数据!F:F,AB403,拍卖数据!O:O,O403,拍卖数据!P:P,">"&X403*0.8,拍卖数据!P:P,"<"&X403*1.2) -> 0 | AY403: =COUNTIFS(拍卖数据!E:E,AA403,拍卖数据!F:F,AB403,拍卖数据!O:O,O403,拍卖数据!AN:AN,"机构",拍卖数据!P:P,">"&X403*0.8,拍卖数据!P:P,"<"&X403*1.2) -> 0 | AZ403: =COUNTIFS(拍卖数据!E:E,AA403,拍卖数据!F:F,AB403,拍卖数据!G:G,AC403,拍卖数据!O:O,O403,拍卖数据!AN:AN,"机构",拍卖数据!P:P,">"&X403*0.8,拍卖数据!P:P,"<"&X403*1.2) -> 0
A404: 18381 | B404: 10190220000500000001 | C404: 否 | D404: 南京雨润食品有限公司 | E404: 速冻食品制造 | F404: 30000 | G404: 6012.3909 | H404: 0 | I404: 0 | J404: 36012.391 | K404: 抵押,质押,保证 | M404: 18835.966 | N404: 现房 | O404: 工业用房 | P404: 非标准工业厂房及仓储 | Q404: 已入库 | R404: 定远县福润肉类加工有限公司 | S404: 91341125695731650E | T404: 01012025090588691 | U404: 安徽省滁州市定远县定城经济开发区泉坞山路168号 | V404: 皖（2015）定远县不动产证明第0002078号 | W404: 0000/00/00 | X404: 187.33 | Y404: 平方米 | Z404: 是 | AA404: 安徽省 | AB404: 滁州市 | AC404: 定远县 | AD404: 安徽省滁州市定远县定城经济开发区泉坞山路168号 | AE404: 第一顺位 | AF404: 46.8325 | AG404: 外部评估 | AH404: 44705 | AI404: 18 | AJ404: 否 | AL404: 不涉及 | AO404: 卢端,周若玮,宋灿可,李静(江苏分公司),杜旭东,王含西,王楷文,谢宏娟,陈姗,陈怀明 | AP404: 江苏分公司 | AQ404: 10190220 | AR404: 商业化收购中信银行南京分行对江苏雨润肉类产业集团有限公司等7户不良债权资产包项目 | AS404: 43822 | AU404: 11001 | AV404: 已剔重 | AX404: =COUNTIFS(拍卖数据!E:E,AA404,拍卖数据!F:F,AB404,拍卖数据!O:O,O404,拍卖数据!P:P,">"&X404*0.8,拍卖数据!P:P,"<"&X404*1.2) -> 0 | AY404: =COUNTIFS(拍卖数据!E:E,AA404,拍卖数据!F:F,AB404,拍卖数据!O:O,O404,拍卖数据!AN:AN,"机构",拍卖数据!P:P,">"&X404*0.8,拍卖数据!P:P,"<"&X404*1.2) -> 0 | AZ404: =COUNTIFS(拍卖数据!E:E,AA404,拍卖数据!F:F,AB404,拍卖数据!G:G,AC404,拍卖数据!O:O,O404,拍卖数据!AN:AN,"机构",拍卖数据!P:P,">"&X404*0.8,拍卖数据!P:P,"<"&X404*1.2) -> 0
A405: 18382 | B405: 10190220000500000001 | C405: 否 | D405: 南京雨润食品有限公司 | E405: 速冻食品制造 | F405: 30000 | G405: 6012.3909 | H405: 0 | I405: 0 | J405: 36012.391 | K405: 抵押,质押,保证 | M405: 18835.966 | N405: 现房 | O405: 工业用房 | P405: 非标准工业厂房及仓储 | Q405: 已入库 | R405: 定远县福润肉类加工有限公司 | S405: 91341125695731650E | T405: 01012025090588690 | U405: 安徽省滁州市定远县定城经济开发区泉坞山路168号 | V405: 皖（2015）定远县不动产证明第0002074号 | W405: 0000/00/00 | X405: 632.42 | Y405: 平方米 | Z405: 是 | AA405: 安徽省 | AB405: 滁州市 | AC405: 定远县 | AD405: 安徽省滁州市定远县定城经济开发区泉坞山路168号 | AE405: 第一顺位 | AF405: 158.105 | AG405: 外部评估 | AH405: 44705 | AI405: 60 | AJ405: 否 | AL405: 不涉及 | AO405: 卢端,周若玮,宋灿可,李静(江苏分公司),杜旭东,王含西,王楷文,谢宏娟,陈姗,陈怀明 | AP405: 江苏分公司 | AQ405: 10190220 | AR405: 商业化收购中信银行南京分行对江苏雨润肉类产业集团有限公司等7户不良债权资产包项目 | AS405: 43822 | AU405: 11001 | AV405: 已剔重 | AX405: =COUNTIFS(拍卖数据!E:E,AA405,拍卖数据!F:F,AB405,拍卖数据!O:O,O405,拍卖数据!P:P,">"&X405*0.8,拍卖数据!P:P,"<"&X405*1.2) -> 1 | AY405: =COUNTIFS(拍卖数据!E:E,AA405,拍卖数据!F:F,AB405,拍卖数据!O:O,O405,拍卖数据!AN:AN,"机构",拍卖数据!P:P,">"&X405*0.8,拍卖数据!P:P,"<"&X405*1.2) -> 0 | AZ405: =COUNTIFS(拍卖数据!E:E,AA405,拍卖数据!F:F,AB405,拍卖数据!G:G,AC405,拍卖数据!O:O,O405,拍卖数据!AN:AN,"机构",拍卖数据!P:P,">"&X405*0.8,拍卖数据!P:P,"<"&X405*1.2) -> 0
A406: 22224 | B406: 12253002010015 | C406: 否 | D406: 合肥令辉物流有限公司 | E406: 交通运输、仓储和邮政业 | F406: 41.7 | G406: 0.606983 | H406: 0 | J406: 42.306983 | K406: 抵押,保证 | L406: 孔令辉,薛飞 | M406: 0 | N406: 现房 | O406: 居住用房 | P406: 普通商品住房 | Q406: 已入库 | R406: 薛飞 | S406: 340123197811045078 | T406: 01012025062630017 | U406: 合肥市肥东县撮镇镇唐安社区和平路北侧东方早城15幢704室 | V406: 皖 (2023)肥东县不动产证明第0108805号 | W406: 2086/5/24 | X406: 93.3 | Y406: 平方米 | Z406: 是 | AA406: 安徽省 | AB406: 合肥市 | AC406: 肥东县 | AD406: 合肥市肥东县撮镇镇唐安社区和平路北侧东方早城15幢704室 | AE406: 第二顺位 | AF406: 64 | AG406: 内部测算 | AH406: 45803 | AI406: 0 | AJ406: 是 | AK406: A02.押品非第一顺位抵质押 | AL406: 不涉及 | AM406: 0 | AO406: 张乐群,郑舒凌,陈文轩 | AP406: 安徽分公司 | AQ406: 12253002 | AR406: 收购浙商银行2025年第二季度总对总不良资产包项目 | AS406: 45838 | AU406: 11002 | AV406: 已剔重 | AX406: =COUNTIFS(拍卖数据!E:E,AA406,拍卖数据!F:F,AB406,拍卖数据!O:O,O406,拍卖数据!P:P,">"&X406*0.8,拍卖数据!P:P,"<"&X406*1.2) -> 331 | AY406: =COUNTIFS(拍卖数据!E:E,AA406,拍卖数据!F:F,AB406,拍卖数据!O:O,O406,拍卖数据!AN:AN,"机构",拍卖数据!P:P,">"&X406*0.8,拍卖数据!P:P,"<"&X406*1.2) -> 1 | AZ406: =COUNTIFS(拍卖数据!E:E,AA406,拍卖数据!F:F,AB406,拍卖数据!G:G,AC406,拍卖数据!O:O,O406,拍卖数据!AN:AN,"机构",拍卖数据!P:P,">"&X406*0.8,拍卖数据!P:P,"<"&X406*1.2) -> 0
A407: 22226 | B407: 12253002010010 | C407: 否 | D407: 合肥市包河区市会巷火锅店 | E407: 租赁和商务服务业 | F407: 17 | G407: 0.422394 | H407: 0 | J407: 17.422394 | K407: 抵押,保证 | L407: 周成 | M407: 0 | N407: 现房 | O407: 居住用房 | P407: 普通商品住房 | Q407: 已入库 | R407: 周成 | S407: 440582198602285577 | T407: 01012025062630010 | U407: 合肥市安徽省合肥市包河区繁华大道6525号格林雅地小区B幢1304 | V407: 皖（2023）合 肥 市 不 动 产 证明第 5022071 号 | W407: 2076-12-28 | X407: 45.85 | Y407: 平方米 | Z407: 是 | AA407: 安徽省 | AB407: 合肥市 | AC407: 包河区 | AD407: 合肥市安徽省合肥市包河区繁华大道6525号格林雅地小区B幢1304 | AE407: 第二顺位 | AF407: 29.8 | AG407: 内部测算 | AH407: 45803 | AI407: 0 | AJ407: 是 | AK407: A02.押品非第一顺位抵质押 | AL407: 不涉及 | AM407: 0 | AO407: 张乐群,郑舒凌,陈文轩 | AP407: 安徽分公司 | AQ407: 12253002 | AR407: 收购浙商银行2025年第二季度总对总不良资产包项目 | AS407: 45838 | AU407: 11002 | AV407: 已剔重 | AX407: =COUNTIFS(拍卖数据!E:E,AA407,拍卖数据!F:F,AB407,拍卖数据!O:O,O407,拍卖数据!P:P,">"&X407*0.8,拍卖数据!P:P,"<"&X407*1.2) -> 30 | AY407: =COUNTIFS(拍卖数据!E:E,AA407,拍卖数据!F:F,AB407,拍卖数据!O:O,O407,拍卖数据!AN:AN,"机构",拍卖数据!P:P,">"&X407*0.8,拍卖数据!P:P,"<"&X407*1.2) -> 0 | AZ407: =COUNTIFS(拍卖数据!E:E,AA407,拍卖数据!F:F,AB407,拍卖数据!G:G,AC407,拍卖数据!O:O,O407,拍卖数据!AN:AN,"机构",拍卖数据!P:P,">"&X407*0.8,拍卖数据!P:P,"<"&X407*1.2) -> 0
A408: 22227 | B408: 12253002010013 | C408: 否 | D408: 合肥市包河区芭甯建材经营部 | E408: 批发和零售业 | F408: 99.999716 | G408: 1.523878 | H408: 0 | J408: 101.52359 | K408: 抵押,保证 | L408: 许文,黄兰 | M408: 0 | N408: 现房 | O408: 居住用房 | P408: 普通商品住房 | Q408: 已入库 | R408: 许文，黄兰 | S408: 340123198806283930；340123198803042867 | T408: 01012025062630014 | U408: 合肥市滨湖区贵阳路655号湖滨荣府13幢1706 | V408: 皖 (2024)合肥市不动产证明第1015520号 | W408: 2088-11-15 | X408: 122.55 | Y408: 平方米 | Z408: 是 | AA408: 安徽省 | AB408: 合肥市 | AC408: 包河区 | AD408: 合肥市滨湖区贵阳路655号湖滨荣府13幢1706 | AE408: 第二顺位 | AF408: 149 | AG408: 内部测算 | AH408: 45803 | AI408: 0 | AJ408: 是 | AK408: A02.押品非第一顺位抵质押 | AL408: 不涉及 | AM408: 0 | AO408: 张乐群,郑舒凌,陈文轩 | AP408: 安徽分公司 | AQ408: 12253002 | AR408: 收购浙商银行2025年第二季度总对总不良资产包项目 | AS408: 45838 | AU408: 11002 | AV408: 已剔重 | AX408: =COUNTIFS(拍卖数据!E:E,AA408,拍卖数据!F:F,AB408,拍卖数据!O:O,O408,拍卖数据!P:P,">"&X408*0.8,拍卖数据!P:P,"<"&X408*1.2) -> 365 | AY408: =COUNTIFS(拍卖数据!E:E,AA408,拍卖数据!F:F,AB408,拍卖数据!O:O,O408,拍卖数据!AN:AN,"机构",拍卖数据!P:P,">"&X408*0.8,拍卖数据!P:P,"<"&X408*1.2) -> 1 | AZ408: =COUNTIFS(拍卖数据!E:E,AA408,拍卖数据!F:F,AB408,拍卖数据!G:G,AC408,拍卖数据!O:O,O408,拍卖数据!AN:AN,"机构",拍卖数据!P:P,">"&X408*0.8,拍卖数据!P:P,"<"&X408*1.2) -> 1
A409: 22228 | B409: 12253002010011 | C409: 否 | D409: 合肥市瑶海区老张生鲜店 | E409: 租赁和商务服务业 | F409: 61 | G409: 2.204007 | H409: 0 | J409: 63.204007 | K409: 抵押,保证 | L409: 张立水,蔡萍 | M409: 0 | N409: 现房 | O409: 居住用房 | P409: 普通商品住房 | Q409: 已入库 | R409: 张立水 | S409: 340123196811255812 | T409: 01012025062630011 | U409: 合肥市瑶海区临泉东路北侧静安新天地13幢405室 | V409: 皖（2024合肥市不动产证明第2010422 号（新证） | W409: 2071-01-18 | X409: 82.22 | Y409: 平方米 | Z409: 是 | AA409: 安徽省 | AB409: 合肥市 | AC409: 瑶海区 | AD409: 合肥市瑶海区临泉东路北侧静安新天地13幢405室 | AE409: 第二顺位 | AF409: 78 | AG409: 内部测算 | AH409: 45803 | AI409: 0 | AJ409: 是 | AK409: A02.押品非第一顺位抵质押 | AL409: 不涉及 | AM409: 0 | AO409: 张乐群,郑舒凌,陈文轩 | AP409: 安徽分公司 | AQ409: 12253002 | AR409: 收购浙商银行2025年第二季度总对总不良资产包项目 | AS409: 45838 | AU409: 11002 | AV409: 已剔重 | AX409: =COUNTIFS(拍卖数据!E:E,AA409,拍卖数据!F:F,AB409,拍卖数据!O:O,O409,拍卖数据!P:P,">"&X409*0.8,拍卖数据!P:P,"<"&X409*1.2) -> 264 | AY409: =COUNTIFS(拍卖数据!E:E,AA409,拍卖数据!F:F,AB409,拍卖数据!O:O,O409,拍卖数据!AN:AN,"机构",拍卖数据!P:P,">"&X409*0.8,拍卖数据!P:P,"<"&X409*1.2) -> 0 | AZ409: =COUNTIFS(拍卖数据!E:E,AA409,拍卖数据!F:F,AB409,拍卖数据!G:G,AC409,拍卖数据!O:O,O409,拍卖数据!AN:AN,"机构",拍卖数据!P:P,">"&X409*0.8,拍卖数据!P:P,"<"&X409*1.2) -> 0
A410: 22229 | B410: 12253002010014 | C410: 否 | D410: 合肥市蜀山区洱橙蔬菜经营部（个体工商户） | E410: 批发和零售业 | F410: 200 | G410: 4.241762 | H410: 0 | J410: 204.24176 | K410: 抵押,保证 | L410: 杨军,毛红雨 | M410: 0 | N410: 现房 | O410: 居住用房 | P410: 普通商品住房 | Q410: 已入库 | R410: 杨军 | S410: 340102196811282034 | T410: 01012025062630015 | U410: 合肥市庐阳区颐和花园·庐阳佳苑4幢502室 | V410: 皖(2023)合肥市不动产证明第4015983号 | W410: 2073-04-14 | X410: 168.59 | Y410: 平方米 | Z410: 是 | AA410: 安徽省 | AB410: 合肥市 | AC410: 庐阳区 | AD410: 合肥市庐阳区颐和花园·庐阳佳苑4幢502室 | AE410: 第一顺位 | AF410: 253 | AG410: 内部测算 | AH410: 45803 | AI410: 0 | AJ410: 否 | AL410: 不涉及 | AM410: 0 | AO410: 张乐群,郑舒凌,陈文轩 | AP410: 安徽分公司 | AQ410: 12253002 | AR410: 收购浙商银行2025年第二季度总对总不良资产包项目 | AS410: 45838 | AU410: 11001 | AV410: 已剔重 | AX410: =COUNTIFS(拍卖数据!E:E,AA410,拍卖数据!F:F,AB410,拍卖数据!O:O,O410,拍卖数据!P:P,">"&X410*0.8,拍卖数据!P:P,"<"&X410*1.2) -> 113 | AY410: =COUNTIFS(拍卖数据!E:E,AA410,拍卖数据!F:F,AB410,拍卖数据!O:O,O410,拍卖数据!AN:AN,"机构",拍卖数据!P:P,">"&X410*0.8,拍卖数据!P:P,"<"&X410*1.2) -> 1 | AZ410: =COUNTIFS(拍卖数据!E:E,AA410,拍卖数据!F:F,AB410,拍卖数据!G:G,AC410,拍卖数据!O:O,O410,拍卖数据!AN:AN,"机构",拍卖数据!P:P,">"&X410*0.8,拍卖数据!P:P,"<"&X410*1.2) -> 0
A411: 22230 | B411: 12230013032900000001 | C411: 否 | D411: 合肥恒康物流有限公司 | E411: 其他仓储业 | F411: 222 | G411: 135.50236 | H411: 0 | I411: 0 | J411: 357.50236 | K411: 抵押,质押,保证 | L411: 合肥卓尔美生态园林有限公司,周先勇,孙康琪,徐袁,谢守聪 | M411: 31 | N411: 现房 | O411: 商业用房 | P411: 集中商业（购物中心，综合体商业等） | Q411: 新建 | R411: 孙康琪 | S411: 340122197704053324 | T411: 01012025091430191 | U411: 撮镇镇合肥裕隆农机大市场A1-1幢110室房地权肥东字第059738号 | V411: 房地产他证肥东字第20049633号 | W411: 2048/1/1 | X411: 73.22 | Y411: 平方米 | Z411: 是 | AA411: 安徽省 | AB411: 合肥市 | AC411: 肥东县 | AD411: 撮镇镇合肥裕隆农机大市场A1-1幢110室 | AE411: 第一顺位 | AF411: 43.87 | AG411: 外部评估 | AH411: 45071 | AI411: 40.27 | AJ411: 否 | AL411: 不涉及 | AO411: 张乐群,曹吉峰,董俣顺,许之玮,邹熠峰,郑舒凌 | AP411: 安徽分公司 | AQ411: 12230013 | AR411: 收购徽商银行2023年第2批133户不良资产包项目 | AS411: 45170 | AU411: 11001 | AV411: 已剔重 | AX411: =COUNTIFS(拍卖数据!E:E,AA411,拍卖数据!F:F,AB411,拍卖数据!O:O,O411,拍卖数据!P:P,">"&X411*0.8,拍卖数据!P:P,"<"&X411*1.2) -> 66 | AY411: =COUNTIFS(拍卖数据!E:E,AA411,拍卖数据!F:F,AB411,拍卖数据!O:O,O411,拍卖数据!AN:AN,"机构",拍卖数据!P:P,">"&X411*0.8,拍卖数据!P:P,"<"&X411*1.2) -> 6 | AZ411: =COUNTIFS(拍卖数据!E:E,AA411,拍卖数据!F:F,AB411,拍卖数据!G:G,AC411,拍卖数据!O:O,O411,拍卖数据!AN:AN,"机构",拍卖数据!P:P,">"&X411*0.8,拍卖数据!P:P,"<"&X411*1.2) -> 0
A412: 22231 | B412: 12253002010018 | C412: 否 | D412: 合肥无题商贸有限公司 | E412: 批发和零售业 | F412: 72 | G412: 1.748451 | H412: 0 | J412: 73.748451 | K412: 抵押,保证 | L412: 丁超琼,王顺生 | M412: 0 | N412: 现房 | O412: 居住用房 | P412: 普通商品住房 | Q412: 已入库 | R412: 王顺生 | S412: 340122199005196915 | T412: 01012025062630020 | U412: 合肥市肥西县上派镇金寨南路与青年北路交口华邦万派城6号楼1105室 | V412: 皖 (2023) 肥西县不动 产证明第0002513号 | W412: 2080-04-04 | X412: 84.43 | Y412: 平方米 | Z412: 是 | AA412: 安徽省 | AB412: 合肥市 | AC412: 肥西县 | AD412: 合肥市肥西县上派镇金寨南路与青年北路交口华邦万派城6号楼1105室 | AE412: 第二顺位 | AF412: 101 | AG412: 内部测算 | AH412: 45803 | AI412: 0 | AJ412: 是 | AK412: A02.押品非第一顺位抵质押 | AL412: 不涉及 | AM412: 0 | AO412: 张乐群,郑舒凌,陈文轩 | AP412: 安徽分公司 | AQ412: 12253002 | AR412: 收购浙商银行2025年第二季度总对总不良资产包项目 | AS412: 45838 | AU412: 11002 | AV412: 已剔重 | AX412: =COUNTIFS(拍卖数据!E:E,AA412,拍卖数据!F:F,AB412,拍卖数据!O:O,O412,拍卖数据!P:P,">"&X412*0.8,拍卖数据!P:P,"<"&X412*1.2) -> 283 | AY412: =COUNTIFS(拍卖数据!E:E,AA412,拍卖数据!F:F,AB412,拍卖数据!O:O,O412,拍卖数据!AN:AN,"机构",拍卖数据!P:P,">"&X412*0.8,拍卖数据!P:P,"<"&X412*1.2) -> 1 | AZ412: =COUNTIFS(拍卖数据!E:E,AA412,拍卖数据!F:F,AB412,拍卖数据!G:G,AC412,拍卖数据!O:O,O412,拍卖数据!AN:AN,"机构",拍卖数据!P:P,">"&X412*0.8,拍卖数据!P:P,"<"&X412*1.2) -> 0
A413: 22232 | B413: 12230013032500000001 | C413: 否 | D413: 合肥海贝特科贸有限公司 | E413: 其他文化用品批发 | F413: 777.16123 | G413: 762.27406 | H413: 0 | I413: 0 | J413: 1539.4353 | K413: 抵押,质押,保证 | L413: 汪昌其,汪涧明 | M413: 260 | N413: 现房 | O413: 商业用房 | P413: 宾馆酒店 | Q413: 新建 | R413: 安徽上景酒店有限公司 | S413: 913417230691243862 | T413: 01012025091430192 | U413: 青阳县经济开发区伯益上东城小区6-2幢101、201室青房地权证2013字第00000954号 | V413: 青房地产他证2014字第00001937号 | W413: 2048/1/1 | X413: 65.54 | Y413: 平方米 | Z413: 是 | AA413: 安徽省 | AB413: 池州市 | AC413: 青阳县 | AD413: 青阳县经济开发区伯益上东城小区6-2幢101、201室 | AE413: 第一顺位 | AF413: 800 | AG413: 外部评估 | AH413: 45071 | AI413: 30.48 | AJ413: 否 | AL413: 不涉及 | AO413: 张乐群,曹吉峰,董俣顺,许之玮,邹熠峰,郑舒凌 | AP413: 安徽分公司 | AQ413: 12230013 | AR413: 收购徽商银行2023年第2批133户不良资产包项目 | AS413: 45170 | AU413: 11001 | AV413: 已剔重 | AX413: =COUNTIFS(拍卖数据!E:E,AA413,拍卖数据!F:F,AB413,拍卖数据!O:O,O413,拍卖数据!P:P,">"&X413*0.8,拍卖数据!P:P,"<"&X413*1.2) -> 2 | AY413: =COUNTIFS(拍卖数据!E:E,AA413,拍卖数据!F:F,AB413,拍卖数据!O:O,O413,拍卖数据!AN:AN,"机构",拍卖数据!P:P,">"&X413*0.8,拍卖数据!P:P,"<"&X413*1.2) -> 0 | AZ413: =COUNTIFS(拍卖数据!E:E,AA413,拍卖数据!F:F,AB413,拍卖数据!G:G,AC413,拍卖数据!O:O,O413,拍卖数据!AN:AN,"机构",拍卖数据!P:P,">"&X413*0.8,拍卖数据!P:P,"<"&X413*1.2) -> 0
A414: 22233 | B414: 12230013032500000001 | C414: 否 | D414: 合肥海贝特科贸有限公司 | E414: 其他文化用品批发 | F414: 777.16123 | G414: 762.27406 | H414: 0 | I414: 0 | J414: 1539.4353 | K414: 抵押,质押,保证 | L414: 汪昌其,汪涧明 | M414: 260 | N414: 现房 | O414: 商业用房 | P414: 宾馆酒店 | Q414: 新建 | R414: 安徽上景酒店有限公司 | S414: 913417230691243862 | T414: 01012025091430196 | U414: 青阳县经济开发区伯益上东城小区6-2幢307、407室青房地权证2013字第00000961号 | V414: 青房地产他证2014字第00001937号 | W414: 2048/1/1 | X414: 1337 | Y414: 平方米 | Z414: 是 | AA414: 安徽省 | AB414: 池州市 | AC414: 青阳县 | AD414: 青阳县经济开发区伯益上东城小区6-2幢307、407室 | AE414: 第一顺位 | AF414: 800 | AG414: 外部评估 | AH414: 45071 | AI414: 310.85 | AJ414: 否 | AL414: 不涉及 | AO414: 张乐群,曹吉峰,董俣顺,许之玮,邹熠峰,郑舒凌 | AP414: 安徽分公司 | AQ414: 12230013 | AR414: 收购徽商银行2023年第2批133户不良资产包项目 | AS414: 45170 | AU414: 11001 | AV414: 已剔重 | AX414: =COUNTIFS(拍卖数据!E:E,AA414,拍卖数据!F:F,AB414,拍卖数据!O:O,O414,拍卖数据!P:P,">"&X414*0.8,拍卖数据!P:P,"<"&X414*1.2) -> 1 | AY414: =COUNTIFS(拍卖数据!E:E,AA414,拍卖数据!F:F,AB414,拍卖数据!O:O,O414,拍卖数据!AN:AN,"机构",拍卖数据!P:P,">"&X414*0.8,拍卖数据!P:P,"<"&X414*1.2) -> 0 | AZ414: =COUNTIFS(拍卖数据!E:E,AA414,拍卖数据!F:F,AB414,拍卖数据!G:G,AC414,拍卖数据!O:O,O414,拍卖数据!AN:AN,"机构",拍卖数据!P:P,">"&X414*0.8,拍卖数据!P:P,"<"&X414*1.2) -> 0
A415: 22234 | B415: 12230013032500000001 | C415: 否 | D415: 合肥海贝特科贸有限公司 | E415: 其他文化用品批发 | F415: 777.16123 | G415: 762.27406 | H415: 0 | I415: 0 | J415: 1539.4353 | K415: 抵押,质押,保证 | L415: 汪昌其,汪涧明 | M415: 260 | N415: 现房 | O415: 商业用房 | P415: 宾馆酒店 | Q415: 新建 | R415: 安徽上景酒店有限公司 | S415: 913417230691243862 | T415: 01012025091430195 | U415: 青阳县经济开发区伯益上东城小区6-2幢107、207室青房地权证2013字第00000960号 | V415: 青房地产他证2014字第00001937号 | W415: 2048/1/1 | X415: 973.48 | Y415: 平方米 | Z415: 是 | AA415: 安徽省 | AB415: 池州市 | AC415: 青阳县 | AD415: 青阳县经济开发区伯益上东城小区6-2幢107、207室 | AE415: 第一顺位 | AF415: 800 | AG415: 外部评估 | AH415: 45071 | AI415: 452.67 | AJ415: 否 | AL415: 不涉及 | AO415: 张乐群,曹吉峰,董俣顺,许之玮,邹熠峰,郑舒凌 | AP415: 安徽分公司 | AQ415: 12230013 | AR415: 收购徽商银行2023年第2批133户不良资产包项目 | AS415: 45170 | AU415: 11001 | AV415: 已剔重 | AX415: =COUNTIFS(拍卖数据!E:E,AA415,拍卖数据!F:F,AB415,拍卖数据!O:O,O415,拍卖数据!P:P,">"&X415*0.8,拍卖数据!P:P,"<"&X415*1.2) -> 1 | AY415: =COUNTIFS(拍卖数据!E:E,AA415,拍卖数据!F:F,AB415,拍卖数据!O:O,O415,拍卖数据!AN:AN,"机构",拍卖数据!P:P,">"&X415*0.8,拍卖数据!P:P,"<"&X415*1.2) -> 0 | AZ415: =COUNTIFS(拍卖数据!E:E,AA415,拍卖数据!F:F,AB415,拍卖数据!G:G,AC415,拍卖数据!O:O,O415,拍卖数据!AN:AN,"机构",拍卖数据!P:P,">"&X415*0.8,拍卖数据!P:P,"<"&X415*1.2) -> 0
A416: 22235 | B416: 12230013032500000001 | C416: 否 | D416: 合肥海贝特科贸有限公司 | E416: 其他文化用品批发 | F416: 777.16123 | G416: 762.27406 | H416: 0 | I416: 0 | J416: 1539.4353 | K416: 抵押,质押,保证 | L416: 汪昌其,汪涧明 | M416: 260 | N416: 现房 | O416: 商业用房 | P416: 宾馆酒店 | Q416: 新建 | R416: 安徽上景酒店有限公司 | S416: 913417230691243862 | T416: 01012025091430194 | U416: 青阳县经济开发区伯益上东城小区6-2幢103、203室青房地权证2013字第00000956号 | V416: 青房地产他证2014字第00001937号 | W416: 2048/1/1 | X416: 65.54 | Y416: 平方米 | Z416: 是 | AA416: 安徽省 | AB416: 池州市 | AC416: 青阳县 | AD416: 青阳县经济开发区伯益上东城小区6-2幢103、203室 | AE416: 第一顺位 | AF416: 800 | AG416: 外部评估 | AH416: 45071 | AI416: 30.48 | AJ416: 否 | AL416: 不涉及 | AO416: 张乐群,曹吉峰,董俣顺,许之玮,邹熠峰,郑舒凌 | AP416: 安徽分公司 | AQ416: 12230013 | AR416: 收购徽商银行2023年第2批133户不良资产包项目 | AS416: 45170 | AU416: 11001 | AV416: 已剔重 | AX416: =COUNTIFS(拍卖数据!E:E,AA416,拍卖数据!F:F,AB416,拍卖数据!O:O,O416,拍卖数据!P:P,">"&X416*0.8,拍卖数据!P:P,"<"&X416*1.2) -> 2 | AY416: =COUNTIFS(拍卖数据!E:E,AA416,拍卖数据!F:F,AB416,拍卖数据!O:O,O416,拍卖数据!AN:AN,"机构",拍卖数据!P:P,">"&X416*0.8,拍卖数据!P:P,"<"&X416*1.2) -> 0 | AZ416: =COUNTIFS(拍卖数据!E:E,AA416,拍卖数据!F:F,AB416,拍卖数据!G:G,AC416,拍卖数据!O:O,O416,拍卖数据!AN:AN,"机构",拍卖数据!P:P,">"&X416*0.8,拍卖数据!P:P,"<"&X416*1.2) -> 0
A417: 22236 | B417: 12230013032500000001 | C417: 否 | D417: 合肥海贝特科贸有限公司 | E417: 其他文化用品批发 | F417: 777.16123 | G417: 762.27406 | H417: 0 | I417: 0 | J417: 1539.4353 | K417: 抵押,质押,保证 | L417: 汪昌其,汪涧明 | M417: 260 | N417: 现房 | O417: 商业用房 | P417: 宾馆酒店 | Q417: 新建 | R417: 安徽上景酒店有限公司 | S417: 913417230691243862 | T417: 01012025091430193 | U417: 青阳县经济开发区伯益上东城小区6-2幢102、202室青房地权证2013字第00000955号 | V417: 青房地产他证2014字第00001937号 | W417: 2048/1/1 | X417: 66.46 | Y417: 平方米 | Z417: 是 | AA417: 安徽省 | AB417: 池州市 | AC417: 青阳县 | AD417: 青阳县经济开发区伯益上东城小区6-2幢102、202室 | AE417: 第一顺位 | AF417: 800 | AG417: 外部评估 | AH417: 45071 | AI417: 30.9 | AJ417: 否 | AL417: 不涉及 | AO417: 张乐群,曹吉峰,董俣顺,许之玮,邹熠峰,郑舒凌 | AP417: 安徽分公司 | AQ417: 12230013 | AR417: 收购徽商银行2023年第2批133户不良资产包项目 | AS417: 45170 | AU417: 11001 | AV417: 已剔重 | AX417: =COUNTIFS(拍卖数据!E:E,AA417,拍卖数据!F:F,AB417,拍卖数据!O:O,O417,拍卖数据!P:P,">"&X417*0.8,拍卖数据!P:P,"<"&X417*1.2) -> 2 | AY417: =COUNTIFS(拍卖数据!E:E,AA417,拍卖数据!F:F,AB417,拍卖数据!O:O,O417,拍卖数据!AN:AN,"机构",拍卖数据!P:P,">"&X417*0.8,拍卖数据!P:P,"<"&X417*1.2) -> 0 | AZ417: =COUNTIFS(拍卖数据!E:E,AA417,拍卖数据!F:F,AB417,拍卖数据!G:G,AC417,拍卖数据!O:O,O417,拍卖数据!AN:AN,"机构",拍卖数据!P:P,">"&X417*0.8,拍卖数据!P:P,"<"&X417*1.2) -> 0
A418: 22237 | B418: 12230013033900000001 | C418: 否 | D418: 合肥聚声信息科技有限公司 | E418: 软件和信息技术服务业 | F418: 203.66041 | G418: 391.24156 | H418: 0 | I418: 0 | J418: 594.90197 | K418: 抵押,质押,保证 | L418: 何承旺,沈浩 | M418: 100 | N418: 现房 | O418: 商业用房 | P418: 集中商业（购物中心，综合体商业等） | Q418: 新建 | R418: 何巨 | S418: 340102197611263028 | T418: 01012025091430190 | U418: 和平广场114,115号房地权瑶字第015241号 | V418: 房地产他证合瑶字第220039853号 | W418: 2039/1/1 | X418: 224.38 | Y418: 平方米 | Z418: 是 | AA418: 安徽省 | AB418: 合肥市 | AC418: 瑶海区 | AD418: 和平广场114,115号 | AE418: 第一顺位 | AF418: 350 | AG418: 外部评估 | AH418: 45071 | AI418: 180.63 | AJ418: 否 | AL418: 不涉及 | AM418: 0 | AO418: 张乐群,曹吉峰,董俣顺,许之玮,邹熠峰,郑舒凌 | AP418: 安徽分公司 | AQ418: 12230013 | AR418: 收购徽商银行2023年第2批133户不良资产包项目 | AS418: 45170 | AU418: 11001 | AV418: 已剔重 | AX418: =COUNTIFS(拍卖数据!E:E,AA418,拍卖数据!F:F,AB418,拍卖数据!O:O,O418,拍卖数据!P:P,">"&X418*0.8,拍卖数据!P:P,"<"&X418*1.2) -> 24 | AY418: =COUNTIFS(拍卖数据!E:E,AA418,拍卖数据!F:F,AB418,拍卖数据!O:O,O418,拍卖数据!AN:AN,"机构",拍卖数据!P:P,">"&X418*0.8,拍卖数据!P:P,"<"&X418*1.2) -> 1 | AZ418: =COUNTIFS(拍卖数据!E:E,AA418,拍卖数据!F:F,AB418,拍卖数据!G:G,AC418,拍卖数据!O:O,O418,拍卖数据!AN:AN,"机构",拍卖数据!P:P,">"&X418*0.8,拍卖数据!P:P,"<"&X418*1.2) -> 0
A419: 22238 | B419: 12240051001000000001 | C419: 否 | D419: 合肥达美建筑装饰工程有限责任公司 | E419: 其他未列明建筑业 | F419: 2900 | G419: 154.56777 | H419: 15.5 | I419: 0 | J419: 3070.0678 | K419: 抵押,质押,保证 | L419: 蒋勇,蒋建良 | M419: 2790.0956 | N419: 现房 | O419: 工业用房 | P419: 标准工业厂房及仓储 | Q419: 已入库 | R419: 安徽合光幕墙建设工程有限公司 | S419: 91340100563444246D | T419: 01012025080780815 | U419: 小庙镇工业聚集区安徽合光幕墙建设工程有限公司2#厂房 | V419: 皖(2021)肥西县不动产证明第0024012号 | W419: 2061/12/19 | X419: 26664.65 | Y419: 平方米 | Z419: 是 | AA419: 安徽省 | AB419: 合肥市 | AC419: 蜀山区 | AD419: 小庙镇工业聚集区安徽合光幕墙建设工程有限公司2#厂房 | AE419: 第一顺位 | AF419: 4333.01 | AG419: 外部评估 | AH419: 45565 | AI419: 3514.51 | AJ419: 否 | AL419: 不涉及 | AO419: 张乐群,董俣顺,许之玮,郑舒凌 | AP419: 安徽分公司 | AQ419: 12240051 | AR419: 收购中信银行合肥分行2024年第1批10户不良资产包项目 | AS419: 45642 | AU419: 11001 | AV419: 已剔重 | AX419: =COUNTIFS(拍卖数据!E:E,AA419,拍卖数据!F:F,AB419,拍卖数据!O:O,O419,拍卖数据!P:P,">"&X419*0.8,拍卖数据!P:P,"<"&X419*1.2) -> 0 | AY419: =COUNTIFS(拍卖数据!E:E,AA419,拍卖数据!F:F,AB419,拍卖数据!O:O,O419,拍卖数据!AN:AN,"机构",拍卖数据!P:P,">"&X419*0.8,拍卖数据!P:P,"<"&X419*1.2) -> 0 | AZ419: =COUNTIFS(拍卖数据!E:E,AA419,拍卖数据!F:F,AB419,拍卖数据!G:G,AC419,拍卖数据!O:O,O419,拍卖数据!AN:AN,"机构",拍卖数据!P:P,">"&X419*0.8,拍卖数据!P:P,"<"&X419*1.2) -> 0
A420: 22239 | B420: 12253002010016 | C420: 否 | D420: 合肥金荟文化传媒有限公司 | E420: 文化、体育和娱乐业 | F420: 37 | G420: 0.686521 | H420: 0 | J420: 37.686521 | K420: 抵押,保证 | L420: 包金山,黄霞 | M420: 0 | N420: 现房 | O420: 居住用房 | P420: 普通商品住房 | Q420: 已入库 | R420: 包金山 | S420: 342901199008036611 | T420: 01012025062630018 | U420: 合肥市瑶海区明光路518号恒大广场20幢住宅2705 | V420: 皖 (2022) 合肥市不动产证明第2016397号 | W420: 2083-09-10 | X420: 81.76 | Y420: 平方米 | Z420: 是 | AA420: 安徽省 | AB420: 合肥市 | AC420: 瑶海区 | AD420: 合肥市瑶海区明光路518号恒大广场20幢住宅2705 | AE420: 第二顺位 | AF420: 90 | AG420: 内部测算 | AH420: 45803 | AI420: 0 | AJ420: 是 | AK420: A02.押品非第一顺位抵质押 | AL420: 不涉及 | AM420: 0 | AO420: 张乐群,郑舒凌,陈文轩 | AP420: 安徽分公司 | AQ420: 12253002 | AR420: 收购浙商银行2025年第二季度总对总不良资产包项目 | AS420: 45838 | AU420: 11002 | AV420: 已剔重 | AX420: =COUNTIFS(拍卖数据!E:E,AA420,拍卖数据!F:F,AB420,拍卖数据!O:O,O420,拍卖数据!P:P,">"&X420*0.8,拍卖数据!P:P,"<"&X420*1.2) -> 261 | AY420: =COUNTIFS(拍卖数据!E:E,AA420,拍卖数据!F:F,AB420,拍卖数据!O:O,O420,拍卖数据!AN:AN,"机构",拍卖数据!P:P,">"&X420*0.8,拍卖数据!P:P,"<"&X420*1.2) -> 0 | AZ420: =COUNTIFS(拍卖数据!E:E,AA420,拍卖数据!F:F,AB420,拍卖数据!G:G,AC420,拍卖数据!O:O,O420,拍卖数据!AN:AN,"机构",拍卖数据!P:P,">"&X420*0.8,拍卖数据!P:P,"<"&X420*1.2) -> 0
A421: 22241 | B421: 12240051000700000001 | C421: 否 | D421: 合肥高压开关有限公司 | E421: 配电开关控制设备制造 | F421: 2500 | G421: 2094.1537 | H421: 26.5787 | I421: 0 | J421: 4620.7324 | K421: 抵押,质押,保证 | L421: 何建国,郑彩萍 | M421: 2398.9532 | N421: 现房 | O421: 工业用房 | P421: 标准工业厂房及仓储 | Q421: 已入库 | R421: 安徽耀华控股集团有限公司 | S421: 91340100756822290K | T421: 01012025080780813 | U421: 新站区瑶海区工业园区01号永泵车间房地权证合产字第8110104751号 | V421: 房地产他证合产字第8210044096号 | W421: 2056/12/1 | X421: 8741.09 | Y421: 平方米 | Z421: 是 | AA421: 安徽省 | AB421: 合肥市 | AC421: 瑶海区 | AD421: 新站区瑶海区工业园区01号永泵车间 | AE421: 第一顺位 | AF421: 1000 | AG421: 外部评估 | AH421: 45565 | AI421: 774.12 | AJ421: 否 | AL421: 不涉及 | AO421: 张乐群,董俣顺,许之玮,郑舒凌 | AP421: 安徽分公司 | AQ421: 12240051 | AR421: 收购中信银行合肥分行2024年第1批10户不良资产包项目 | AS421: 45642 | AU421: 11001 | AV421: 已剔重 | AX421: =COUNTIFS(拍卖数据!E:E,AA421,拍卖数据!F:F,AB421,拍卖数据!O:O,O421,拍卖数据!P:P,">"&X421*0.8,拍卖数据!P:P,"<"&X421*1.2) -> 0 | AY421: =COUNTIFS(拍卖数据!E:E,AA421,拍卖数据!F:F,AB421,拍卖数据!O:O,O421,拍卖数据!AN:AN,"机构",拍卖数据!P:P,">"&X421*0.8,拍卖数据!P:P,"<"&X421*1.2) -> 0 | AZ421: =COUNTIFS(拍卖数据!E:E,AA421,拍卖数据!F:F,AB421,拍卖数据!G:G,AC421,拍卖数据!O:O,O421,拍卖数据!AN:AN,"机构",拍卖数据!P:P,">"&X421*0.8,拍卖数据!P:P,"<"&X421*1.2) -> 0
A422: 22242 | B422: 12240051000700000001 | C422: 否 | D422: 合肥高压开关有限公司 | E422: 配电开关控制设备制造 | F422: 2500 | G422: 2094.1537 | H422: 26.5787 | I422: 0 | J422: 4620.7324 | K422: 抵押,质押,保证 | L422: 何建国,郑彩萍 | M422: 2398.9532 | N422: 土地使用权 | O422: 工业用地 | P422: 工业用地 | Q422: 已入库 | R422: 安徽耀华控股集团有限公司 | S422: 91340100756822290K | T422: 01022025080780814 | U422: 新海大道南合新站国用（2013）第054号 | V422: 合新站他项（2013）第154号 | W422: 2056/12/1 | X422: 43469.1 | Y422: 平方米 | Z422: 是 | AA422: 安徽省 | AB422: 合肥市 | AC422: 瑶海区 | AD422: 新海大道 | AE422: 第一顺位 | AF422: 2500 | AG422: 外部评估 | AH422: 45565 | AI422: 1731.81 | AJ422: 否 | AL422: 不涉及 | AO422: 张乐群,董俣顺,许之玮,郑舒凌 | AP422: 安徽分公司 | AQ422: 12240051 | AR422: 收购中信银行合肥分行2024年第1批10户不良资产包项目 | AS422: 45642 | AU422: 11001 | AV422: 已剔重 | AX422: =COUNTIFS(拍卖数据!E:E,AA422,拍卖数据!F:F,AB422,拍卖数据!O:O,O422,拍卖数据!P:P,">"&X422*0.8,拍卖数据!P:P,"<"&X422*1.2) -> 0 | AY422: =COUNTIFS(拍卖数据!E:E,AA422,拍卖数据!F:F,AB422,拍卖数据!O:O,O422,拍卖数据!AN:AN,"机构",拍卖数据!P:P,">"&X422*0.8,拍卖数据!P:P,"<"&X422*1.2) -> 0 | AZ422: =COUNTIFS(拍卖数据!E:E,AA422,拍卖数据!F:F,AB422,拍卖数据!G:G,AC422,拍卖数据!O:O,O422,拍卖数据!AN:AN,"机构",拍卖数据!P:P,">"&X422*0.8,拍卖数据!P:P,"<"&X422*1.2) -> 0
A423: 22244 | B423: 12190067000400000002 | C423: 否 | D423: 合肥龙泰农业科技有限公司 | E423: 农业科学研究和试验发展 | F423: 944.39545 | G423: 551.2484 | H423: 0 | I423: 0 | J423: 1495.6439 | K423: 抵押,质押,保证 | M423: 502.95175 | N423: 现房 | O423: 商业用房 | P423: 商业公寓 | Q423: 新建 | R423: 沈倩 | S423: 340111198703036544 | T423: 01012025081220452 | U423: 庐阳区蒙城北路102号新华文景苑10幢商业二层204室房权证合庐字第8130004192号,合国用2008第567号 | V423: 房地产他证合庐字第230024608号 | W423: 2047/1/1 | X423: 668.57 | Y423: 平方米 | Z423: 是 | AA423: 安徽省 | AB423: 合肥市 | AC423: 庐阳区 | AD423: 庐阳区蒙城北路102号新华文景苑10幢商业二层204室 | AE423: 第一顺位 | AF423: 1150 | AG423: 外部评估 | AH423: 43710 | AI423: 521.48 | AJ423: 否 | AL423: 不涉及 | AM423: 0 | AO423: 刘伟(安徽分公司),姜碧霏,张乐群,张梅,戴宁,牛琪,许之玮,赵艳(安徽分公司),郑蓓,齐奥 | AP423: 安徽分公司 | AQ423: 12190067 | AR423: 收购安徽建行对安徽大平油脂公司等16户企业持有的金融不良债权项目 | AS423: 43791 | AU423: 11001 | AV423: 已剔重 | AX423: =COUNTIFS(拍卖数据!E:E,AA423,拍卖数据!F:F,AB423,拍卖数据!O:O,O423,拍卖数据!P:P,">"&X423*0.8,拍卖数据!P:P,"<"&X423*1.2) -> 8 | AY423: =COUNTIFS(拍卖数据!E:E,AA423,拍卖数据!F:F,AB423,拍卖数据!O:O,O423,拍卖数据!AN:AN,"机构",拍卖数据!P:P,">"&X423*0.8,拍卖数据!P:P,"<"&X423*1.2) -> 3 | AZ423: =COUNTIFS(拍卖数据!E:E,AA423,拍卖数据!F:F,AB423,拍卖数据!G:G,AC423,拍卖数据!O:O,O423,拍卖数据!AN:AN,"机构",拍卖数据!P:P,">"&X423*0.8,拍卖数据!P:P,"<"&X423*1.2) -> 1
A424: 22245 | B424: 12190067000400000002 | C424: 否 | D424: 合肥龙泰农业科技有限公司 | E424: 农业科学研究和试验发展 | F424: 944.39545 | G424: 551.2484 | H424: 0 | I424: 0 | J424: 1495.6439 | K424: 抵押,质押,保证 | M424: 502.95175 | N424: 现房 | O424: 商业用房 | P424: 独立商铺 | Q424: 新建 | R424: 沈倩 | S424: 340111198703036544 | T424: 01012025081220455 | U424: 合肥市新海大道星港湾家园会所132室房地权证合瑶字第120049502号 | V424: 房地产他证合产字第8210058565号 | W424: 2047/1/1 | X424: 56.52 | Y424: 平方米 | Z424: 是 | AA424: 安徽省 | AB424: 合肥市 | AC424: 庐阳区 | AD424: 合肥市新海大道星港湾家园会所132室 | AE424: 第一顺位 | AF424: 750 | AG424: 外部评估 | AH424: 43710 | AI424: 67.82 | AJ424: 否 | AL424: 不涉及 | AM424: 0 | AO424: 刘伟(安徽分公司),姜碧霏,张乐群,张梅,戴宁,牛琪,许之玮,赵艳(安徽分公司),郑蓓,齐奥 | AP424: 安徽分公司 | AQ424: 12190067 | AR424: 收购安徽建行对安徽大平油脂公司等16户企业持有的金融不良债权项目 | AS424: 43791 | AU424: 11001 | AV424: 已剔重 | AX424: =COUNTIFS(拍卖数据!E:E,AA424,拍卖数据!F:F,AB424,拍卖数据!O:O,O424,拍卖数据!P:P,">"&X424*0.8,拍卖数据!P:P,"<"&X424*1.2) -> 41 | AY424: =COUNTIFS(拍卖数据!E:E,AA424,拍卖数据!F:F,AB424,拍卖数据!O:O,O424,拍卖数据!AN:AN,"机构",拍卖数据!P:P,">"&X424*0.8,拍卖数据!P:P,"<"&X424*1.2) -> 0 | AZ424: =COUNTIFS(拍卖数据!E:E,AA424,拍卖数据!F:F,AB424,拍卖数据!G:G,AC424,拍卖数据!O:O,O424,拍卖数据!AN:AN,"机构",拍卖数据!P:P,">"&X424*0.8,拍卖数据!P:P,"<"&X424*1.2) -> 0
A425: 22246 | B425: 12190067000400000002 | C425: 否 | D425: 合肥龙泰农业科技有限公司 | E425: 农业科学研究和试验发展 | F425: 944.39545 | G425: 551.2484 | H425: 0 | I425: 0 | J425: 1495.6439 | K425: 抵押,质押,保证 | M425: 502.95175 | N425: 现房 | O425: 商业用房 | P425: 独立商铺 | Q425: 新建 | R425: 沈倩 | S425: 340111198703036544 | T425: 01012025081220454 | U425: 合肥市新海大道星港湾家园会所131室房地权证合瑶字第120049501号 | V425: 房地产他证合产字第8210058565号 | W425: 2047/1/1 | X425: 56.52 | Y425: 平方米 | Z425: 是 | AA425: 安徽省 | AB425: 合肥市 | AC425: 庐阳区 | AD425: 合肥市新海大道星港湾家园会所131室 | AE425: 第一顺位 | AF425: 750 | AG425: 外部评估 | AH425: 43710 | AI425: 67.82 | AJ425: 否 | AL425: 不涉及 | AM425: 0 | AO425: 刘伟(安徽分公司),姜碧霏,张乐群,张梅,戴宁,牛琪,许之玮,赵艳(安徽分公司),郑蓓,齐奥 | AP425: 安徽分公司 | AQ425: 12190067 | AR425: 收购安徽建行对安徽大平油脂公司等16户企业持有的金融不良债权项目 | AS425: 43791 | AU425: 11001 | AV425: 已剔重 | AX425: =COUNTIFS(拍卖数据!E:E,AA425,拍卖数据!F:F,AB425,拍卖数据!O:O,O425,拍卖数据!P:P,">"&X425*0.8,拍卖数据!P:P,"<"&X425*1.2) -> 41 | AY425: =COUNTIFS(拍卖数据!E:E,AA425,拍卖数据!F:F,AB425,拍卖数据!O:O,O425,拍卖数据!AN:AN,"机构",拍卖数据!P:P,">"&X425*0.8,拍卖数据!P:P,"<"&X425*1.2) -> 0 | AZ425: =COUNTIFS(拍卖数据!E:E,AA425,拍卖数据!F:F,AB425,拍卖数据!G:G,AC425,拍卖数据!O:O,O425,拍卖数据!AN:AN,"机构",拍卖数据!P:P,">"&X425*0.8,拍卖数据!P:P,"<"&X425*1.2) -> 0
A426: 22247 | B426: 12190067000400000002 | C426: 否 | D426: 合肥龙泰农业科技有限公司 | E426: 农业科学研究和试验发展 | F426: 944.39545 | G426: 551.2484 | H426: 0 | I426: 0 | J426: 1495.6439 | K426: 抵押,质押,保证 | M426: 502.95175 | N426: 现房 | O426: 商业用房 | P426: 独立商铺 | Q426: 新建 | R426: 沈倩 | S426: 340111198703036544 | T426: 01012025081220453 | U426: 合肥市新海大道星港湾家园会所130室房地权证合瑶字第120049500号 | V426: 房地产他证合产字第8210058565号 | W426: 2047/1/1 | X426: 56.52 | Y426: 平方米 | Z426: 是 | AA426: 安徽省 | AB426: 合肥市 | AC426: 庐阳区 | AD426: 合肥市新海大道星港湾家园会所130室 | AE426: 第一顺位 | AF426: 750 | AG426: 外部评估 | AH426: 43710 | AI426: 67.82 | AJ426: 否 | AL426: 不涉及 | AM426: 0 | AO426: 刘伟(安徽分公司),姜碧霏,张乐群,张梅,戴宁,牛琪,许之玮,赵艳(安徽分公司),郑蓓,齐奥 | AP426: 安徽分公司 | AQ426: 12190067 | AR426: 收购安徽建行对安徽大平油脂公司等16户企业持有的金融不良债权项目 | AS426: 43791 | AU426: 11001 | AV426: 已剔重 | AX426: =COUNTIFS(拍卖数据!E:E,AA426,拍卖数据!F:F,AB426,拍卖数据!O:O,O426,拍卖数据!P:P,">"&X426*0.8,拍卖数据!P:P,"<"&X426*1.2) -> 41 | AY426: =COUNTIFS(拍卖数据!E:E,AA426,拍卖数据!F:F,AB426,拍卖数据!O:O,O426,拍卖数据!AN:AN,"机构",拍卖数据!P:P,">"&X426*0.8,拍卖数据!P:P,"<"&X426*1.2) -> 0 | AZ426: =COUNTIFS(拍卖数据!E:E,AA426,拍卖数据!F:F,AB426,拍卖数据!G:G,AC426,拍卖数据!O:O,O426,拍卖数据!AN:AN,"机构",拍卖数据!P:P,">"&X426*0.8,拍卖数据!P:P,"<"&X426*1.2) -> 0
A427: 28872 | B427: 12253005010005 | C427: 否 | D427: 国厚资产管理股份有限公司 | E427: 其他未包括金融业 | F427: 11399.611 | G427: 80.803886 | H427: 0.5 | J427: 11480.915 | K427: 抵押,保证 | L427: 李厚文,李双全 | M427: 6388.6485 | N427: 现房 | O427: 办公用房 | P427: 高层办公楼 | Q427: 已入库 | R427: 澳中财富（合肥）投资置业有限公司 | S427: 91340100799823859F | T427: 01012025071130000 | U427: 商业房产 | V427: 皖（2024）合肥市不动产证明第1028551号 | W427: 2048-04-15 | X427: 14634.03 | Y427: 平方米 | Z427: 是 | AA427: 安徽省 | AB427: 合肥市 | AC427: 蜀山区 | AD427: 合肥市经开区金寨南路916号澳中财富中心一期工程 | AE427: 第零顺位 | AF427: 11400 | AG427: 外部评估 | AH427: 45776 | AI427: 9952.34 | AJ427: 否 | AL427: 不涉及 | AM427: 0 | AO427: 许之玮,陈文轩 | AP427: 安徽分公司 | AQ427: 12253005 | AR427: 收购九江银行合肥分行2025年第1批3户不良资产包项目 | AS427: 45834 | AU427: 11000 | AV427: 已剔重 | AX427: =COUNTIFS(拍卖数据!E:E,AA427,拍卖数据!F:F,AB427,拍卖数据!O:O,O427,拍卖数据!P:P,">"&X427*0.8,拍卖数据!P:P,"<"&X427*1.2) -> 0 | AY427: =COUNTIFS(拍卖数据!E:E,AA427,拍卖数据!F:F,AB427,拍卖数据!O:O,O427,拍卖数据!AN:AN,"机构",拍卖数据!P:P,">"&X427*0.8,拍卖数据!P:P,"<"&X427*1.2) -> 0 | AZ427: =COUNTIFS(拍卖数据!E:E,AA427,拍卖数据!F:F,AB427,拍卖数据!G:G,AC427,拍卖数据!O:O,O427,拍卖数据!AN:AN,"机构",拍卖数据!P:P,">"&X427*0.8,拍卖数据!P:P,"<"&X427*1.2) -> 0
A428: 37288 | B428: 12190067001400000001 | C428: 否 | D428: 宁国市国泰建材销售有限公司 | E428: 建材批发 | F428: 60.42295 | G428: 3.023637 | H428: 0 | I428: 0 | J428: 63.446587 | K428: 抵押,质押,保证 | M428: 20.217547 | N428: 现房 | O428: 商业用房 | P428: 独立商铺 | Q428: 新建 | R428: 邓庆平,佘昌琴 | S428: ‘342524196504152012,342524197109202045 | T428: 01012025081220449 | U428: 凤形路金宁锦秀家园32幢1001号房地权证宁字第00051326号,宁国用（2013）第304号 | V428: 皖（2016）宁国市不动产证明第0000812号 | W428: 2046/6/29 | X428: 304.41 | Y428: 平方米 | Z428: 是 | AA428: 安徽省 | AB428: 宣城市 | AC428: 宁国市 | AD428: 凤形路金宁锦秀家园32幢1001号 | AE428: 第一顺位 | AF428: 200 | AG428: 外部评估 | AH428: 43710 | AI428: 243.53 | AJ428: 否 | AL428: 不涉及 | AO428: 刘伟(安徽分公司),姜碧霏,张乐群,张梅,戴宁,牛琪,许之玮,赵艳(安徽分公司),郑蓓,齐奥 | AP428: 安徽分公司 | AQ428: 12190067 | AR428: 收购安徽建行对安徽大平油脂公司等16户企业持有的金融不良债权项目 | AS428: 43791 | AU428: 11001 | AV428: 已剔重 | AX428: =COUNTIFS(拍卖数据!E:E,AA428,拍卖数据!F:F,AB428,拍卖数据!O:O,O428,拍卖数据!P:P,">"&X428*0.8,拍卖数据!P:P,"<"&X428*1.2) -> 7 | AY428: =COUNTIFS(拍卖数据!E:E,AA428,拍卖数据!F:F,AB428,拍卖数据!O:O,O428,拍卖数据!AN:AN,"机构",拍卖数据!P:P,">"&X428*0.8,拍卖数据!P:P,"<"&X428*1.2) -> 0 | AZ428: =COUNTIFS(拍卖数据!E:E,AA428,拍卖数据!F:F,AB428,拍卖数据!G:G,AC428,拍卖数据!O:O,O428,拍卖数据!AN:AN,"机构",拍卖数据!P:P,">"&X428*0.8,拍卖数据!P:P,"<"&X428*1.2) -> 0
A429: 37289 | B429: 12190067001400000002 | C429: 否 | D429: 宁国市国泰建材销售有限公司 | E429: 建材批发 | F429: 177.98242 | G429: 10.416315 | H429: 0 | I429: 0 | J429: 188.39873 | K429: 抵押,质押,保证 | M429: 62.565403 | N429: 现房 | O429: 商业用房 | P429: 独立商铺 | Q429: 新建 | R429: 邓庆平,佘昌琴 | S429: ‘342524196504152012,342524197109202045 | T429: 01012025081220450 | U429: 凤形路凤形商住楼3幢1011室房地权证宁字第00044837号,宁国用（2012）第786号 | V429: 皖（2018）宁国市不动产证明第0000804号 | W429: 2047/5/31 | X429: 44.49 | Y429: 平方米 | Z429: 是 | AA429: 安徽省 | AB429: 宣城市 | AC429: 宁国市 | AD429: 凤形路凤形商住楼3幢1011室 | AE429: 第一顺位 | AF429: 90 | AG429: 外部评估 | AH429: 43710 | AI429: 31.14 | AJ429: 否 | AL429: 不涉及 | AO429: 刘伟(安徽分公司),姜碧霏,张乐群,张梅,戴宁,牛琪,许之玮,赵艳(安徽分公司),郑蓓,齐奥 | AP429: 安徽分公司 | AQ429: 12190067 | AR429: 收购安徽建行对安徽大平油脂公司等16户企业持有的金融不良债权项目 | AS429: 43791 | AU429: 11001 | AV429: 已剔重 | AX429: =COUNTIFS(拍卖数据!E:E,AA429,拍卖数据!F:F,AB429,拍卖数据!O:O,O429,拍卖数据!P:P,">"&X429*0.8,拍卖数据!P:P,"<"&X429*1.2) -> 2 | AY429: =COUNTIFS(拍卖数据!E:E,AA429,拍卖数据!F:F,AB429,拍卖数据!O:O,O429,拍卖数据!AN:AN,"机构",拍卖数据!P:P,">"&X429*0.8,拍卖数据!P:P,"<"&X429*1.2) -> 0 | AZ429: =COUNTIFS(拍卖数据!E:E,AA429,拍卖数据!F:F,AB429,拍卖数据!G:G,AC429,拍卖数据!O:O,O429,拍卖数据!AN:AN,"机构",拍卖数据!P:P,">"&X429*0.8,拍卖数据!P:P,"<"&X429*1.2) -> 0
A430: 37290 | B430: 12190067001400000002 | C430: 否 | D430: 宁国市国泰建材销售有限公司 | E430: 建材批发 | F430: 177.98242 | G430: 10.416315 | H430: 0 | I430: 0 | J430: 188.39873 | K430: 抵押,质押,保证 | M430: 62.565403 | N430: 现房 | O430: 商业用房 | P430: 独立商铺 | Q430: 新建 | R430: 邓庆平,佘昌琴 | S430: ‘342524196504152012,342524197109202045 | T430: 01012025081220451 | U430: 凤形路凤形商住楼3幢1012室房地权证宁字第00044836号,宁国用（2012）第787号 | V430: 皖（2018）宁国市不动产证明第0000804号 | W430: 2047/5/31 | X430: 41.4 | Y430: 平方米 | Z430: 是 | AA430: 安徽省 | AB430: 宣城市 | AC430: 宁国市 | AD430: 凤形路凤形商住楼3幢1012室 | AE430: 第一顺位 | AF430: 90 | AG430: 外部评估 | AH430: 43710 | AI430: 28.98 | AJ430: 否 | AL430: 不涉及 | AO430: 刘伟(安徽分公司),姜碧霏,张乐群,张梅,戴宁,牛琪,许之玮,赵艳(安徽分公司),郑蓓,齐奥 | AP430: 安徽分公司 | AQ430: 12190067 | AR430: 收购安徽建行对安徽大平油脂公司等16户企业持有的金融不良债权项目 | AS430: 43791 | AU430: 11001 | AV430: 已剔重 | AX430: =COUNTIFS(拍卖数据!E:E,AA430,拍卖数据!F:F,AB430,拍卖数据!O:O,O430,拍卖数据!P:P,">"&X430*0.8,拍卖数据!P:P,"<"&X430*1.2) -> 1 | AY430: =COUNTIFS(拍卖数据!E:E,AA430,拍卖数据!F:F,AB430,拍卖数据!O:O,O430,拍卖数据!AN:AN,"机构",拍卖数据!P:P,">"&X430*0.8,拍卖数据!P:P,"<"&X430*1.2) -> 0 | AZ430: =COUNTIFS(拍卖数据!E:E,AA430,拍卖数据!F:F,AB430,拍卖数据!G:G,AC430,拍卖数据!O:O,O430,拍卖数据!AN:AN,"机构",拍卖数据!P:P,">"&X430*0.8,拍卖数据!P:P,"<"&X430*1.2) -> 0
A431: 39525 | B431: 12200049000100000001 | C431: 否 | D431: 安庆健帆贸易有限公司 | E431: 建材批发 | F431: 990.4764 | G431: 51.359118 | H431: 0 | I431: 0 | J431: 1041.8355 | K431: 抵押,质押,保证 | M431: 558.28214 | N431: 现房 | O431: 工业用房 | P431: 标准工业厂房及仓储 | Q431: 新建 | R431: 胡徐结,刘义琴 | S431: 342827197105186338,342524197505212026 | T431: 01012025081220503 | U431: 开发区 1.3 平方里工业园内欣荣油脂公司3#科研综合楼三层房地权证宜字第50090891号,房地权证宜字第50090892号,庆国用（2012）403号 | V431: 房地产证宜字第5049066号,2013年第726号,皖（2017）宜高抵不动产证明第6008304号 | W431: 2062/5/14 | X431: 922.21 | Y431: 平方米 | Z431: 是 | AA431: 安徽省 | AB431: 安庆市 | AC431: 宜秀区 | AD431: 开发区 1.3 平方里工业园内欣荣油脂公司 3#科研综合楼三层 | AE431: 第一顺位 | AF431: 1300 | AG431: 外部评估 | AH431: 43987 | AI431: 258.22 | AJ431: 否 | AL431: 不涉及 | AO431: 刘伟(安徽分公司),姜碧霏,张乐群,张梅,戴宁,牛琪,许之玮,赵艳(安徽分公司),郑蓓,齐奥 | AP431: 安徽分公司 | AQ431: 12200049 | AR431: 收购安徽交行对安庆健帆贸易有限公司等12户企业持有的金融不良债权项目 | AS431: 44010 | AU431: 11001 | AV431: 已剔重 | AX431: =COUNTIFS(拍卖数据!E:E,AA431,拍卖数据!F:F,AB431,拍卖数据!O:O,O431,拍卖数据!P:P,">"&X431*0.8,拍卖数据!P:P,"<"&X431*1.2) -> 0 | AY431: =COUNTIFS(拍卖数据!E:E,AA431,拍卖数据!F:F,AB431,拍卖数据!O:O,O431,拍卖数据!AN:AN,"机构",拍卖数据!P:P,">"&X431*0.8,拍卖数据!P:P,"<"&X431*1.2) -> 0 | AZ431: =COUNTIFS(拍卖数据!E:E,AA431,拍卖数据!F:F,AB431,拍卖数据!G:G,AC431,拍卖数据!O:O,O431,拍卖数据!AN:AN,"机构",拍卖数据!P:P,">"&X431*0.8,拍卖数据!P:P,"<"&X431*1.2) -> 0
...

Sheet Sheet1
B2: 要求：
B3: 发邮件，点击链接跳转
